Workbook

Sheet Lucros aos Sócios
A1: Código | B1: CNPJ | C1: Razão Social | D1: Tipo de Aferiação | E1: CPF / CNPJ | F1: Sócios | G1: Participação | H1: Lucros Distribuídos
A2: 106 | B2: =VLOOKUP(A2,Empresas!A:B,2,0) -> 04.431.460/0001-25 | C2: =VLOOKUP(B2,Empresas!B:C,2,0) -> 04.431.460 Ramiro Duenas Aranzabal | D2: =VLOOKUP(C2,'[1]Controle Distribuição de Lucros'!$C$1:$G$357,5,0) -> #N/A | E2: 217.925.868-25 | F2: Ramiro DuenasAranzal | G2: 1 | H2: =IF(D2="Contabilidade Aproximada",(VLOOKUP(C2,'Apuração Contabilidade Aproxima'!$C$1:$M$357,11,0)*G2),IF(D2="Distribuição por Presunção",(VLOOKUP(C2,'[1]Controle Distribuição de Lucros'!$C$1:$Q$357,15)*'Lucros aos Sócios'!G2),IF(D2="Contabilidade"," ",0))) -> #N/A
A3: 119 | B3: =VLOOKUP(A3,Empresas!A:B,2,0) -> 27.541.980/0001-96 | C3: =VLOOKUP(B3,Empresas!B:C,2,0) -> 4.Com Serviços Empresariais Ltda | D3: =VLOOKUP(C3,'[1]Controle Distribuição de Lucros'!$C$1:$G$357,5,0) -> #N/A | E3: 945.266.568-87 | F3: Milton Munhoz | G3: 0.5 | H3: =IF(D3="Contabilidade Aproximada",(VLOOKUP(C3,'Apuração Contabilidade Aproxima'!$C$1:$M$357,11,0)*G3),IF(D3="Distribuição por Presunção",(VLOOKUP(C3,'[1]Controle Distribuição de Lucros'!$C$1:$Q$357,15)*'Lucros aos Sócios'!G3),IF(D3="Contabilidade"," ",0))) -> #N/A
A4: 119 | B4: =VLOOKUP(A4,Empresas!A:B,2,0) -> 27.541.980/0001-96 | C4: =VLOOKUP(B4,Empresas!B:C,2,0) -> 4.Com Serviços Empresariais Ltda | D4: =VLOOKUP(C4,'[1]Controle Distribuição de Lucros'!$C$1:$G$357,5,0) -> #N/A | E4: 033.786.148-03 | F4: Selma Maria de Avellar | G4: 0.5 | H4: =IF(D4="Contabilidade Aproximada",(VLOOKUP(C4,'Apuração Contabilidade Aproxima'!$C$1:$M$357,11,0)*G4),IF(D4="Distribuição por Presunção",(VLOOKUP(C4,'[1]Controle Distribuição de Lucros'!$C$1:$Q$357,15)*'Lucros aos Sócios'!G4),IF(D4="Contabilidade"," ",0))) -> #N/A
A5: 415 | B5: =VLOOKUP(A5,Empresas!A:B,2,0) -> 42.360.609/0001-11 | C5: =VLOOKUP(B5,Empresas!B:C,2,0) -> 42.360.609 Dener Mendonça de Souza | D5: =VLOOKUP(C5,'[1]Controle Distribuição de Lucros'!$C$1:$G$357,5,0) -> #N/A | E5: 359.623.988-58 | F5: Dener Mendonca de Souza | G5: 1 | H5: =IF(D5="Contabilidade Aproximada",(VLOOKUP(C5,'Apuração Contabilidade Aproxima'!$C$1:$M$357,11,0)*G5),IF(D5="Distribuição por Presunção",(VLOOKUP(C5,'[1]Controle Distribuição de Lucros'!$C$1:$Q$357,15)*'Lucros aos Sócios'!G5),IF(D5="Contabilidade"," ",0))) -> #N/A
A6: 218 | B6: =VLOOKUP(A6,Empresas!A:B,2,0) -> 43.436.474/0001-93 | C6: =VLOOKUP(B6,Empresas!B:C,2,0) -> 43.436.474 Maria Clara Tomé Garcia | D6: =VLOOKUP(C6,'[1]Controle Distribuição de Lucros'!$C$1:$G$357,5,0) -> #N/A | E6: 390.807.018-07 | F6: Maria Clara Tome Garcia | G6: 1 | H6: =IF(D6="Contabilidade Aproximada",(VLOOKUP(C6,'Apuração Contabilidade Aproxima'!$C$1:$M$357,11,0)*G6),IF(D6="Distribuição por Presunção",(VLOOKUP(C6,'[1]Controle Distribuição de Lucros'!$C$1:$Q$357,15)*'Lucros aos Sócios'!G6),IF(D6="Contabilidade"," ",0))) -> #N/A
A7: 628 | B7: =VLOOKUP(A7,Empresas!A:B,2,0) -> 43.959.791/0001-94 | C7: =VLOOKUP(B7,Empresas!B:C,2,0) -> 43.959.791 Ana Isabela Pithan Maraschin | D7: =VLOOKUP(C7,'[1]Controle Distribuição de Lucros'!$C$1:$G$357,5,0) -> #N/A | E7: 060.646.018-76 | F7: Ana Isabela Pithan Maraschin | G7: 1 | H7: =IF(D7="Contabilidade Aproximada",(VLOOKUP(C7,'Apuração Contabilidade Aproxima'!$C$1:$M$357,11,0)*G7),IF(D7="Distribuição por Presunção",(VLOOKUP(C7,'[1]Controle Distribuição de Lucros'!$C$1:$Q$357,15)*'Lucros aos Sócios'!G7),IF(D7="Contabilidade"," ",0))) -> #N/A
A8: 227 | B8: =VLOOKUP(A8,Empresas!A:B,2,0) -> 44.645.259/0001-65 | C8: =VLOOKUP(B8,Empresas!B:C,2,0) -> 44.645.259 Rebeca Brito Cardoso | D8: =VLOOKUP(C8,'[1]Controle Distribuição de Lucros'!$C$1:$G$357,5,0) -> #N/A | E8: 416.773.648-90 | F8: Rebeca Brito Cardoso | G8: 1 | H8: =IF(D8="Contabilidade Aproximada",(VLOOKUP(C8,'Apuração Contabilidade Aproxima'!$C$1:$M$357,11,0)*G8),IF(D8="Distribuição por Presunção",(VLOOKUP(C8,'[1]Controle Distribuição de Lucros'!$C$1:$Q$357,15)*'Lucros aos Sócios'!G8),IF(D8="Contabilidade"," ",0))) -> #N/A
A9: 359 | B9: =VLOOKUP(A9,Empresas!A:B,2,0) -> 04.362.429/0001-80 | C9: =VLOOKUP(B9,Empresas!B:C,2,0) -> 4CS Serviços Ltda | D9: =VLOOKUP(C9,'[1]Controle Distribuição de Lucros'!$C$1:$G$357,5,0) -> #N/A | E9: 373.682.718-00 | F9: Daniel Gomes Pereira Assunção | G9: 1 | H9: =IF(D9="Contabilidade Aproximada",(VLOOKUP(C9,'Apuração Contabilidade Aproxima'!$C$1:$M$357,11,0)*G9),IF(D9="Distribuição por Presunção",(VLOOKUP(C9,'[1]Controle Distribuição de Lucros'!$C$1:$Q$357,15)*'Lucros aos Sócios'!G9),IF(D9="Contabilidade"," ",0))) -> #N/A
A10: 638 | B10: =VLOOKUP(A10,Empresas!A:B,2,0) -> 51.957.545/0001-21 | C10: =VLOOKUP(B10,Empresas!B:C,2,0) -> 51.957.545 Marjorie Abdallah | D10: =VLOOKUP(C10,'[1]Controle Distribuição de Lucros'!$C$1:$G$357,5,0) -> #N/A | E10: 44728556824 | F10: Marjorie Abdallah | G10: 1 | H10: =IF(D10="Contabilidade Aproximada",(VLOOKUP(C10,'Apuração Contabilidade Aproxima'!$C$1:$M$357,11,0)*G10),IF(D10="Distribuição por Presunção",(VLOOKUP(C10,'[1]Controle Distribuição de Lucros'!$C$1:$Q$357,15)*'Lucros aos Sócios'!G10),IF(D10="Contabilidade"," ",0))) -> #N/A
A11: 437 | B11: =VLOOKUP(A11,Empresas!A:B,2,0) -> 53.494.930/0001-05 | C11: =VLOOKUP(B11,Empresas!B:C,2,0) -> 53.494.930 Gabriela Afonso Prado | D11: =VLOOKUP(C11,'[1]Controle Distribuição de Lucros'!$C$1:$G$357,5,0) -> #N/A | E11: 855.893.301-49 | F11: Gabriela Afonso Prado | G11: 1 | H11: =IF(D11="Contabilidade Aproximada",(VLOOKUP(C11,'Apuração Contabilidade Aproxima'!$C$1:$M$357,11,0)*G11),IF(D11="Distribuição por Presunção",(VLOOKUP(C11,'[1]Controle Distribuição de Lucros'!$C$1:$Q$357,15)*'Lucros aos Sócios'!G11),IF(D11="Contabilidade"," ",0))) -> #N/A
A12: 461 | B12: =VLOOKUP(A12,Empresas!A:B,2,0) -> 54.535.015/0001-83 | C12: =VLOOKUP(B12,Empresas!B:C,2,0) -> Ada Maria Fraulo Pires | D12: =VLOOKUP(C12,'[1]Controle Distribuição de Lucros'!$C$1:$G$357,5,0) -> #N/A | E12: 297.312.228-71 | F12: Ada Maria Fraulo Pires | G12: 1 | H12: =IF(D12="Contabilidade Aproximada",(VLOOKUP(C12,'Apuração Contabilidade Aproxima'!$C$1:$M$357,11,0)*G12),IF(D12="Distribuição por Presunção",(VLOOKUP(C12,'[1]Controle Distribuição de Lucros'!$C$1:$Q$357,15)*'Lucros aos Sócios'!G12),IF(D12="Contabilidade"," ",0))) -> #N/A
A13: 525 | B13: =VLOOKUP(A13,Empresas!A:B,2,0) -> 58.344.129/0001-05 | C13: =VLOOKUP(B13,Empresas!B:C,2,0) -> 58.344.129 Gilda Maria de Lima Roberto | D13: =VLOOKUP(C13,'[1]Controle Distribuição de Lucros'!$C$1:$G$357,5,0) -> #N/A | E13: 270.967.878-01 | F13: Gilda Maria de Lima Roberto | G13: 1 | H13: =IF(D13="Contabilidade Aproximada",(VLOOKUP(C13,'Apuração Contabilidade Aproxima'!$C$1:$M$357,11,0)*G13),IF(D13="Distribuição por Presunção",(VLOOKUP(C13,'[1]Controle Distribuição de Lucros'!$C$1:$Q$357,15)*'Lucros aos Sócios'!G13),IF(D13="Contabilidade"," ",0))) -> #N/A
A14: 608 | B14: =VLOOKUP(A14,Empresas!A:B,2,0) -> 13.581.219/0001-73 | C14: =VLOOKUP(B14,Empresas!B:C,2,0) -> A & V Marques Imóveis Ltda | D14: =VLOOKUP(C14,'[1]Controle Distribuição de Lucros'!$C$1:$G$357,5,0) -> #N/A | E14: 29477113867 | F14: Vagner Luis Marques | G14: 1 | H14: =IF(D14="Contabilidade Aproximada",(VLOOKUP(C14,'Apuração Contabilidade Aproxima'!$C$1:$M$357,11,0)*G14),IF(D14="Distribuição por Presunção",(VLOOKUP(C14,'[1]Controle Distribuição de Lucros'!$C$1:$Q$357,15)*'Lucros aos Sócios'!G14),IF(D14="Contabilidade"," ",0))) -> #N/A
A15: 34 | B15: =VLOOKUP(A15,Empresas!A:B,2,0) -> 22.189.167/0001-85 | C15: =VLOOKUP(B15,Empresas!B:C,2,0) -> A Galeria Artes Presentes Jóias Design Rocym Ltda | D15: =VLOOKUP(C15,'[1]Controle Distribuição de Lucros'!$C$1:$G$357,5,0) -> #N/A | E15: 082.807.148-98 | F15: Ronaldo Szaniecki | G15: 1 | H15: =IF(D15="Contabilidade Aproximada",(VLOOKUP(C15,'Apuração Contabilidade Aproxima'!$C$1:$M$357,11,0)*G15),IF(D15="Distribuição por Presunção",(VLOOKUP(C15,'[1]Controle Distribuição de Lucros'!$C$1:$Q$357,15)*'Lucros aos Sócios'!G15),IF(D15="Contabilidade"," ",0))) -> #N/A
A16: 523 | B16: =VLOOKUP(A16,Empresas!A:B,2,0) -> 11.360.241/0001-68 | C16: =VLOOKUP(B16,Empresas!B:C,2,0) -> A. de S. Cafcalas | D16: =VLOOKUP(C16,'[1]Controle Distribuição de Lucros'!$C$1:$G$357,5,0) -> #N/A | E16: 24787045873 | F16: Alexandre de Siqueira Cafcalas | G16: 1 | H16: =IF(D16="Contabilidade Aproximada",(VLOOKUP(C16,'Apuração Contabilidade Aproxima'!$C$1:$M$357,11,0)*G16),IF(D16="Distribuição por Presunção",(VLOOKUP(C16,'[1]Controle Distribuição de Lucros'!$C$1:$Q$357,15)*'Lucros aos Sócios'!G16),IF(D16="Contabilidade"," ",0))) -> #N/A
A17: 587 | B17: =VLOOKUP(A17,Empresas!A:B,2,0) -> 61.203.201/0001-80 | C17: =VLOOKUP(B17,Empresas!B:C,2,0) -> A2M Ltda | D17: =VLOOKUP(C17,'[1]Controle Distribuição de Lucros'!$C$1:$G$357,5,0) -> #N/A | E17: 51229283803 | F17: Fred Ades | G17: 0.5 | H17: =IF(D17="Contabilidade Aproximada",(VLOOKUP(C17,'Apuração Contabilidade Aproxima'!$C$1:$M$357,11,0)*G17),IF(D17="Distribuição por Presunção",(VLOOKUP(C17,'[1]Controle Distribuição de Lucros'!$C$1:$Q$357,15)*'Lucros aos Sócios'!G17),IF(D17="Contabilidade"," ",0))) -> #N/A
A18: 587 | B18: =VLOOKUP(A18,Empresas!A:B,2,0) -> 61.203.201/0001-80 | C18: =VLOOKUP(B18,Empresas!B:C,2,0) -> A2M Ltda | D18: =VLOOKUP(C18,'[1]Controle Distribuição de Lucros'!$C$1:$G$357,5,0) -> #N/A | E18: 50195368819 | F18: Jean Richard Mansur | G18: 0.5 | H18: =IF(D18="Contabilidade Aproximada",(VLOOKUP(C18,'Apuração Contabilidade Aproxima'!$C$1:$M$357,11,0)*G18),IF(D18="Distribuição por Presunção",(VLOOKUP(C18,'[1]Controle Distribuição de Lucros'!$C$1:$Q$357,15)*'Lucros aos Sócios'!G18),IF(D18="Contabilidade"," ",0))) -> #N/A
A19: 225 | B19: =VLOOKUP(A19,Empresas!A:B,2,0) -> 04.438.239/0001-07 | C19: =VLOOKUP(B19,Empresas!B:C,2,0) -> AGM Representações Comerciais Ltda | D19: =VLOOKUP(C19,'[1]Controle Distribuição de Lucros'!$C$1:$G$357,5,0) -> #N/A | E19: 29351733840 | F19: Andre Berti Sampaio Xavier | G19: 0.93 | H19: =IF(D19="Contabilidade Aproximada",(VLOOKUP(C19,'Apuração Contabilidade Aproxima'!$C$1:$M$357,11,0)*G19),IF(D19="Distribuição por Presunção",(VLOOKUP(C19,'[1]Controle Distribuição de Lucros'!$C$1:$Q$357,15)*'Lucros aos Sócios'!G19),IF(D19="Contabilidade"," ",0))) -> #N/A
A20: 225 | B20: =VLOOKUP(A20,Empresas!A:B,2,0) -> 04.438.239/0001-07 | C20: =VLOOKUP(B20,Empresas!B:C,2,0) -> AGM Representações Comerciais Ltda | D20: =VLOOKUP(C20,'[1]Controle Distribuição de Lucros'!$C$1:$G$357,5,0) -> #N/A | E20: 30502745819 | F20: Fernanda Diniz Silva | G20: 0.07 | H20: =IF(D20="Contabilidade Aproximada",(VLOOKUP(C20,'Apuração Contabilidade Aproxima'!$C$1:$M$357,11,0)*G20),IF(D20="Distribuição por Presunção",(VLOOKUP(C20,'[1]Controle Distribuição de Lucros'!$C$1:$Q$357,15)*'Lucros aos Sócios'!G20),IF(D20="Contabilidade"," ",0))) -> #N/A
A21: 572 | B21: =VLOOKUP(A21,Empresas!A:B,2,0) -> 44.114.755/0001-92 | C21: =VLOOKUP(B21,Empresas!B:C,2,0) -> AGR Tubos Conexões e Válvulas Ltda | D21: =VLOOKUP(C21,'[1]Controle Distribuição de Lucros'!$C$1:$G$357,5,0) -> #N/A | E21: 333.804.098-98 | F21: Francisca Regis da Silva | G21: 1 | H21: =IF(D21="Contabilidade Aproximada",(VLOOKUP(C21,'Apuração Contabilidade Aproxima'!$C$1:$M$357,11,0)*G21),IF(D21="Distribuição por Presunção",(VLOOKUP(C21,'[1]Controle Distribuição de Lucros'!$C$1:$Q$357,15)*'Lucros aos Sócios'!G21),IF(D21="Contabilidade"," ",0))) -> #N/A
A22: 597 | B22: =VLOOKUP(A22,Empresas!A:B,2,0) -> 33.023.255/0001-29 | C22: =VLOOKUP(B22,Empresas!B:C,2,0) -> Alan W de O Lima Tecnologia da Informação | D22: =VLOOKUP(C22,'[1]Controle Distribuição de Lucros'!$C$1:$G$357,5,0) -> #N/A | E22: 281.763.258-30 | F22: Alan William de Oliveira Lima | G22: 1 | H22: =IF(D22="Contabilidade Aproximada",(VLOOKUP(C22,'Apuração Contabilidade Aproxima'!$C$1:$M$357,11,0)*G22),IF(D22="Distribuição por Presunção",(VLOOKUP(C22,'[1]Controle Distribuição de Lucros'!$C$1:$Q$357,15)*'Lucros aos Sócios'!G22),IF(D22="Contabilidade"," ",0))) -> #N/A
A23: 617 | B23: =VLOOKUP(A23,Empresas!A:B,2,0) -> 58.717.889/0001-02 | C23: =VLOOKUP(B23,Empresas!B:C,2,0) -> Ale Holding Participações e Negócios Ltda | D23: =VLOOKUP(C23,'[1]Controle Distribuição de Lucros'!$C$1:$G$357,5,0) -> #N/A | E23: 395.549.548-59 | F23: Luis Henrique Ale Cezar | G23: 1 | H23: =IF(D23="Contabilidade Aproximada",(VLOOKUP(C23,'Apuração Contabilidade Aproxima'!$C$1:$M$357,11,0)*G23),IF(D23="Distribuição por Presunção",(VLOOKUP(C23,'[1]Controle Distribuição de Lucros'!$C$1:$Q$357,15)*'Lucros aos Sócios'!G23),IF(D23="Contabilidade"," ",0))) -> #N/A
A24: 303 | B24: =VLOOKUP(A24,Empresas!A:B,2,0) -> 02.864.188/0001-41 | C24: =VLOOKUP(B24,Empresas!B:C,2,0) -> Alexandre Sgreccia | D24: =VLOOKUP(C24,'[1]Controle Distribuição de Lucros'!$C$1:$G$357,5,0) -> #N/A | E24: 528.843.098-53 | F24: Alexandre Sgreccia | G24: 1 | H24: =IF(D24="Contabilidade Aproximada",(VLOOKUP(C24,'Apuração Contabilidade Aproxima'!$C$1:$M$357,11,0)*G24),IF(D24="Distribuição por Presunção",(VLOOKUP(C24,'[1]Controle Distribuição de Lucros'!$C$1:$Q$357,15)*'Lucros aos Sócios'!G24),IF(D24="Contabilidade"," ",0))) -> #N/A
A25: 230 | B25: =VLOOKUP(A25,Empresas!A:B,2,0) -> 04.746.127/0001-05 | C25: =VLOOKUP(B25,Empresas!B:C,2,0) -> Alexandre Silva Voza | D25: =VLOOKUP(C25,'[1]Controle Distribuição de Lucros'!$C$1:$G$357,5,0) -> #N/A | E25: 12558085867 | F25: Alexandre Silva Voza | G25: 1 | H25: =IF(D25="Contabilidade Aproximada",(VLOOKUP(C25,'Apuração Contabilidade Aproxima'!$C$1:$M$357,11,0)*G25),IF(D25="Distribuição por Presunção",(VLOOKUP(C25,'[1]Controle Distribuição de Lucros'!$C$1:$Q$357,15)*'Lucros aos Sócios'!G25),IF(D25="Contabilidade"," ",0))) -> #N/A
A26: 370 | B26: =VLOOKUP(A26,Empresas!A:B,2,0) -> 37.140.411/0001-92 | C26: =VLOOKUP(B26,Empresas!B:C,2,0) -> Allora Construtora e Incorporadora Ltda | D26: =VLOOKUP(C26,'[1]Controle Distribuição de Lucros'!$C$1:$G$357,5,0) -> #N/A | E26: 870.580.144-34 | F26: Gustavo Lopes Berard | G26: 1 | H26: =IF(D26="Contabilidade Aproximada",(VLOOKUP(C26,'Apuração Contabilidade Aproxima'!$C$1:$M$357,11,0)*G26),IF(D26="Distribuição por Presunção",(VLOOKUP(C26,'[1]Controle Distribuição de Lucros'!$C$1:$Q$357,15)*'Lucros aos Sócios'!G26),IF(D26="Contabilidade"," ",0))) -> #N/A
A27: 578 | B27: =VLOOKUP(A27,Empresas!A:B,2,0) -> 13.314.231/0001-11 | C27: =VLOOKUP(B27,Empresas!B:C,2,0) -> Alpha Entretenimento e Lazer Ltda | D27: =VLOOKUP(C27,'[1]Controle Distribuição de Lucros'!$C$1:$G$357,5,0) -> #N/A | E27: 269.649.348-04 | F27: João Aprobato Neto | G27: 0.7 | H27: =IF(D27="Contabilidade Aproximada",(VLOOKUP(C27,'Apuração Contabilidade Aproxima'!$C$1:$M$357,11,0)*G27),IF(D27="Distribuição por Presunção",(VLOOKUP(C27,'[1]Controle Distribuição de Lucros'!$C$1:$Q$357,15)*'Lucros aos Sócios'!G27),IF(D27="Contabilidade"," ",0))) -> #N/A
A28: 578 | B28: =VLOOKUP(A28,Empresas!A:B,2,0) -> 13.314.231/0001-11 | C28: =VLOOKUP(B28,Empresas!B:C,2,0) -> Alpha Entretenimento e Lazer Ltda | D28: =VLOOKUP(C28,'[1]Controle Distribuição de Lucros'!$C$1:$G$357,5,0) -> #N/A | E28: 285.321.248-36 | F28: Flaviane Gomes Assunção Aprobato | G28: 0.3 | H28: =IF(D28="Contabilidade Aproximada",(VLOOKUP(C28,'Apuração Contabilidade Aproxima'!$C$1:$M$357,11,0)*G28),IF(D28="Distribuição por Presunção",(VLOOKUP(C28,'[1]Controle Distribuição de Lucros'!$C$1:$Q$357,15)*'Lucros aos Sócios'!G28),IF(D28="Contabilidade"," ",0))) -> #N/A
A29: 302 | B29: =VLOOKUP(A29,Empresas!A:B,2,0) -> 01.665.434/0001-73 | C29: =VLOOKUP(B29,Empresas!B:C,2,0) -> Alphaville Comercial Ltda | D29: =VLOOKUP(C29,'[1]Controle Distribuição de Lucros'!$C$1:$G$357,5,0) -> #N/A | E29: 14843851876 | F29: Fabiana Romani Vieira | G29: 0.5 | H29: =IF(D29="Contabilidade Aproximada",(VLOOKUP(C29,'Apuração Contabilidade Aproxima'!$C$1:$M$357,11,0)*G29),IF(D29="Distribuição por Presunção",(VLOOKUP(C29,'[1]Controle Distribuição de Lucros'!$C$1:$Q$357,15)*'Lucros aos Sócios'!G29),IF(D29="Contabilidade"," ",0))) -> #N/A
A30: 302 | B30: =VLOOKUP(A30,Empresas!A:B,2,0) -> 01.665.434/0001-73 | C30: =VLOOKUP(B30,Empresas!B:C,2,0) -> Alphaville Comercial Ltda | D30: =VLOOKUP(C30,'[1]Controle Distribuição de Lucros'!$C$1:$G$357,5,0) -> #N/A | E30: 16505634851 | F30: Luis Gustavo Ozorio Valentim | G30: 0.5 | H30: =IF(D30="Contabilidade Aproximada",(VLOOKUP(C30,'Apuração Contabilidade Aproxima'!$C$1:$M$357,11,0)*G30),IF(D30="Distribuição por Presunção",(VLOOKUP(C30,'[1]Controle Distribuição de Lucros'!$C$1:$Q$357,15)*'Lucros aos Sócios'!G30),IF(D30="Contabilidade"," ",0))) -> #N/A
A31: 376 | B31: =VLOOKUP(A31,Empresas!A:B,2,0) -> 09.086.104/0001-35 | C31: =VLOOKUP(B31,Empresas!B:C,2,0) -> Américo Suriano e Companhia Ltda | D31: =VLOOKUP(C31,'[1]Controle Distribuição de Lucros'!$C$1:$G$357,5,0) -> #N/A | E31: 069.248.158-39 | F31: Americo Suriano Neto | G31: 0.9998 | H31: =IF(D31="Contabilidade Aproximada",(VLOOKUP(C31,'Apuração Contabilidade Aproxima'!$C$1:$M$357,11,0)*G31),IF(D31="Distribuição por Presunção",(VLOOKUP(C31,'[1]Controle Distribuição de Lucros'!$C$1:$Q$357,15)*'Lucros aos Sócios'!G31),IF(D31="Contabilidade"," ",0))) -> #N/A
A32: 376 | B32: =VLOOKUP(A32,Empresas!A:B,2,0) -> 09.086.104/0001-35 | C32: =VLOOKUP(B32,Empresas!B:C,2,0) -> Américo Suriano e Companhia Ltda | D32: =VLOOKUP(C32,'[1]Controle Distribuição de Lucros'!$C$1:$G$357,5,0) -> #N/A | E32: 319.004.148-21 | F32: Michelle de Lacerda Castor | G32: 0.0001 | H32: =IF(D32="Contabilidade Aproximada",(VLOOKUP(C32,'Apuração Contabilidade Aproxima'!$C$1:$M$357,11,0)*G32),IF(D32="Distribuição por Presunção",(VLOOKUP(C32,'[1]Controle Distribuição de Lucros'!$C$1:$Q$357,15)*'Lucros aos Sócios'!G32),IF(D32="Contabilidade"," ",0))) -> #N/A
A33: 376 | B33: =VLOOKUP(A33,Empresas!A:B,2,0) -> 09.086.104/0001-35 | C33: =VLOOKUP(B33,Empresas!B:C,2,0) -> Américo Suriano e Companhia Ltda | D33: =VLOOKUP(C33,'[1]Controle Distribuição de Lucros'!$C$1:$G$357,5,0) -> #N/A | E33: 368.579.708-58 | F33: Monica Lacerda Suriano | G33: 0.0001 | H33: =IF(D33="Contabilidade Aproximada",(VLOOKUP(C33,'Apuração Contabilidade Aproxima'!$C$1:$M$357,11,0)*G33),IF(D33="Distribuição por Presunção",(VLOOKUP(C33,'[1]Controle Distribuição de Lucros'!$C$1:$Q$357,15)*'Lucros aos Sócios'!G33),IF(D33="Contabilidade"," ",0))) -> #N/A
A34: 576 | B34: =VLOOKUP(A34,Empresas!A:B,2,0) -> 49.343.692/0001-60 | C34: =VLOOKUP(B34,Empresas!B:C,2,0) -> Ápice Artes Gráficas Ltda | D34: =VLOOKUP(C34,'[1]Controle Distribuição de Lucros'!$C$1:$G$357,5,0) -> #N/A | E34: 039.267.368-10 | F34: Anna Lia Grandi Wosniak | G34: 0.334 | H34: =IF(D34="Contabilidade Aproximada",(VLOOKUP(C34,'Apuração Contabilidade Aproxima'!$C$1:$M$357,11,0)*G34),IF(D34="Distribuição por Presunção",(VLOOKUP(C34,'[1]Controle Distribuição de Lucros'!$C$1:$Q$357,15)*'Lucros aos Sócios'!G34),IF(D34="Contabilidade"," ",0))) -> #N/A
A35: 576 | B35: =VLOOKUP(A35,Empresas!A:B,2,0) -> 49.343.692/0001-60 | C35: =VLOOKUP(B35,Empresas!B:C,2,0) -> Ápice Artes Gráficas Ltda | D35: =VLOOKUP(C35,'[1]Controle Distribuição de Lucros'!$C$1:$G$357,5,0) -> #N/A | E35: 878.137.778-91 | F35: Reinaldo Wosniak | G35: 0.666 | H35: =IF(D35="Contabilidade Aproximada",(VLOOKUP(C35,'Apuração Contabilidade Aproxima'!$C$1:$M$357,11,0)*G35),IF(D35="Distribuição por Presunção",(VLOOKUP(C35,'[1]Controle Distribuição de Lucros'!$C$1:$Q$357,15)*'Lucros aos Sócios'!G35),IF(D35="Contabilidade"," ",0))) -> #N/A
A36: 61 | B36: =VLOOKUP(A36,Empresas!A:B,2,0) -> 03.338.180/0001-04 | C36: =VLOOKUP(B36,Empresas!B:C,2,0) -> Aprobato Neto Contabilidade e Apoio Empresarial Ltda | D36: =VLOOKUP(C36,'[1]Controle Distribuição de Lucros'!$C$1:$G$357,5,0) -> #N/A | E36: 269.649.348-04 | F36: João Aprobato Neto | G36: 1 | H36: =IF(D36="Contabilidade Aproximada",(VLOOKUP(C36,'Apuração Contabilidade Aproxima'!$C$1:$M$357,11,0)*G36),IF(D36="Distribuição por Presunção",(VLOOKUP(C36,'[1]Controle Distribuição de Lucros'!$C$1:$Q$357,15)*'Lucros aos Sócios'!G36),IF(D36="Contabilidade"," ",0))) -> #N/A
A37: 972 | B37: =VLOOKUP(A37,Empresas!A:B,2,0) -> 00.000.904/0001-17 | C37: =VLOOKUP(B37,Empresas!B:C,2,0) -> Aprobato Neto Perícias Técnicas Ltda | D37: =VLOOKUP(C37,'[1]Controle Distribuição de Lucros'!$C$1:$G$357,5,0) -> #N/A | E37: 269.649.348-04 | F37: João Aprobato Neto | G37: 0.825 | H37: =IF(D37="Contabilidade Aproximada",(VLOOKUP(C37,'Apuração Contabilidade Aproxima'!$C$1:$M$357,11,0)*G37),IF(D37="Distribuição por Presunção",(VLOOKUP(C37,'[1]Controle Distribuição de Lucros'!$C$1:$Q$357,15)*'Lucros aos Sócios'!G37),IF(D37="Contabilidade"," ",0))) -> #N/A
A38: 972 | B38: =VLOOKUP(A38,Empresas!A:B,2,0) -> 00.000.904/0001-17 | C38: =VLOOKUP(B38,Empresas!B:C,2,0) -> Aprobato Neto Perícias Técnicas Ltda | D38: =VLOOKUP(C38,'[1]Controle Distribuição de Lucros'!$C$1:$G$357,5,0) -> #N/A | E38: 294.594.188-05 | F38: Carina Turatti Farina Butuem | G38: 0.175 | H38: =IF(D38="Contabilidade Aproximada",(VLOOKUP(C38,'Apuração Contabilidade Aproxima'!$C$1:$M$357,11,0)*G38),IF(D38="Distribuição por Presunção",(VLOOKUP(C38,'[1]Controle Distribuição de Lucros'!$C$1:$Q$357,15)*'Lucros aos Sócios'!G38),IF(D38="Contabilidade"," ",0))) -> #N/A
A39: 440 | B39: =VLOOKUP(A39,Empresas!A:B,2,0) -> 71.912.349/0001-48 | C39: =VLOOKUP(B39,Empresas!B:C,2,0) -> Arakaki Enterprise Ltda | D39: =VLOOKUP(C39,'[1]Controle Distribuição de Lucros'!$C$1:$G$357,5,0) -> #N/A | E39: 324.904.628-06 | F39: Suzimeire Arakaki | G39: 0.5 | H39: =IF(D39="Contabilidade Aproximada",(VLOOKUP(C39,'Apuração Contabilidade Aproxima'!$C$1:$M$357,11,0)*G39),IF(D39="Distribuição por Presunção",(VLOOKUP(C39,'[1]Controle Distribuição de Lucros'!$C$1:$Q$357,15)*'Lucros aos Sócios'!G39),IF(D39="Contabilidade"," ",0))) -> #N/A
A40: 440 | B40: =VLOOKUP(A40,Empresas!A:B,2,0) -> 71.912.349/0001-48 | C40: =VLOOKUP(B40,Empresas!B:C,2,0) -> Arakaki Enterprise Ltda | D40: =VLOOKUP(C40,'[1]Controle Distribuição de Lucros'!$C$1:$G$357,5,0) -> #N/A | E40: 006.679.768-33 | F40: Arlete Mieco Tokunaga Arakaki | G40: 0.5 | H40: =IF(D40="Contabilidade Aproximada",(VLOOKUP(C40,'Apuração Contabilidade Aproxima'!$C$1:$M$357,11,0)*G40),IF(D40="Distribuição por Presunção",(VLOOKUP(C40,'[1]Controle Distribuição de Lucros'!$C$1:$Q$357,15)*'Lucros aos Sócios'!G40),IF(D40="Contabilidade"," ",0))) -> #N/A
A41: 18 | B41: =VLOOKUP(A41,Empresas!A:B,2,0) -> 61.094.660/0001-73 | C41: =VLOOKUP(B41,Empresas!B:C,2,0) -> Aramfactor Utilidades em Arames Ltda | D41: =VLOOKUP(C41,'[1]Controle Distribuição de Lucros'!$C$1:$G$357,5,0) -> #N/A | E41: 1432684817 | F41: Solange Diez Mattos Mattioli | G41: 0.3334 | H41: =IF(D41="Contabilidade Aproximada",(VLOOKUP(C41,'Apuração Contabilidade Aproxima'!$C$1:$M$357,11,0)*G41),IF(D41="Distribuição por Presunção",(VLOOKUP(C41,'[1]Controle Distribuição de Lucros'!$C$1:$Q$357,15)*'Lucros aos Sócios'!G41),IF(D41="Contabilidade"," ",0))) -> #N/A
A42: 18 | B42: =VLOOKUP(A42,Empresas!A:B,2,0) -> 61.094.660/0001-73 | C42: =VLOOKUP(B42,Empresas!B:C,2,0) -> Aramfactor Utilidades em Arames Ltda | D42: =VLOOKUP(C42,'[1]Controle Distribuição de Lucros'!$C$1:$G$357,5,0) -> #N/A | E42: 1111711801 | F42: Magda Diez Mattos Machado | G42: 0.3333 | H42: =IF(D42="Contabilidade Aproximada",(VLOOKUP(C42,'Apuração Contabilidade Aproxima'!$C$1:$M$357,11,0)*G42),IF(D42="Distribuição por Presunção",(VLOOKUP(C42,'[1]Controle Distribuição de Lucros'!$C$1:$Q$357,15)*'Lucros aos Sócios'!G42),IF(D42="Contabilidade"," ",0))) -> #N/A
A43: 18 | B43: =VLOOKUP(A43,Empresas!A:B,2,0) -> 61.094.660/0001-73 | C43: =VLOOKUP(B43,Empresas!B:C,2,0) -> Aramfactor Utilidades em Arames Ltda | D43: =VLOOKUP(C43,'[1]Controle Distribuição de Lucros'!$C$1:$G$357,5,0) -> #N/A | E43: 3566928844 | F43: Sandra Diez Mattos Ramos | G43: 0.3333 | H43: =IF(D43="Contabilidade Aproximada",(VLOOKUP(C43,'Apuração Contabilidade Aproxima'!$C$1:$M$357,11,0)*G43),IF(D43="Distribuição por Presunção",(VLOOKUP(C43,'[1]Controle Distribuição de Lucros'!$C$1:$Q$357,15)*'Lucros aos Sócios'!G43),IF(D43="Contabilidade"," ",0))) -> #N/A
A44: 175 | B44: =VLOOKUP(A44,Empresas!A:B,2,0) -> 39.563.909/0001-93 | C44: =VLOOKUP(B44,Empresas!B:C,2,0) -> Assunção Antunes Corretora de Seguros Ltda | D44: =VLOOKUP(C44,'[1]Controle Distribuição de Lucros'!$C$1:$G$357,5,0) -> #N/A | E44: 9164252663 | F44: Caio Henrique Assuncao Antunes | G44: 1 | H44: =IF(D44="Contabilidade Aproximada",(VLOOKUP(C44,'Apuração Contabilidade Aproxima'!$C$1:$M$357,11,0)*G44),IF(D44="Distribuição por Presunção",(VLOOKUP(C44,'[1]Controle Distribuição de Lucros'!$C$1:$Q$357,15)*'Lucros aos Sócios'!G44),IF(D44="Contabilidade"," ",0))) -> #N/A
A45: 594 | B45: =VLOOKUP(A45,Empresas!A:B,2,0) -> 61.633.486/0001-90 | C45: =VLOOKUP(B45,Empresas!B:C,2,0) -> Astra Tecnologia Ltda | D45: =VLOOKUP(C45,'[1]Controle Distribuição de Lucros'!$C$1:$G$357,5,0) -> #N/A | E45: 017.717.663-60 | F45: Luciano Leal de Sousa | G45: 0.5 | H45: =IF(D45="Contabilidade Aproximada",(VLOOKUP(C45,'Apuração Contabilidade Aproxima'!$C$1:$M$357,11,0)*G45),IF(D45="Distribuição por Presunção",(VLOOKUP(C45,'[1]Controle Distribuição de Lucros'!$C$1:$Q$357,15)*'Lucros aos Sócios'!G45),IF(D45="Contabilidade"," ",0))) -> #N/A
A46: 594 | B46: =VLOOKUP(A46,Empresas!A:B,2,0) -> 61.633.486/0001-90 | C46: =VLOOKUP(B46,Empresas!B:C,2,0) -> Astra Tecnologia Ltda | D46: =VLOOKUP(C46,'[1]Controle Distribuição de Lucros'!$C$1:$G$357,5,0) -> #N/A | E46: 003.427.701-36 | F46: Renato Araújo Sinkere da Cruz | G46: 0.5 | H46: =IF(D46="Contabilidade Aproximada",(VLOOKUP(C46,'Apuração Contabilidade Aproxima'!$C$1:$M$357,11,0)*G46),IF(D46="Distribuição por Presunção",(VLOOKUP(C46,'[1]Controle Distribuição de Lucros'!$C$1:$Q$357,15)*'Lucros aos Sócios'!G46),IF(D46="Contabilidade"," ",0))) -> #N/A
A47: 556 | B47: =VLOOKUP(A47,Empresas!A:B,2,0) -> 37.911.956/0001-55 | C47: =VLOOKUP(B47,Empresas!B:C,2,0) -> Atta Participações Ltda | D47: =VLOOKUP(C47,'[1]Controle Distribuição de Lucros'!$C$1:$G$357,5,0) -> #N/A | E47: 50.145.058/0001-00 | F47: Tixe Participações Ltda | G47: 1 | H47: =IF(D47="Contabilidade Aproximada",(VLOOKUP(C47,'Apuração Contabilidade Aproxima'!$C$1:$M$357,11,0)*G47),IF(D47="Distribuição por Presunção",(VLOOKUP(C47,'[1]Controle Distribuição de Lucros'!$C$1:$Q$357,15)*'Lucros aos Sócios'!G47),IF(D47="Contabilidade"," ",0))) -> #N/A
A48: 615 | B48: =VLOOKUP(A48,Empresas!A:B,2,0) -> 63.531.342/0001-58 | C48: =VLOOKUP(B48,Empresas!B:C,2,0) -> Augusto Ferrari Gestão Patrimonial Ltda | D48: =VLOOKUP(C48,'[1]Controle Distribuição de Lucros'!$C$1:$G$357,5,0) -> #N/A | E48: 147.347.468-00 | F48: César Augusto | G48: 0.4038 | H48: =IF(D48="Contabilidade Aproximada",(VLOOKUP(C48,'Apuração Contabilidade Aproxima'!$C$1:$M$357,11,0)*G48),IF(D48="Distribuição por Presunção",(VLOOKUP(C48,'[1]Controle Distribuição de Lucros'!$C$1:$Q$357,15)*'Lucros aos Sócios'!G48),IF(D48="Contabilidade"," ",0))) -> #N/A
A49: 615 | B49: =VLOOKUP(A49,Empresas!A:B,2,0) -> 63.531.342/0001-58 | C49: =VLOOKUP(B49,Empresas!B:C,2,0) -> Augusto Ferrari Gestão Patrimonial Ltda | D49: =VLOOKUP(C49,'[1]Controle Distribuição de Lucros'!$C$1:$G$357,5,0) -> #N/A | E49: 166.517.868-06 | F49: Patrícia Augusto Ferrari | G49: 0.4038 | H49: =IF(D49="Contabilidade Aproximada",(VLOOKUP(C49,'Apuração Contabilidade Aproxima'!$C$1:$M$357,11,0)*G49),IF(D49="Distribuição por Presunção",(VLOOKUP(C49,'[1]Controle Distribuição de Lucros'!$C$1:$Q$357,15)*'Lucros aos Sócios'!G49),IF(D49="Contabilidade"," ",0))) -> #N/A
A50: 615 | B50: =VLOOKUP(A50,Empresas!A:B,2,0) -> 63.531.342/0001-58 | C50: =VLOOKUP(B50,Empresas!B:C,2,0) -> Augusto Ferrari Gestão Patrimonial Ltda | D50: =VLOOKUP(C50,'[1]Controle Distribuição de Lucros'!$C$1:$G$357,5,0) -> #N/A | E50: 471.888.278-85 | F50: Rafaella Ferrari Augusto | G50: 0.1924 | H50: =IF(D50="Contabilidade Aproximada",(VLOOKUP(C50,'Apuração Contabilidade Aproxima'!$C$1:$M$357,11,0)*G50),IF(D50="Distribuição por Presunção",(VLOOKUP(C50,'[1]Controle Distribuição de Lucros'!$C$1:$Q$357,15)*'Lucros aos Sócios'!G50),IF(D50="Contabilidade"," ",0))) -> #N/A
A51: 574 | B51: =VLOOKUP(A51,Empresas!A:B,2,0) -> #N/A | C51: =VLOOKUP(B51,Empresas!B:C,2,0) -> #N/A | D51: =VLOOKUP(C51,'[1]Controle Distribuição de Lucros'!$C$1:$G$357,5,0) -> #N/A | E51: 396.841.508-65 | F51: Thamires Piasentim Avena Morais | G51: 1 | H51: =IF(D51="Contabilidade Aproximada",(VLOOKUP(C51,'Apuração Contabilidade Aproxima'!$C$1:$M$357,11,0)*G51),IF(D51="Distribuição por Presunção",(VLOOKUP(C51,'[1]Controle Distribuição de Lucros'!$C$1:$Q$357,15)*'Lucros aos Sócios'!G51),IF(D51="Contabilidade"," ",0))) -> #N/A
A52: 586 | B52: =VLOOKUP(A52,Empresas!A:B,2,0) -> 61.108.827/0001-08 | C52: =VLOOKUP(B52,Empresas!B:C,2,0) -> Aviana Ltda | D52: =VLOOKUP(C52,'[1]Controle Distribuição de Lucros'!$C$1:$G$357,5,0) -> #N/A | E52: 18951344800 | F52: Aluysson Viana do Nascimento | G52: 1 | H52: =IF(D52="Contabilidade Aproximada",(VLOOKUP(C52,'Apuração Contabilidade Aproxima'!$C$1:$M$357,11,0)*G52),IF(D52="Distribuição por Presunção",(VLOOKUP(C52,'[1]Controle Distribuição de Lucros'!$C$1:$Q$357,15)*'Lucros aos Sócios'!G52),IF(D52="Contabilidade"," ",0))) -> #N/A
A53: 330 | B53: =VLOOKUP(A53,Empresas!A:B,2,0) -> 00.368.304/0001-06 | C53: =VLOOKUP(B53,Empresas!B:C,2,0) -> Avs Vital Comércio de Tecidos e Resíduos Ltda | D53: =VLOOKUP(C53,'[1]Controle Distribuição de Lucros'!$C$1:$G$357,5,0) -> #N/A | E53: 941.886.538-68 | F53: Amaro Vital da Silva | G53: 1 | H53: =IF(D53="Contabilidade Aproximada",(VLOOKUP(C53,'Apuração Contabilidade Aproxima'!$C$1:$M$357,11,0)*G53),IF(D53="Distribuição por Presunção",(VLOOKUP(C53,'[1]Controle Distribuição de Lucros'!$C$1:$Q$357,15)*'Lucros aos Sócios'!G53),IF(D53="Contabilidade"," ",0))) -> #N/A
A54: 148 | B54: =VLOOKUP(A54,Empresas!A:B,2,0) -> 31.748.724/0001-41 | C54: =VLOOKUP(B54,Empresas!B:C,2,0) -> B.M.M. Apoio Empresarial Ltda | D54: =VLOOKUP(C54,'[1]Controle Distribuição de Lucros'!$C$1:$G$357,5,0) -> #N/A | E54: 371.370.068-09 | F54: Bruno Menecucci Morais | G54: 1 | H54: =IF(D54="Contabilidade Aproximada",(VLOOKUP(C54,'Apuração Contabilidade Aproxima'!$C$1:$M$357,11,0)*G54),IF(D54="Distribuição por Presunção",(VLOOKUP(C54,'[1]Controle Distribuição de Lucros'!$C$1:$Q$357,15)*'Lucros aos Sócios'!G54),IF(D54="Contabilidade"," ",0))) -> #N/A
A55: 512 | B55: =VLOOKUP(A55,Empresas!A:B,2,0) -> 65.934.747/0001-62 | C55: =VLOOKUP(B55,Empresas!B:C,2,0) -> Bar e Lanches Volta Cruzeiro Ltda | D55: =VLOOKUP(C55,'[1]Controle Distribuição de Lucros'!$C$1:$G$357,5,0) -> #N/A | E55: 214.426.238-10 | F55: Alessandra de Oliveira França | G55: 0.5 | H55: =IF(D55="Contabilidade Aproximada",(VLOOKUP(C55,'Apuração Contabilidade Aproxima'!$C$1:$M$357,11,0)*G55),IF(D55="Distribuição por Presunção",(VLOOKUP(C55,'[1]Controle Distribuição de Lucros'!$C$1:$Q$357,15)*'Lucros aos Sócios'!G55),IF(D55="Contabilidade"," ",0))) -> #N/A
A56: 512 | B56: =VLOOKUP(A56,Empresas!A:B,2,0) -> 65.934.747/0001-62 | C56: =VLOOKUP(B56,Empresas!B:C,2,0) -> Bar e Lanches Volta Cruzeiro Ltda | D56: =VLOOKUP(C56,'[1]Controle Distribuição de Lucros'!$C$1:$G$357,5,0) -> #N/A | E56: 674.879.398-04 | F56: Hailton Souza França | G56: 0.5 | H56: =IF(D56="Contabilidade Aproximada",(VLOOKUP(C56,'Apuração Contabilidade Aproxima'!$C$1:$M$357,11,0)*G56),IF(D56="Distribuição por Presunção",(VLOOKUP(C56,'[1]Controle Distribuição de Lucros'!$C$1:$Q$357,15)*'Lucros aos Sócios'!G56),IF(D56="Contabilidade"," ",0))) -> #N/A
A57: 155 | B57: =VLOOKUP(A57,Empresas!A:B,2,0) -> 32.412.497/0001-41 | C57: =VLOOKUP(B57,Empresas!B:C,2,0) -> Benedito José da Silva 08720320868 | D57: =VLOOKUP(C57,'[1]Controle Distribuição de Lucros'!$C$1:$G$357,5,0) -> #N/A | E57: 087.203.208-68 | F57: Benedito Jose da Silva | G57: 1 | H57: =IF(D57="Contabilidade Aproximada",(VLOOKUP(C57,'Apuração Contabilidade Aproxima'!$C$1:$M$357,11,0)*G57),IF(D57="Distribuição por Presunção",(VLOOKUP(C57,'[1]Controle Distribuição de Lucros'!$C$1:$Q$357,15)*'Lucros aos Sócios'!G57),IF(D57="Contabilidade"," ",0))) -> #N/A
A58: 351 | B58: =VLOOKUP(A58,Empresas!A:B,2,0) -> 47.407.177/0001-70 | C58: =VLOOKUP(B58,Empresas!B:C,2,0) -> Bepass S.A. | D58: =VLOOKUP(C58,'[1]Controle Distribuição de Lucros'!$C$1:$G$357,5,0) -> #N/A | E58: 065.091.628-06 | F58: Fernando José Ruiz Melchert | G58: 0.1317 | H58: =IF(D58="Contabilidade Aproximada",(VLOOKUP(C58,'Apuração Contabilidade Aproxima'!$C$1:$M$357,11,0)*G58),IF(D58="Distribuição por Presunção",(VLOOKUP(C58,'[1]Controle Distribuição de Lucros'!$C$1:$Q$357,15)*'Lucros aos Sócios'!G58),IF(D58="Contabilidade"," ",0))) -> #N/A
A59: 351 | B59: =VLOOKUP(A59,Empresas!A:B,2,0) -> 47.407.177/0001-70 | C59: =VLOOKUP(B59,Empresas!B:C,2,0) -> Bepass S.A. | D59: =VLOOKUP(C59,'[1]Controle Distribuição de Lucros'!$C$1:$G$357,5,0) -> #N/A | E59: 30.227.736/0001-68 | F59: FF2 Participações Societárias Ltda | G59: 0.4722 | H59: =IF(D59="Contabilidade Aproximada",(VLOOKUP(C59,'Apuração Contabilidade Aproxima'!$C$1:$M$357,11,0)*G59),IF(D59="Distribuição por Presunção",(VLOOKUP(C59,'[1]Controle Distribuição de Lucros'!$C$1:$Q$357,15)*'Lucros aos Sócios'!G59),IF(D59="Contabilidade"," ",0))) -> #N/A
A60: 351 | B60: =VLOOKUP(A60,Empresas!A:B,2,0) -> 47.407.177/0001-70 | C60: =VLOOKUP(B60,Empresas!B:C,2,0) -> Bepass S.A. | D60: =VLOOKUP(C60,'[1]Controle Distribuição de Lucros'!$C$1:$G$357,5,0) -> #N/A | E60: 138.405.158-90 | F60: Cláudio Coli Fernandes | G60: 0.1752 | H60: =IF(D60="Contabilidade Aproximada",(VLOOKUP(C60,'Apuração Contabilidade Aproxima'!$C$1:$M$357,11,0)*G60),IF(D60="Distribuição por Presunção",(VLOOKUP(C60,'[1]Controle Distribuição de Lucros'!$C$1:$Q$357,15)*'Lucros aos Sócios'!G60),IF(D60="Contabilidade"," ",0))) -> #N/A
A61: 351 | B61: =VLOOKUP(A61,Empresas!A:B,2,0) -> 47.407.177/0001-70 | C61: =VLOOKUP(B61,Empresas!B:C,2,0) -> Bepass S.A. | D61: =VLOOKUP(C61,'[1]Controle Distribuição de Lucros'!$C$1:$G$357,5,0) -> #N/A | E61: 332.073.428-84 | F61: Felipe de Souza Barros | G61: 0.0178 | H61: =IF(D61="Contabilidade Aproximada",(VLOOKUP(C61,'Apuração Contabilidade Aproxima'!$C$1:$M$357,11,0)*G61),IF(D61="Distribuição por Presunção",(VLOOKUP(C61,'[1]Controle Distribuição de Lucros'!$C$1:$Q$357,15)*'Lucros aos Sócios'!G61),IF(D61="Contabilidade"," ",0))) -> #N/A
A62: 351 | B62: =VLOOKUP(A62,Empresas!A:B,2,0) -> 47.407.177/0001-70 | C62: =VLOOKUP(B62,Empresas!B:C,2,0) -> Bepass S.A. | D62: =VLOOKUP(C62,'[1]Controle Distribuição de Lucros'!$C$1:$G$357,5,0) -> #N/A | E62: 353.259.268-10 | F62: Jefferson da Costa Moura | G62: 0.0178 | H62: =IF(D62="Contabilidade Aproximada",(VLOOKUP(C62,'Apuração Contabilidade Aproxima'!$C$1:$M$357,11,0)*G62),IF(D62="Distribuição por Presunção",(VLOOKUP(C62,'[1]Controle Distribuição de Lucros'!$C$1:$Q$357,15)*'Lucros aos Sócios'!G62),IF(D62="Contabilidade"," ",0))) -> #N/A
A63: 351 | B63: =VLOOKUP(A63,Empresas!A:B,2,0) -> 47.407.177/0001-70 | C63: =VLOOKUP(B63,Empresas!B:C,2,0) -> Bepass S.A. | D63: =VLOOKUP(C63,'[1]Controle Distribuição de Lucros'!$C$1:$G$357,5,0) -> #N/A | E63: 120.330.858-21 | F63: Edison Paranhos Torres | G63: 0.0188 | H63: =IF(D63="Contabilidade Aproximada",(VLOOKUP(C63,'Apuração Contabilidade Aproxima'!$C$1:$M$357,11,0)*G63),IF(D63="Distribuição por Presunção",(VLOOKUP(C63,'[1]Controle Distribuição de Lucros'!$C$1:$Q$357,15)*'Lucros aos Sócios'!G63),IF(D63="Contabilidade"," ",0))) -> #N/A
A64: 351 | B64: =VLOOKUP(A64,Empresas!A:B,2,0) -> 47.407.177/0001-70 | C64: =VLOOKUP(B64,Empresas!B:C,2,0) -> Bepass S.A. | D64: =VLOOKUP(C64,'[1]Controle Distribuição de Lucros'!$C$1:$G$357,5,0) -> #N/A | E64: 14.855.526/0001-68 | F64: Ingresse Ingressos Para Eventos S.A. | G64: 0.0199 | H64: =IF(D64="Contabilidade Aproximada",(VLOOKUP(C64,'Apuração Contabilidade Aproxima'!$C$1:$M$357,11,0)*G64),IF(D64="Distribuição por Presunção",(VLOOKUP(C64,'[1]Controle Distribuição de Lucros'!$C$1:$Q$357,15)*'Lucros aos Sócios'!G64),IF(D64="Contabilidade"," ",0))) -> #N/A
... A78: 510 | B78: =VLOOKUP(A78,Empresas!A:B,2,0) -> 55.769.305/0001-54 | C78: =VLOOKUP(B78,Empresas!B:C,2,0) -> Bianca Ribeiro Mattos Ltda | D78: =VLOOKUP(C78,'[1]Controle Distribuição de Lucros'!$C$1:$G$357,5,0) -> #N/A | E78: 454.791.538-54 | F78: Bianca Ribeiro Mattos | G78: 1 | H78: =IF(D78="Contabilidade Aproximada",(VLOOKUP(C78,'Apuração Contabilidade Aproxima'!$C$1:$M$357,11,0)*G78),IF(D78="Distribuição por Presunção",(VLOOKUP(C78,'[1]Controle Distribuição de Lucros'!$C$1:$Q$357,15)*'Lucros aos Sócios'!G78),IF(D78="Contabilidade"," ",0))) -> #N/A
A79: 646 | B79: =VLOOKUP(A79,Empresas!A:B,2,0) -> 67.041.408/0001-82 | C79: =VLOOKUP(B79,Empresas!B:C,2,0) -> Bitachon Serviços Administrativos Ltda | D79: =VLOOKUP(C79,'[1]Controle Distribuição de Lucros'!$C$1:$G$357,5,0) -> #N/A | E79: 50195368819 | F79: Jean Richard Mansur | G79: 1 | H79: =IF(D79="Contabilidade Aproximada",(VLOOKUP(C79,'Apuração Contabilidade Aproxima'!$C$1:$M$357,11,0)*G79),IF(D79="Distribuição por Presunção",(VLOOKUP(C79,'[1]Controle Distribuição de Lucros'!$C$1:$Q$357,15)*'Lucros aos Sócios'!G79),IF(D79="Contabilidade"," ",0))) -> #N/A
A80: 542 | B80: =VLOOKUP(A80,Empresas!A:B,2,0) -> 12.107.957/0001-10 | C80: =VLOOKUP(B80,Empresas!B:C,2,0) -> BJ2R Serviços Ltda | D80: =VLOOKUP(C80,'[1]Controle Distribuição de Lucros'!$C$1:$G$357,5,0) -> #N/A | E80: 93280068800 | F80: Cleide Maria Gutierrez | G80: 0.9 | H80: =IF(D80="Contabilidade Aproximada",(VLOOKUP(C80,'Apuração Contabilidade Aproxima'!$C$1:$M$357,11,0)*G80),IF(D80="Distribuição por Presunção",(VLOOKUP(C80,'[1]Controle Distribuição de Lucros'!$C$1:$Q$357,15)*'Lucros aos Sócios'!G80),IF(D80="Contabilidade"," ",0))) -> #N/A
A81: 542 | B81: =VLOOKUP(A81,Empresas!A:B,2,0) -> 12.107.957/0001-10 | C81: =VLOOKUP(B81,Empresas!B:C,2,0) -> BJ2R Serviços Ltda | D81: =VLOOKUP(C81,'[1]Controle Distribuição de Lucros'!$C$1:$G$357,5,0) -> #N/A | E81: 472.526.008-82 | F81: José Ricardo Gutierrez | G81: 0.1 | H81: =IF(D81="Contabilidade Aproximada",(VLOOKUP(C81,'Apuração Contabilidade Aproxima'!$C$1:$M$357,11,0)*G81),IF(D81="Distribuição por Presunção",(VLOOKUP(C81,'[1]Controle Distribuição de Lucros'!$C$1:$Q$357,15)*'Lucros aos Sócios'!G81),IF(D81="Contabilidade"," ",0))) -> #N/A
A82: 240 | B82: =VLOOKUP(A82,Empresas!A:B,2,0) -> 36.557.666/0001-92 | C82: =VLOOKUP(B82,Empresas!B:C,2,0) -> BLGR Serviços Empresariais Ltda | D82: =VLOOKUP(C82,'[1]Controle Distribuição de Lucros'!$C$1:$G$357,5,0) -> #N/A | E82: 7558526809 | F82: Ricardo Marchioni Belenguer | G82: 1 | H82: =IF(D82="Contabilidade Aproximada",(VLOOKUP(C82,'Apuração Contabilidade Aproxima'!$C$1:$M$357,11,0)*G82),IF(D82="Distribuição por Presunção",(VLOOKUP(C82,'[1]Controle Distribuição de Lucros'!$C$1:$Q$357,15)*'Lucros aos Sócios'!G82),IF(D82="Contabilidade"," ",0))) -> #N/A
A83: 486 | B83: =VLOOKUP(A83,Empresas!A:B,2,0) -> 35.048.108/0001-39 | C83: =VLOOKUP(B83,Empresas!B:C,2,0) -> BNC Print Comércio e Soluções Técnicas Ltda | D83: =VLOOKUP(C83,'[1]Controle Distribuição de Lucros'!$C$1:$G$357,5,0) -> #N/A | E83: 251.750.008-88 | F83: Ricardo Augusto Nascimento Benucci | G83: 1 | H83: =IF(D83="Contabilidade Aproximada",(VLOOKUP(C83,'Apuração Contabilidade Aproxima'!$C$1:$M$357,11,0)*G83),IF(D83="Distribuição por Presunção",(VLOOKUP(C83,'[1]Controle Distribuição de Lucros'!$C$1:$Q$357,15)*'Lucros aos Sócios'!G83),IF(D83="Contabilidade"," ",0))) -> #N/A
A84: 71 | B84: =VLOOKUP(A84,Empresas!A:B,2,0) -> 08.991.576/0001-70 | C84: =VLOOKUP(B84,Empresas!B:C,2,0) -> Botecaria Distribuição e Marketing Ltda | D84: =VLOOKUP(C84,'[1]Controle Distribuição de Lucros'!$C$1:$G$357,5,0) -> #N/A | E84: 34995519858 | F84: Igor Vianna Anjos | G84: 0.25 | H84: =IF(D84="Contabilidade Aproximada",(VLOOKUP(C84,'Apuração Contabilidade Aproxima'!$C$1:$M$357,11,0)*G84),IF(D84="Distribuição por Presunção",(VLOOKUP(C84,'[1]Controle Distribuição de Lucros'!$C$1:$Q$357,15)*'Lucros aos Sócios'!G84),IF(D84="Contabilidade"," ",0))) -> #N/A
A85: 71 | B85: =VLOOKUP(A85,Empresas!A:B,2,0) -> 08.991.576/0001-70 | C85: =VLOOKUP(B85,Empresas!B:C,2,0) -> Botecaria Distribuição e Marketing Ltda | D85: =VLOOKUP(C85,'[1]Controle Distribuição de Lucros'!$C$1:$G$357,5,0) -> #N/A | E85: 34042591817 | F85: Rafael Ormeni de Alencar | G85: 0.25 | H85: =IF(D85="Contabilidade Aproximada",(VLOOKUP(C85,'Apuração Contabilidade Aproxima'!$C$1:$M$357,11,0)*G85),IF(D85="Distribuição por Presunção",(VLOOKUP(C85,'[1]Controle Distribuição de Lucros'!$C$1:$Q$357,15)*'Lucros aos Sócios'!G85),IF(D85="Contabilidade"," ",0))) -> #N/A
A86: 71 | B86: =VLOOKUP(A86,Empresas!A:B,2,0) -> 08.991.576/0001-70 | C86: =VLOOKUP(B86,Empresas!B:C,2,0) -> Botecaria Distribuição e Marketing Ltda | D86: =VLOOKUP(C86,'[1]Controle Distribuição de Lucros'!$C$1:$G$357,5,0) -> #N/A | E86: 35147898867 | F86: Andrey Mattos Machado | G86: 0.25 | H86: =IF(D86="Contabilidade Aproximada",(VLOOKUP(C86,'Apuração Contabilidade Aproxima'!$C$1:$M$357,11,0)*G86),IF(D86="Distribuição por Presunção",(VLOOKUP(C86,'[1]Controle Distribuição de Lucros'!$C$1:$Q$357,15)*'Lucros aos Sócios'!G86),IF(D86="Contabilidade"," ",0))) -> #N/A
A87: 71 | B87: =VLOOKUP(A87,Empresas!A:B,2,0) -> 08.991.576/0001-70 | C87: =VLOOKUP(B87,Empresas!B:C,2,0) -> Botecaria Distribuição e Marketing Ltda | D87: =VLOOKUP(C87,'[1]Controle Distribuição de Lucros'!$C$1:$G$357,5,0) -> #N/A | E87: 35181634850 | F87: Rodrigo Soares Goncalves Dias Guimaraes | G87: 0.25 | H87: =IF(D87="Contabilidade Aproximada",(VLOOKUP(C87,'Apuração Contabilidade Aproxima'!$C$1:$M$357,11,0)*G87),IF(D87="Distribuição por Presunção",(VLOOKUP(C87,'[1]Controle Distribuição de Lucros'!$C$1:$Q$357,15)*'Lucros aos Sócios'!G87),IF(D87="Contabilidade"," ",0))) -> #N/A
A88: 458 | B88: =VLOOKUP(A88,Empresas!A:B,2,0) -> 26.635.239/0001-21 | C88: =VLOOKUP(B88,Empresas!B:C,2,0) -> Brunna Vomstein Andrade | D88: =VLOOKUP(C88,'[1]Controle Distribuição de Lucros'!$C$1:$G$357,5,0) -> #N/A | E88: 341.580.568-96 | F88: Bruna Vomstein Andrade | G88: 1 | H88: =IF(D88="Contabilidade Aproximada",(VLOOKUP(C88,'Apuração Contabilidade Aproxima'!$C$1:$M$357,11,0)*G88),IF(D88="Distribuição por Presunção",(VLOOKUP(C88,'[1]Controle Distribuição de Lucros'!$C$1:$Q$357,15)*'Lucros aos Sócios'!G88),IF(D88="Contabilidade"," ",0))) -> #N/A
A89: 122 | B89: =VLOOKUP(A89,Empresas!A:B,2,0) -> 00.833.464/0001-89 | C89: =VLOOKUP(B89,Empresas!B:C,2,0) -> Buffet Israel Ltda | D89: =VLOOKUP(C89,'[1]Controle Distribuição de Lucros'!$C$1:$G$357,5,0) -> #N/A | E89: 17605853866 | F89: Kelly Cristini Rodrigues Leite Russo | G89: 0.01 | H89: =IF(D89="Contabilidade Aproximada",(VLOOKUP(C89,'Apuração Contabilidade Aproxima'!$C$1:$M$357,11,0)*G89),IF(D89="Distribuição por Presunção",(VLOOKUP(C89,'[1]Controle Distribuição de Lucros'!$C$1:$Q$357,15)*'Lucros aos Sócios'!G89),IF(D89="Contabilidade"," ",0))) -> #N/A
A90: 122 | B90: =VLOOKUP(A90,Empresas!A:B,2,0) -> 00.833.464/0001-89 | C90: =VLOOKUP(B90,Empresas!B:C,2,0) -> Buffet Israel Ltda | D90: =VLOOKUP(C90,'[1]Controle Distribuição de Lucros'!$C$1:$G$357,5,0) -> #N/A | E90: 66675359800 | F90: Jose Gomes Machado | G90: 0.99 | H90: =IF(D90="Contabilidade Aproximada",(VLOOKUP(C90,'Apuração Contabilidade Aproxima'!$C$1:$M$357,11,0)*G90),IF(D90="Distribuição por Presunção",(VLOOKUP(C90,'[1]Controle Distribuição de Lucros'!$C$1:$Q$357,15)*'Lucros aos Sócios'!G90),IF(D90="Contabilidade"," ",0))) -> #N/A
A91: 499 | B91: =VLOOKUP(A91,Empresas!A:B,2,0) -> 57.262.385/0001-82 | C91: =VLOOKUP(B91,Empresas!B:C,2,0) -> C.M.S. Holding Participações Ltda | D91: =VLOOKUP(C91,'[1]Controle Distribuição de Lucros'!$C$1:$G$357,5,0) -> #N/A | E91: 151.536.108-02 | F91: Sandra Albina Simões | G91: 1 | H91: =IF(D91="Contabilidade Aproximada",(VLOOKUP(C91,'Apuração Contabilidade Aproxima'!$C$1:$M$357,11,0)*G91),IF(D91="Distribuição por Presunção",(VLOOKUP(C91,'[1]Controle Distribuição de Lucros'!$C$1:$Q$357,15)*'Lucros aos Sócios'!G91),IF(D91="Contabilidade"," ",0))) -> #N/A
A92: 435 | B92: =VLOOKUP(A92,Empresas!A:B,2,0) -> 52.796.465/0001-02 | C92: =VLOOKUP(B92,Empresas!B:C,2,0) -> C2C Ltda | D92: =VLOOKUP(C92,'[1]Controle Distribuição de Lucros'!$C$1:$G$357,5,0) -> #N/A | E92: 043.575.006-21 | F92: Maura Alves Pereira | G92: 1 | H92: =IF(D92="Contabilidade Aproximada",(VLOOKUP(C92,'Apuração Contabilidade Aproxima'!$C$1:$M$357,11,0)*G92),IF(D92="Distribuição por Presunção",(VLOOKUP(C92,'[1]Controle Distribuição de Lucros'!$C$1:$Q$357,15)*'Lucros aos Sócios'!G92),IF(D92="Contabilidade"," ",0))) -> #N/A
A93: 591 | B93: =VLOOKUP(A93,Empresas!A:B,2,0) -> 61.256.978/0001-03 | C93: =VLOOKUP(B93,Empresas!B:C,2,0) -> C3C Corretora de Seguros Ltda | D93: =VLOOKUP(C93,'[1]Controle Distribuição de Lucros'!$C$1:$G$357,5,0) -> #N/A | E93: 043.575.006-21 | F93: Maura Alves Pereira | G93: 1 | H93: =IF(D93="Contabilidade Aproximada",(VLOOKUP(C93,'Apuração Contabilidade Aproxima'!$C$1:$M$357,11,0)*G93),IF(D93="Distribuição por Presunção",(VLOOKUP(C93,'[1]Controle Distribuição de Lucros'!$C$1:$Q$357,15)*'Lucros aos Sócios'!G93),IF(D93="Contabilidade"," ",0))) -> #N/A
A94: 419 | B94: =VLOOKUP(A94,Empresas!A:B,2,0) -> 09.666.095/0001-51 | C94: =VLOOKUP(B94,Empresas!B:C,2,0) -> Calcam Comercial de Suprimentos de Informática Ltda | D94: =VLOOKUP(C94,'[1]Controle Distribuição de Lucros'!$C$1:$G$357,5,0) -> #N/A | E94: 086.044.888-63 | F94: Luciane Vilella Castello Letizio | G94: 1 | H94: =IF(D94="Contabilidade Aproximada",(VLOOKUP(C94,'Apuração Contabilidade Aproxima'!$C$1:$M$357,11,0)*G94),IF(D94="Distribuição por Presunção",(VLOOKUP(C94,'[1]Controle Distribuição de Lucros'!$C$1:$Q$357,15)*'Lucros aos Sócios'!G94),IF(D94="Contabilidade"," ",0))) -> #N/A
A95: 273 | B95: =VLOOKUP(A95,Empresas!A:B,2,0) -> 41.118.298/0001-16 | C95: =VLOOKUP(B95,Empresas!B:C,2,0) -> Cami Concept Ltda | D95: =VLOOKUP(C95,'[1]Controle Distribuição de Lucros'!$C$1:$G$357,5,0) -> #N/A | E95: 230.330.008-86 | F95: Camila Oliveira de Lacerda | G95: 1 | H95: =IF(D95="Contabilidade Aproximada",(VLOOKUP(C95,'Apuração Contabilidade Aproxima'!$C$1:$M$357,11,0)*G95),IF(D95="Distribuição por Presunção",(VLOOKUP(C95,'[1]Controle Distribuição de Lucros'!$C$1:$Q$357,15)*'Lucros aos Sócios'!G95),IF(D95="Contabilidade"," ",0))) -> #N/A
A96: 262 | B96: =VLOOKUP(A96,Empresas!A:B,2,0) -> 39.960.783/0001-90 | C96: =VLOOKUP(B96,Empresas!B:C,2,0) -> Capella Comércio e Representações de Produtos Químicos Ltda | D96: =VLOOKUP(C96,'[1]Controle Distribuição de Lucros'!$C$1:$G$357,5,0) -> #N/A | E96: 127.934.468-74 | F96: Wando Capella | G96: 0.7 | H96: =IF(D96="Contabilidade Aproximada",(VLOOKUP(C96,'Apuração Contabilidade Aproxima'!$C$1:$M$357,11,0)*G96),IF(D96="Distribuição por Presunção",(VLOOKUP(C96,'[1]Controle Distribuição de Lucros'!$C$1:$Q$357,15)*'Lucros aos Sócios'!G96),IF(D96="Contabilidade"," ",0))) -> #N/A
A97: 262 | B97: =VLOOKUP(A97,Empresas!A:B,2,0) -> 39.960.783/0001-90 | C97: =VLOOKUP(B97,Empresas!B:C,2,0) -> Capella Comércio e Representações de Produtos Químicos Ltda | D97: =VLOOKUP(C97,'[1]Controle Distribuição de Lucros'!$C$1:$G$357,5,0) -> #N/A | E97: 274.862.708-38 | F97: Ricardina de Carvalho Capella | G97: 0.3 | H97: =IF(D97="Contabilidade Aproximada",(VLOOKUP(C97,'Apuração Contabilidade Aproxima'!$C$1:$M$357,11,0)*G97),IF(D97="Distribuição por Presunção",(VLOOKUP(C97,'[1]Controle Distribuição de Lucros'!$C$1:$Q$357,15)*'Lucros aos Sócios'!G97),IF(D97="Contabilidade"," ",0))) -> #N/A
A98: 411 | B98: =VLOOKUP(A98,Empresas!A:B,2,0) -> 51.764.963/0001-00 | C98: =VLOOKUP(B98,Empresas!B:C,2,0) -> Caresma & Schmidt Office Consultoria Empresarial Ltda | D98: =VLOOKUP(C98,'[1]Controle Distribuição de Lucros'!$C$1:$G$357,5,0) -> #N/A | E98: 248.785.418-90 | F98: Anderson Ribeiro Caresma | G98: 0.5 | H98: =IF(D98="Contabilidade Aproximada",(VLOOKUP(C98,'Apuração Contabilidade Aproxima'!$C$1:$M$357,11,0)*G98),IF(D98="Distribuição por Presunção",(VLOOKUP(C98,'[1]Controle Distribuição de Lucros'!$C$1:$Q$357,15)*'Lucros aos Sócios'!G98),IF(D98="Contabilidade"," ",0))) -> #N/A
A99: 411 | B99: =VLOOKUP(A99,Empresas!A:B,2,0) -> 51.764.963/0001-00 | C99: =VLOOKUP(B99,Empresas!B:C,2,0) -> Caresma & Schmidt Office Consultoria Empresarial Ltda | D99: =VLOOKUP(C99,'[1]Controle Distribuição de Lucros'!$C$1:$G$357,5,0) -> #N/A | E99: 270.786.178-27 | F99: Amanda Schmidt Lima | G99: 0.5 | H99: =IF(D99="Contabilidade Aproximada",(VLOOKUP(C99,'Apuração Contabilidade Aproxima'!$C$1:$M$357,11,0)*G99),IF(D99="Distribuição por Presunção",(VLOOKUP(C99,'[1]Controle Distribuição de Lucros'!$C$1:$Q$357,15)*'Lucros aos Sócios'!G99),IF(D99="Contabilidade"," ",0))) -> #N/A
A100: 505 | B100: =VLOOKUP(A100,Empresas!A:B,2,0) -> 57.642.648/0001-89 | C100: =VLOOKUP(B100,Empresas!B:C,2,0) -> Carrilho Donas Sociedade Individual de Advocacia | D100: =VLOOKUP(C100,'[1]Controle Distribuição de Lucros'!$C$1:$G$357,5,0) -> #N/A | E100: 726.852.391-20 | F100: Frederico Gustavo Pereira Carrilho Donas | G100: 1 | H100: =IF(D100="Contabilidade Aproximada",(VLOOKUP(C100,'Apuração Contabilidade Aproxima'!$C$1:$M$357,11,0)*G100),IF(D100="Distribuição por Presunção",(VLOOKUP(C100,'[1]Controle Distribuição de Lucros'!$C$1:$Q$357,15)*'Lucros aos Sócios'!G100),IF(D100="Contabilidade"," ",0))) -> #N/A
A101: 495 | B101: =VLOOKUP(A101,Empresas!A:B,2,0) -> 57.121.049/0001-10 | C101: =VLOOKUP(B101,Empresas!B:C,2,0) -> Cass Consultoria Empresarial Ltda | D101: =VLOOKUP(C101,'[1]Controle Distribuição de Lucros'!$C$1:$G$357,5,0) -> #N/A | E101: 126.508.738-50 | F101: Fabiana de Cassia Lorencani | G101: 1 | H101: =IF(D101="Contabilidade Aproximada",(VLOOKUP(C101,'Apuração Contabilidade Aproxima'!$C$1:$M$357,11,0)*G101),IF(D101="Distribuição por Presunção",(VLOOKUP(C101,'[1]Controle Distribuição de Lucros'!$C$1:$Q$357,15)*'Lucros aos Sócios'!G101),IF(D101="Contabilidade"," ",0))) -> #N/A
A102: 293 | B102: =VLOOKUP(A102,Empresas!A:B,2,0) -> 42.638.806/0001-50 | C102: =VLOOKUP(B102,Empresas!B:C,2,0) -> Catedral Intermediação de Negócios Ltda | D102: =VLOOKUP(C102,'[1]Controle Distribuição de Lucros'!$C$1:$G$357,5,0) -> #N/A | E102: 1217110801 | F102: Valdir Ferreira de Carvalho | G102: 0.9999 | H102: =IF(D102="Contabilidade Aproximada",(VLOOKUP(C102,'Apuração Contabilidade Aproxima'!$C$1:$M$357,11,0)*G102),IF(D102="Distribuição por Presunção",(VLOOKUP(C102,'[1]Controle Distribuição de Lucros'!$C$1:$Q$357,15)*'Lucros aos Sócios'!G102),IF(D102="Contabilidade"," ",0))) -> #N/A
A103: 293 | B103: =VLOOKUP(A103,Empresas!A:B,2,0) -> 42.638.806/0001-50 | C103: =VLOOKUP(B103,Empresas!B:C,2,0) -> Catedral Intermediação de Negócios Ltda | D103: =VLOOKUP(C103,'[1]Controle Distribuição de Lucros'!$C$1:$G$357,5,0) -> #N/A | E103: 5472325862 | F103: Airton Ferreira de Carvalho | G103: 0.0001 | H103: =IF(D103="Contabilidade Aproximada",(VLOOKUP(C103,'Apuração Contabilidade Aproxima'!$C$1:$M$357,11,0)*G103),IF(D103="Distribuição por Presunção",(VLOOKUP(C103,'[1]Controle Distribuição de Lucros'!$C$1:$Q$357,15)*'Lucros aos Sócios'!G103),IF(D103="Contabilidade"," ",0))) -> #N/A
A104: 335 | B104: =VLOOKUP(A104,Empresas!A:B,2,0) -> 13.574.084/0001-19 | C104: =VLOOKUP(B104,Empresas!B:C,2,0) -> CCKids Comércio e Confecção de Roupas e Acessórios Ltda | D104: =VLOOKUP(C104,'[1]Controle Distribuição de Lucros'!$C$1:$G$357,5,0) -> #N/A | E104: 118.355.238-62 | F104: Izaura Aparecida do Nascimento | G104: 1 | H104: =IF(D104="Contabilidade Aproximada",(VLOOKUP(C104,'Apuração Contabilidade Aproxima'!$C$1:$M$357,11,0)*G104),IF(D104="Distribuição por Presunção",(VLOOKUP(C104,'[1]Controle Distribuição de Lucros'!$C$1:$Q$357,15)*'Lucros aos Sócios'!G104),IF(D104="Contabilidade"," ",0))) -> #N/A
A105: 372 | B105: =VLOOKUP(A105,Empresas!A:B,2,0) -> 50.685.261/0001-60 | C105: =VLOOKUP(B105,Empresas!B:C,2,0) -> CDM Holding Ltda | D105: =VLOOKUP(C105,'[1]Controle Distribuição de Lucros'!$C$1:$G$357,5,0) -> #N/A | E105: 116.028.748-16 | F105: Renato Pellin Cardoso de Moraes | G105: 0.485 | H105: =IF(D105="Contabilidade Aproximada",(VLOOKUP(C105,'Apuração Contabilidade Aproxima'!$C$1:$M$357,11,0)*G105),IF(D105="Distribuição por Presunção",(VLOOKUP(C105,'[1]Controle Distribuição de Lucros'!$C$1:$Q$357,15)*'Lucros aos Sócios'!G105),IF(D105="Contabilidade"," ",0))) -> #N/A
A106: 372 | B106: =VLOOKUP(A106,Empresas!A:B,2,0) -> 50.685.261/0001-60 | C106: =VLOOKUP(B106,Empresas!B:C,2,0) -> CDM Holding Ltda | D106: =VLOOKUP(C106,'[1]Controle Distribuição de Lucros'!$C$1:$G$357,5,0) -> #N/A | E106: 125.603.458-46 | F106: Luciana Lazara Ramos Cardoso de Moraes | G106: 0.485 | H106: =IF(D106="Contabilidade Aproximada",(VLOOKUP(C106,'Apuração Contabilidade Aproxima'!$C$1:$M$357,11,0)*G106),IF(D106="Distribuição por Presunção",(VLOOKUP(C106,'[1]Controle Distribuição de Lucros'!$C$1:$Q$357,15)*'Lucros aos Sócios'!G106),IF(D106="Contabilidade"," ",0))) -> #N/A
A107: 372 | B107: =VLOOKUP(A107,Empresas!A:B,2,0) -> 50.685.261/0001-60 | C107: =VLOOKUP(B107,Empresas!B:C,2,0) -> CDM Holding Ltda | D107: =VLOOKUP(C107,'[1]Controle Distribuição de Lucros'!$C$1:$G$357,5,0) -> #N/A | E107: 413.650.878-67 | F107: Kaue Ramos Cardoso de Moraes | G107: 0.01 | H107: =IF(D107="Contabilidade Aproximada",(VLOOKUP(C107,'Apuração Contabilidade Aproxima'!$C$1:$M$357,11,0)*G107),IF(D107="Distribuição por Presunção",(VLOOKUP(C107,'[1]Controle Distribuição de Lucros'!$C$1:$Q$357,15)*'Lucros aos Sócios'!G107),IF(D107="Contabilidade"," ",0))) -> #N/A
A108: 372 | B108: =VLOOKUP(A108,Empresas!A:B,2,0) -> 50.685.261/0001-60 | C108: =VLOOKUP(B108,Empresas!B:C,2,0) -> CDM Holding Ltda | D108: =VLOOKUP(C108,'[1]Controle Distribuição de Lucros'!$C$1:$G$357,5,0) -> #N/A | E108: 413.650.868-95 | F108: Lukas Ramos Cardoso de Moraes | G108: 0.01 | H108: =IF(D108="Contabilidade Aproximada",(VLOOKUP(C108,'Apuração Contabilidade Aproxima'!$C$1:$M$357,11,0)*G108),IF(D108="Distribuição por Presunção",(VLOOKUP(C108,'[1]Controle Distribuição de Lucros'!$C$1:$Q$357,15)*'Lucros aos Sócios'!G108),IF(D108="Contabilidade"," ",0))) -> #N/A
A109: 372 | B109: =VLOOKUP(A109,Empresas!A:B,2,0) -> 50.685.261/0001-60 | C109: =VLOOKUP(B109,Empresas!B:C,2,0) -> CDM Holding Ltda | D109: =VLOOKUP(C109,'[1]Controle Distribuição de Lucros'!$C$1:$G$357,5,0) -> #N/A | E109: 447.744.288-25 | F109: Manuella Ramos Cardoso de Moraes | G109: 0.01 | H109: =IF(D109="Contabilidade Aproximada",(VLOOKUP(C109,'Apuração Contabilidade Aproxima'!$C$1:$M$357,11,0)*G109),IF(D109="Distribuição por Presunção",(VLOOKUP(C109,'[1]Controle Distribuição de Lucros'!$C$1:$Q$357,15)*'Lucros aos Sócios'!G109),IF(D109="Contabilidade"," ",0))) -> #N/A
A110: 398 | B110: =VLOOKUP(A110,Empresas!A:B,2,0) -> 03.702.166/0001-48 | C110: =VLOOKUP(B110,Empresas!B:C,2,0) -> Cena Cultural Produções Ltda | D110: =VLOOKUP(C110,'[1]Controle Distribuição de Lucros'!$C$1:$G$357,5,0) -> #N/A | E110: 19580070644 | F110: Maria Julia Gomes | G110: 1 | H110: =IF(D110="Contabilidade Aproximada",(VLOOKUP(C110,'Apuração Contabilidade Aproxima'!$C$1:$M$357,11,0)*G110),IF(D110="Distribuição por Presunção",(VLOOKUP(C110,'[1]Controle Distribuição de Lucros'!$C$1:$Q$357,15)*'Lucros aos Sócios'!G110),IF(D110="Contabilidade"," ",0))) -> #N/A
A111: 321 | B111: =VLOOKUP(A111,Empresas!A:B,2,0) -> 59.650.721/0001-90 | C111: =VLOOKUP(B111,Empresas!B:C,2,0) -> Central Serviços Médicos Ltda | D111: =VLOOKUP(C111,'[1]Controle Distribuição de Lucros'!$C$1:$G$357,5,0) -> #N/A | E111: 9994541889 | F111: Javier Victor Salas Vargas | G111: 1 | H111: =IF(D111="Contabilidade Aproximada",(VLOOKUP(C111,'Apuração Contabilidade Aproxima'!$C$1:$M$357,11,0)*G111),IF(D111="Distribuição por Presunção",(VLOOKUP(C111,'[1]Controle Distribuição de Lucros'!$C$1:$Q$357,15)*'Lucros aos Sócios'!G111),IF(D111="Contabilidade"," ",0))) -> #N/A
A112: 449 | B112: =VLOOKUP(A112,Empresas!A:B,2,0) -> 10.665.359/0001-31 | C112: =VLOOKUP(B112,Empresas!B:C,2,0) -> Centro de Saúde Animal Zoovet Ltda | D112: =VLOOKUP(C112,'[1]Controle Distribuição de Lucros'!$C$1:$G$357,5,0) -> #N/A | E112: 28308647863 | F112: Clayton Goncalves de Souza | G112: 0.3068 | H112: =IF(D112="Contabilidade Aproximada",(VLOOKUP(C112,'Apuração Contabilidade Aproxima'!$C$1:$M$357,11,0)*G112),IF(D112="Distribuição por Presunção",(VLOOKUP(C112,'[1]Controle Distribuição de Lucros'!$C$1:$Q$357,15)*'Lucros aos Sócios'!G112),IF(D112="Contabilidade"," ",0))) -> #N/A
A113: 449 | B113: =VLOOKUP(A113,Empresas!A:B,2,0) -> 10.665.359/0001-31 | C113: =VLOOKUP(B113,Empresas!B:C,2,0) -> Centro de Saúde Animal Zoovet Ltda | D113: =VLOOKUP(C113,'[1]Controle Distribuição de Lucros'!$C$1:$G$357,5,0) -> #N/A | E113: 29331333854 | F113: Gabriel da Silva Seabra | G113: 0.3066 | H113: =IF(D113="Contabilidade Aproximada",(VLOOKUP(C113,'Apuração Contabilidade Aproxima'!$C$1:$M$357,11,0)*G113),IF(D113="Distribuição por Presunção",(VLOOKUP(C113,'[1]Controle Distribuição de Lucros'!$C$1:$Q$357,15)*'Lucros aos Sócios'!G113),IF(D113="Contabilidade"," ",0))) -> #N/A
...

Sheet Base
A1: Estado | B1: Vencimento TFE | C1: Partes Relacionadas | D1: Data | E1: Evento | F1: Tributação | G1: Usuário | H1: Envio de Documentos | I1: Dia Útil | J1: Escriturações | K1: REINF | L1: Movimentação Folha | M1: Tipo Aferição | N1: Procurações | O1: Parcelamentos Ativos
A2: Acre | B2: Janeiro | C2: Grupo Aprobato Neto | D2: 46237 | E2: Cisão | F2: Lucro Presumido | G2: Jorge | H2: E-mail | I2: 1 | J2: OK | K2: OK | L2: Folha de Pagamento | M2: Contabilidade | N2: Aprobato Neto | O2: Não
A3: Alagoas | B3: Fevereiro | C3: Grupo Croce Simões | D3: 46238 | E3: Desenquadramento | F3: Lucro Real | G3: Kamilly | H3: E-mail e Site | I3: 2 | J3: S/M | K3: S/M | L3: Pró-Labore | M3: Contabilidade Aproximada | N3: J P Cont | O3: Sim
A4: Amazonas | B4: Março | C4: Grupo Decor Adesivos | D4: 46239 | E4: Extinção | F4: MEI | G4: Luana | H4: E-mail Renata | I4: 3 | J4: N/A | K4: N/A | L4: Sem Movimento | M4: Contabilidade BPO
A5: Amapá | B5: Abril | C5: Grupo Dovil Indústria | D5: 46240 | E5: Fusão | F5: Simples Nacional | G5: Claudia | H5: Impostos Paulo | I5: 4 | J5: Saldo Credor | M5: Distribuição por Presunção
A6: Bahia | B6: Maio | C6: Grupo Fairbanks | D6: 46241 | E6: Incorporação | G6: Michele | H6: Impresso | I6: 5 | J6: Transmitida S/M | M6: Não Distribuir
A7: Ceará | B7: Junho | C7: Grupo FLM Engenharia | D7: 46244 | E7: Transferida | G7: Bruna | H7: Impresso Aprobato | I7: 6 | M7: Sem Movimento
A8: Distrito Federal | B8: Julho | C8: Grupo Gnomo Comércio | D8: 46245 | E8: Não se Aplica | G8: Paulo | H8: Site | I8: 7
A9: Espírito Santo | B9: Agosto | C9: Grupo Grax Lubrificantes | D9: 46246 | G9: Talita | H9: Site e E-mail | I9: 8
A10: Goiás | B10: Setembro | C10: Grupo GTR Financeira | D10: 46247 | G10: Dyego | H10: Site e WhatsApp | I10: 9
A11: Maranhão | B11: Outubro | C11: Grupo Hocar Comércio | D11: 46248 | G11: Dyego/Bruna | I11: 10
A12: Minas Gerais | B12: Novembro | C12: Grupo Ibel Maq | D12: 46251 | I12: 11
A13: Mato Grosso do Sul | B13: Dezembro | C13: Grupo Ici Gastronomia | D13: 46252 | I13: 12
A14: Mato Grosso | C14: Grupo Indikey Comunicação | D14: 46253
A15: Pará | C15: Grupo Induspacking Indústria | D15: 46254
A16: Paraíba | C16: Grupo Inox Conexões | D16: 46255
A17: Pernambuco | C17: Grupo J B S Inspeção | D17: 46258
A18: Piauí | C18: Grupo Korubo Expedições | D18: 46259
A19: Paraná | C19: Grupo KV Equipamentos | D19: 46260
A20: Rio de Janeiro | C20: Grupo LightPrint Indústria | D20: 46261
A21: Rio Grande do Norte | C21: Grupo Lopérgolo Aguiar | D21: 46262
A22: Rondônia | C22: Grupo Lu Lu | D22: 46265
A23: Roraima | C23: Grupo Media Portal
A24: Rio Grande do Sul | C24: Grupo Minale Brindes
A25: Santa Catarina | C25: Grupo Mobel Engenharia
A26: São Paulo | C26: Grupo Passarela Modas
A27: Sergipe | C27: Grupo Pedro Nevoeiro
A28: Tocantins | C28: Grupo Ribeiro
C29: Grupo SDJ Comercial
C30: Grupo Serralheria Cordeiro
C31: Grupo SeuChico Comércio
C32: Grupo Shuk Alimentos
C33: Grupo Signmaker Comunicação
C34: Grupo Solo Tecnologia
C35: Grupo Tavares Comércio
C36: Grupo Technology Publicidade
C37: Grupo Teles Comércio
C38: Grupo Tixe Participações
C39: Grupo Treeon Soluções
C40: Grupo Tricomix Comércio
... C42: Não se Aplica

Sheet Controle de Datas
A1: ID | B1: Datas
A2: 1 | B2: 46237
A3: 2 | B3: 46238
A4: 3 | B4: 46239
A5: 4 | B5: 46240
A6: 5 | B6: 46241
A7: 6 | B7: 46244
A8: 7 | B8: 46245
A9: 8 | B9: 46246
A10: 9 | B10: 46247
A11: 10 | B11: 46248

Sheet Procedimento Fechamento
A1: ID | B1: Procedimentos
A2: 1 | B2: Escriturar/Importar Notas Fiscais de Serviços
A3: 2 | B3: Escriturar/Importar Notas Fiscais de Saídas
A4: 3 | B4: Escriturar/Importar Notas Fiscais de Entradas (Com Relacionamento)
A5: 4 | B5: Escriturar/Importar Conhecimentos de Transportes Tomados
A6: 5 | B6: Gerar DANFE das Notas Fiscais de Entradas e Conferir as Escriturações (Lucro Presumido e Lucro Real)
A7: 6 | B7: Gerar DANFE dos Conhecimentos de Transportes Tomados e Conferir as Escriturações (Lucro Presumido e Lucro Real)
A8: 7 | B8: Verificar Eventuais Documentos Faltantes
A9: 8 | B9: Verificar Documentos Inutilizados no Ambiente Eletrônico da NFe
A10: 9 | B10: Verificar as Naturezas de ISS e ICMS (Se Estão Condizentes com as Operações da Empresa)
A11: 10 | B11: Verificar o Relacionamento de Produtos x Fornecedores
A12: 11 | B12: Arrumar a Referência dos Produtos e Posteriormente "Atualizar" os Produtos das Entradas e Saídas
A13: 12 | B13: Verificar os CSTs de Entradas e Saídas do ICMS e IPI
... A25: 24 | B25: Enviar os Tributos aos Clientes

Sheet Observações
A1: Código | B1: CNPJ | C1: Razão Social | D1: Usuário | E1: Observações
A2: 106 | B2: =VLOOKUP(A2,Empresas!A:B,2,0) -> 04.431.460/0001-25 | C2: =VLOOKUP(B2,Empresas!B:C,2,0) -> 04.431.460 Ramiro Duenas Aranzabal | D2: =VLOOKUP(A2,Empresas!A:J,10,0) -> Jorge
A3: 119 | B3: 27.541.980/0001-96 | C3: 4.Com Serviços Empresariais Ltda | D3: Jorge
A4: 415 | B4: 42.360.609/0001-11 | C4: 42.360.609 Dener Mendonça de Souza | D4: Jorge
A5: 218 | B5: 43.436.474/0001-93 | C5: 43.436.474 Maria Clara Tomé Garcia | D5: Jorge
A6: 628 | B6: 43.959.791/0001-94 | C6: 43.959.791 Ana Isabela Pithan Maraschin | D6: Jorge
A7: 227 | B7: 44.645.259/0001-65 | C7: 44.645.259 Rebeca Brito Cardoso | D7: Jorge
A8: 359 | B8: 04.362.429/0001-80 | C8: 4CS Serviços Ltda | D8: Paulo
A9: 638 | B9: 51.957.545/0001-21 | C9: 51.957.545 Marjorie Abdallah | D9: Bruna
A10: 437 | B10: 53.494.930/0001-05 | C10: 53.494.930 Gabriela Afonso Prado | D10: Jorge
A11: 461 | B11: 54.535.015/0001-83 | C11: Ada Maria Fraulo Pires | D11: Bruna
A12: 525 | B12: 58.344.129/0001-05 | C12: 58.344.129 Gilda Maria de Lima Roberto | D12: Jorge
A13: 608 | B13: 13.581.219/0001-73 | C13: A & V Marques Imóveis Ltda | D13: Talita
A14: 34 | B14: 22.189.167/0001-85 | C14: A Galeria Artes Presentes Jóias Design Rocym Ltda | D14: Jorge
... A22: 230 | B22: 04.746.127/0001-05 | C22: Alexandre Silva Voza | D22: Michele
A23: 370 | B23: 37.140.411/0001-92 | C23: Allora Construtora e Incorporadora Ltda | D23: Kamilly | E23: As Guias de ISSQN Serão Emitidas por Eles à Partir do Fechamento de Maio-2025
A24: 578 | B24: 13.314.231/0001-11 | C24: Alpha Entretenimento e Lazer Ltda | D24: Talita
A25: 302 | B25: 01.665.434/0001-73 | C25: Alphaville Comercial Ltda | D25: Luana
A26: 376 | B26: 09.086.104/0001-35 | C26: Américo Suriano e Companhia Ltda | D26: Michele
A27: 576 | B27: 49.343.692/0001-60 | C27: Ápice Artes Gráficas Ltda | D27: Paulo | E27: Retenções Apuradas por Competência e Tem Retenção Sobre Aluguéis. Ficar Atento a Tributação das Receitas Financeiras e Outras Receitas Para Fins de PIS e COFINS. Verificar Também os Ajustes de ICMS (i) Aquisição de Paletes com Diferimento; (ii) Aquisição de Energia Elétrica Fora do Estado; e (iii) Diferencial de Alíquota
A28: 61 | B28: 03.338.180/0001-04 | C28: Aprobato Neto Contabilidade e Apoio Empresarial Ltda | D28: Paulo
A29: 972 | B29: 00.000.904/0001-17 | C29: Aprobato Neto Perícias Técnicas Ltda | D29: Paulo | E29: Empresa Sujeita a Prestação de Serviços com Retenção de ISSQN na Fonte, Verificar os Documentos Fiscais e Aplicar a Natureza 5.933.003
A30: 972 (-2) | B30: 00.000.904/0002-06 | C30: Aprobato Neto Perícias Técnicas Ltda | D30: Paulo
A31: 440 | B31: 71.912.349/0001-48 | C31: Arakaki Enterprise Ltda | D31: Talita
A32: 18 | B32: 61.094.660/0001-73 | C32: Aramfactor Utilidades em Arames Ltda | D32: Talita | E32: Verificar as Receitas Financeiras Para Fins de Tributação do IRPJ e CSLL. Cliente Encaminha o Relatório de ICMS e IPI, em Caso de Divergência Entrar em Contato
A33: 127 | B33: 02.400.369/0001-17 | C33: Associação Brasileira de Wakeboard | D33: Jorge
A34: 208 | B34: 07.010.849/0001-95 | C34: Associação dos Serv e Magis Para Manut do Berçário do TRT da 2 Região | D34: Jorge
A35: 175 | B35: 39.563.909/0001-93 | C35: Assunção Antunes Corretora de Seguros Ltda | D35: Luana
A36: 594 | B36: 61.633.486/0001-90 | C36: Astra Tecnologia Ltda | D36: Claudia
A37: 556 | B37: 37.911.956/0001-55 | C37: Atta Participações Ltda | D37: Jorge
A38: 279 | B38: 04.914.402/0001-52 | C38: Augusta e Respeitável Loja Simbólica Paz e Harmonia | D38: Talita
A39: 615 | B39: 63.531.342/0001-58 | C39: Augusto Ferrari Gestão Patrimonial Ltda | D39: Claudia
A40: 586 | B40: 61.108.827/0001-08 | C40: Aviana Ltda | D40: Bruna
A41: 330 | B41: 00.368.304/0001-06 | C41: Avs Vital Comércio de Tecidos e Resíduos Ltda | D41: Claudia
A42: 148 | B42: 31.748.724/0001-41 | C42: B.M.M. Apoio Empresarial Ltda | D42: Jorge
A43: 512 | B43: 65.934.747/0001-62 | C43: Bar e Lanches Volta Cruzeiro Ltda | D43: Claudia
A44: 155 | B44: 32.412.497/0001-41 | C44: Benedito José da Silva 08720320868 | D44: Talita
A45: 351 | B45: 47.407.177/0001-70 | C45: Bepass S.A. | D45: Talita | E45: Empresa Optante Pelo Lucro Real Porém Apura PIS e COFINS de Forma Cumulativa. Verificar a Aplicabilidade do Diferencial de Alíquota
A46: 510 | B46: 55.769.305/0001-54 | C46: Bianca Ribeiro Mattos Ltda | D46: Claudia
A47: 646 | B47: 67.041.408/0001-82 | C47: Bitachon Serviços Administrativos Ltda | D47: Jorge
A48: 542 | B48: 12.107.957/0001-10 | C48: BJ2R Serviços Ltda | D48: Kamilly
A49: 240 | B49: 36.557.666/0001-92 | C49: BLGR Serviços Empresariais Ltda | D49: Bruna
A50: 486 | B50: 35.048.108/0001-39 | C50: BNC Print Comércio e Soluções Técnicas Ltda | D50: Talita | E50: Acessar o Sistema do Cliente para Obtenção dos Documentos e Apuração dos Tributos
A51: 71 | B51: 08.991.576/0001-70 | C51: Botecaria Distribuição e Marketing Ltda | D51: Bruna
A52: 458 | B52: 26.635.239/0001-21 | C52: Brunna Vomstein Andrade | D52: Bruna
A53: 122 | B53: 00.833.464/0001-89 | C53: Buffet Israel Ltda | D53: Kamilly
A54: 499 | B54: 57.262.385/0001-82 | C54: C.M.S. Holding Participações Ltda | D54: Michele
A55: 435 | B55: 52.796.465/0001-02 | C55: C2C Ltda | D55: Luana
A56: 591 | B56: 61.256.978/0001-03 | C56: C3C Corretora de Seguros Ltda | D56: Luana
A57: 419 | B57: 09.666.095/0001-51 | C57: Calcam Comercial de Suprimentos de Informática Ltda | D57: Talita
A58: 273 | B58: 41.118.298/0001-16 | C58: Cami Concept Ltda | D58: Bruna
A59: 262 | B59: 39.960.783/0001-90 | C59: Capella Comércio e Representações de Produtos Químicos Ltda | D59: Kamilly | E59: Verificar as Receitas Financeiras Para Fins de Tributação do IRPJ e CSLL. Caso o Cliente não Encaminhe Oferecer a Tributação por Estimativa
A60: 411 | B60: 51.764.963/0001-00 | C60: Caresma & Schmidt Office Consultoria Empresarial Ltda | D60: Bruna
A61: 505 | B61: 57.642.648/0001-89 | C61: Carrilho Donas Sociedade Individual de Advocacia | D61: Bruna
A62: 495 | B62: 57.121.049/0001-10 | C62: Cass Consultoria Empresarial Ltda | D62: Claudia
A63: 293 | B63: 42.638.806/0001-50 | C63: Catedral Intermediação de Negócios Ltda | D63: Claudia
A64: 335 | B64: 13.574.084/0001-19 | C64: CCKids Comércio e Confecção de Roupas e Acessórios Ltda | D64: Luana
A65: 372 | B65: 50.685.261/0001-60 | C65: CDM Holding Ltda | D65: Kamilly | E65: Verificar as Receitas Financeiras Para Fins de Tributação do IRPJ e CSLL
A66: 398 | B66: 03.702.166/0001-48 | C66: Cena Cultural Produções Ltda | D66: Claudia
A67: 321 | B67: 59.650.721/0001-90 | C67: Central Serviços Médicos Ltda | D67: Talita
A68: 449 | B68: 10.665.359/0001-31 | C68: Centro de Saúde Animal Zoovet Ltda | D68: Talita
A69: 730 | B69: 65.887.267/0001-98 | C69: Chipendalle Arte Móveis Ltda | D69: Jorge
A70: 365 | B70: 34.329.315/0001-07 | C70: CJS Comércio Varejista de Tecidos Ltda | D70: Bruna
A71: 365 (-2) | B71: 34.329.315/0002-80 | C71: CJS Comércio Varejista de Tecidos Ltda | D71: Bruna
A72: 365 (-3) | B72: 34.329.315/0003-60 | C72: CJS Comércio Varejista de Tecidos Ltda | D72: Bruna
A73: 408 | B73: 48.292.179/0001-24 | C73: CLE Comunicação Liderança e Educação Ltda | D73: Luana
A74: 402 | B74: 03.754.180/0001-95 | C74: Clínica de Ortopedia Dr. Javier V. S. Vargas Ltda | D74: Kamilly | E74: Verificar os Recibos Médicos e Proceder com a Emissão dos Documentos Fiscais
A75: 393 | B75: 03.541.023/0001-00 | C75: Clínica Dr. Eduardo de Souza Ltda | D75: Luana | E75: Verificar os Recibos Médicos e Proceder com a Emissão dos Documentos Fiscais
A76: 420 | B76: 52.145.726/0001-16 | C76: Comércio Estético Maison Hair Ltda | D76: Jorge
A77: 187 | B77: 34.504.701/0001-80 | C77: Comuniverse Ltda | D77: Michele | E77: Empresa Optante Pelo Lucro Real Porém Apura PIS e COFINS de Forma Cumulativa
A78: 476 | B78: 03.951.113/0001-60 | C78: Condor Instituto de Psicologia e Pesquisa SS Ltda | D78: Talita
A79: 128 | B79: 06.347.712/0001-68 | C79: Confederação Brasileira de Empresas Juniores | D79: Kamilly
A80: 590 | B80: 61.158.615/0001-35 | C80: Convox Negócios e Serviços Ltda | D80: Talita
A81: 621 | B81: 42.657.808/0001-96 | C81: Corcovado Investimentos Gestão de Recursos Ltda | D81: Michele
A82: 23 | B82: 45.953.312/0001-58 | C82: Cristal Prime Auto Vidros e Acessórios Ltda | D82: Kamilly
A83: 137 | B83: 00.569.062/0001-19 | C83: Cristaltech Auto Vidros e Acessorios Ltda | D83: Kamilly
A84: 137 (-2) | B84: 00.569.062/0002-08 | C84: Cristaltech Auto Vidros e Acessorios Ltda | D84: Kamilly
A85: 494 | B85: 56.778.834/0001-87 | C85: Croce Simões Holding Ltda | D85: Michele
A86: 308 | B86: 18.587.752/0001-66 | C86: Crysthiane Henrique de Matos Gonçalves Tripode | D86: Michele
A87: 557 | B87: 39.940.308/0001-52 | C87: Dataind Tecnologia de Informação Ltda | D87: Jorge
A88: 181 | B88: 00.575.747/0001-78 | C88: Davos Consult Serviços de Apoio Empresarial Ltda | D88: Jorge
A89: 272 | B89: 40.915.081/0001-74 | C89: DBM Consultoria e Participações Ltda | D89: Claudia
A90: 367 | B90: 50.231.188/0001-57 | C90: Decor Adesivos e Decoração Ltda | D90: Talita
A91: 254 | B91: 27.532.933/0001-86 | C91: Decor Revestimentos Adesivos Ltda | D91: Talita
A92: 6 | B92: 16.952.792/0001-34 | C92: Delta Geradores Ltda | D92: Jorge
A93: 113 | B93: 27.372.837/0001-18 | C93: Delta Suporte em Vendas Ltda | D93: Claudia
A94: 145 | B94: 31.496.077/0001-28 | C94: Denis Calazans Cordeiro | D94: Luana
A95: 640 | B95: 33.032.171/0001-51 | C95: DHM Engenharia Ltda | D95: Talita
A96: 103 | B96: 26.025.480/0001-39 | C96: Diógenes Prado Batista Sociedade Individual de Advocacia | D96: Jorge | E96: Solicitar o Faturamento por E-mail
A97: 550 | B97: 12.591.454/0001-63 | C97: Direct Advice Serviços Empresariais Ltda | D97: Bruna
A98: 169 | B98: 14.627.752/0001-91 | C98: Direction Solução em Serviços Administrativos Ltda | D98: Bruna
A99: 643 | B99: 66.673.761/0001-12 | C99: DLS Serviços de Tecnologia Ltda | D99: Kamilly
A100: 585 | B100: 61.054.759/0001-41 | C100: Doces da Lu Lu Ltda | D100: Claudia
A101: 361 | B101: 49.307.542/0001-09 | C101: Dogua Importadora e Comercializadora de Bebidas Ltda | D101: Jorge
A102: 236 | B102: 09.387.685/0001-45 | C102: Dorio Sociedade de Advogados | D102: Talita
A103: 630 | B103: 65.293.919/0001-66 | C103: Douglas K Okamoto Ltda | D103: Talita
A104: 22 | B104: 67.748.657/0001-02 | C104: Dovil Indústria e Comércio de Artigos para Laboratório Ltda | D104: Michele | E104: Antes de Apurar os Tributos Encaminhar Para o Cliente Analisar
A105: 60 | B105: 59.181.040/0001-20 | C105: Dr. Israel Roitman Neurologia Clínica e Eletroencefalografia Ltda | D105: Kamilly | E105: Verificar os Recibos Médicos e Proceder com a Emissão dos Documentos Fiscais. Apuração dos Tributos Federais Mediante Regime de Caixa
A106: 356 | B106: 48.787.005/0001-32 | C106: DX Imóveis Administração Ltda | D106: Talita
A107: 501 | B107: 34.227.106/0001-44 | C107: Easy Wine Utensílios Domésticos Ltda | D107: Bruna
...

Sheet Empresas
A1: Código | B1: CNPJ | C1: Razão Social | D1: Tributação | E1: Inscrição Estadual | F1: Estado | G1: Inscrição Municipal | H1: Município | I1: Partes Relacionadas | J1: Usuário | K1: Eventos | L1: Envio de Documentos | M1: Dia Útil | N1: Data Limite | O1: Data Início | P1: Data Final | Q1: Status | R1: Acompanhamento | S1: Procurações | T1: Conferência
A2: 106 | B2: 04.431.460/0001-25 | C2: 04.431.460 Ramiro Duenas Aranzabal | D2: MEI | E2: 116270616110 | F2: São Paulo | G2: 3.656.245-9 | H2: São Paulo | I2: Não se Aplica | J2: Jorge | K2: Não se Aplica | L2: E-mail | M2: 3 | N2: =VLOOKUP(M2,'Controle de Datas'!A:B,2,0) -> 46239 | O2: 46239 | P2: 46239 | Q2: =IF(R2="Não Inicializada",1,IF(R2="Em Andamento",1,IF(R2="Entregue com Atraso",-1,IF(R2="Em Atraso",-1,0)))) -> 0 | R2: =IF(OR(N2="",AND(O2="",P2="")),"Não Inicializada",IF(AND(O2<=N2,P2=""),"Em Andamento",IF(P2>N2,"Entregue com Atraso",IF(O2>N2,"Em Atraso","Entregue")))) -> Entregue | S2: Aprobato Neto
A3: 119 | B3: 27.541.980/0001-96 | C3: 4.Com Serviços Empresariais Ltda | D3: Simples Nacional | E3: Isenta | F3: São Paulo | G3: 5.694.018-1 | H3: São Paulo | I3: Não se Aplica | J3: Jorge | K3: Não se Aplica | L3: Site | M3: 5 | N3: =VLOOKUP(M3,'Controle de Datas'!A:B,2,0) -> 46241 | O3: 46248 | P3: 46248 | Q3: =IF(R3="Não Inicializada",1,IF(R3="Em Andamento",1,IF(R3="Entregue com Atraso",-1,IF(R3="Em Atraso",-1,0)))) -> -1 | R3: =IF(OR(N3="",AND(O3="",P3="")),"Não Inicializada",IF(AND(O3<=N3,P3=""),"Em Andamento",IF(P3>N3,"Entregue com Atraso",IF(O3>N3,"Em Atraso","Entregue")))) -> Entregue com Atraso | S3: Aprobato Neto
A4: 415 | B4: 42.360.609/0001-11 | C4: 42.360.609 Dener Mendonça de Souza | D4: MEI | E4: Isenta | F4: São Paulo | G4: 1470672 | H4: Jundiaí | I4: Não se Aplica | J4: Jorge | K4: Não se Aplica | L4: Site | M4: 2 | N4: =VLOOKUP(M4,'Controle de Datas'!A:B,2,0) -> 46238 | O4: 46239 | P4: 46239 | Q4: =IF(R4="Não Inicializada",1,IF(R4="Em Andamento",1,IF(R4="Entregue com Atraso",-1,IF(R4="Em Atraso",-1,0)))) -> -1 | R4: =IF(OR(N4="",AND(O4="",P4="")),"Não Inicializada",IF(AND(O4<=N4,P4=""),"Em Andamento",IF(P4>N4,"Entregue com Atraso",IF(O4>N4,"Em Atraso","Entregue")))) -> Entregue com Atraso | S4: J P Cont
A5: 218 | B5: 43.436.474/0001-93 | C5: 43.436.474 Maria Clara Tomé Garcia | D5: MEI | E5: 799468637111 | F5: São Paulo | G5: 298839 | H5: São Bernardo do Campo | I5: Não se Aplica | J5: Jorge | K5: Não se Aplica | L5: Site | M5: 3 | N5: =VLOOKUP(M5,'Controle de Datas'!A:B,2,0) -> 46239 | O5: Distrato | P5: Distrato | Q5: =IF(R5="Não Inicializada",1,IF(R5="Em Andamento",1,IF(R5="Entregue com Atraso",-1,IF(R5="Em Atraso",-1,0)))) -> -1 | R5: =IF(OR(N5="",AND(O5="",P5="")),"Não Inicializada",IF(AND(O5<=N5,P5=""),"Em Andamento",IF(P5>N5,"Entregue com Atraso",IF(O5>N5,"Em Atraso","Entregue")))) -> Entregue com Atraso | S5: Aprobato Neto
A6: 628 | B6: 43.959.791/0001-94 | C6: 43.959.791 Ana Isabela Pithan Maraschin | D6: MEI | E6: 133256510113 | F6: São Paulo | G6: 7.107.342-6 | H6: São Paulo | I6: Não se Aplica | J6: Jorge | K6: Não se Aplica | L6: Site | M6: 4 | N6: =VLOOKUP(M6,'Controle de Datas'!A:B,2,0) -> 46240 | O6: 46239 | P6: 46239 | Q6: =IF(R6="Não Inicializada",1,IF(R6="Em Andamento",1,IF(R6="Entregue com Atraso",-1,IF(R6="Em Atraso",-1,0)))) -> 0 | R6: =IF(OR(N6="",AND(O6="",P6="")),"Não Inicializada",IF(AND(O6<=N6,P6=""),"Em Andamento",IF(P6>N6,"Entregue com Atraso",IF(O6>N6,"Em Atraso","Entregue")))) -> Entregue | S6: J P Cont
A7: 227 | B7: 44.645.259/0001-65 | C7: 44.645.259 Rebeca Brito Cardoso | D7: MEI | E7: Isenta | F7: São Paulo | G7: 158982 | H7: Osasco | I7: Não se Aplica | J7: Jorge | K7: Não se Aplica | L7: Site | M7: 5 | N7: =VLOOKUP(M7,'Controle de Datas'!A:B,2,0) -> 46241 | Q7: =IF(R7="Não Inicializada",1,IF(R7="Em Andamento",1,IF(R7="Entregue com Atraso",-1,IF(R7="Em Atraso",-1,0)))) -> 1 | R7: =IF(OR(N7="",AND(O7="",P7="")),"Não Inicializada",IF(AND(O7<=N7,P7=""),"Em Andamento",IF(P7>N7,"Entregue com Atraso",IF(O7>N7,"Em Atraso","Entregue")))) -> Não Inicializada | S7: Aprobato Neto
A8: 359 | B8: 04.362.429/0001-80 | C8: 4CS Serviços Ltda | D8: Simples Nacional | E8: Isenta | F8: São Paulo | G8: 3.005.100-2 | H8: São Paulo | I8: Grupo Aprobato Neto | J8: Paulo | K8: Não se Aplica | L8: Site | M8: 5 | N8: =VLOOKUP(M8,'Controle de Datas'!A:B,2,0) -> 46241 | Q8: =IF(R8="Não Inicializada",1,IF(R8="Em Andamento",1,IF(R8="Entregue com Atraso",-1,IF(R8="Em Atraso",-1,0)))) -> 1 | R8: =IF(OR(N8="",AND(O8="",P8="")),"Não Inicializada",IF(AND(O8<=N8,P8=""),"Em Andamento",IF(P8>N8,"Entregue com Atraso",IF(O8>N8,"Em Atraso","Entregue")))) -> Não Inicializada | S8: Aprobato Neto
A9: 638 | B9: 51.957.545/0001-21 | C9: 51.957.545 Marjorie Abdallah | D9: Simples Nacional | E9: Isenta | F9: São Paulo | G9: 4067310 | H9: São José do Rio Preto | I9: Não se Aplica | J9: Bruna | K9: Não se Aplica | L9: Site | M9: 3 | N9: =VLOOKUP(M9,'Controle de Datas'!A:B,2,0) -> 46239 | O9: 46237 | P9: 46238 | Q9: =IF(R9="Não Inicializada",1,IF(R9="Em Andamento",1,IF(R9="Entregue com Atraso",-1,IF(R9="Em Atraso",-1,0)))) -> 0 | R9: =IF(OR(N9="",AND(O9="",P9="")),"Não Inicializada",IF(AND(O9<=N9,P9=""),"Em Andamento",IF(P9>N9,"Entregue com Atraso",IF(O9>N9,"Em Atraso","Entregue")))) -> Entregue | S9: J P Cont
A10: 437 | B10: 53.494.930/0001-05 | C10: 53.494.930 Gabriela Afonso Prado | D10: MEI | E10: Isenta | F10: Distrito Federal | G10: 08.271.808/001-19 | H10: Brasília | I10: Não se Aplica | J10: Jorge | K10: Não se Aplica | L10: Site | M10: 1 | N10: =VLOOKUP(M10,'Controle de Datas'!A:B,2,0) -> 46237 | O10: 46239 | P10: 46239 | Q10: =IF(R10="Não Inicializada",1,IF(R10="Em Andamento",1,IF(R10="Entregue com Atraso",-1,IF(R10="Em Atraso",-1,0)))) -> -1 | R10: =IF(OR(N10="",AND(O10="",P10="")),"Não Inicializada",IF(AND(O10<=N10,P10=""),"Em Andamento",IF(P10>N10,"Entregue com Atraso",IF(O10>N10,"Em Atraso","Entregue")))) -> Entregue com Atraso | S10: J P Cont
A11: 461 | B11: 54.535.015/0001-83 | C11: Ada Maria Fraulo Pires | D11: Simples Nacional | E11: 135862064112 | F11: São Paulo | G11: 1.302.220-2 | H11: São Paulo | I11: Não se Aplica | J11: Bruna | K11: Não se Aplica | L11: Site | M11: 1 | N11: =VLOOKUP(M11,'Controle de Datas'!A:B,2,0) -> 46237 | O11: 46237 | P11: 46244 | Q11: =IF(R11="Não Inicializada",1,IF(R11="Em Andamento",1,IF(R11="Entregue com Atraso",-1,IF(R11="Em Atraso",-1,0)))) -> -1 | R11: =IF(OR(N11="",AND(O11="",P11="")),"Não Inicializada",IF(AND(O11<=N11,P11=""),"Em Andamento",IF(P11>N11,"Entregue com Atraso",IF(O11>N11,"Em Atraso","Entregue")))) -> Entregue com Atraso | S11: J P Cont
A12: 525 | B12: 58.344.129/0001-05 | C12: 58.344.129 Gilda Maria de Lima Roberto | D12: MEI | E12: 151811726114 | F12: São Paulo | G12: 1.609.138-9 | H12: São Paulo | I12: Não se Aplica | J12: Jorge | K12: Não se Aplica | L12: Site | M12: 1 | N12: =VLOOKUP(M12,'Controle de Datas'!A:B,2,0) -> 46237 | O12: 46239 | P12: 46239 | Q12: =IF(R12="Não Inicializada",1,IF(R12="Em Andamento",1,IF(R12="Entregue com Atraso",-1,IF(R12="Em Atraso",-1,0)))) -> -1 | R12: =IF(OR(N12="",AND(O12="",P12="")),"Não Inicializada",IF(AND(O12<=N12,P12=""),"Em Andamento",IF(P12>N12,"Entregue com Atraso",IF(O12>N12,"Em Atraso","Entregue")))) -> Entregue com Atraso | S12: J P Cont
A13: 608 | B13: 13.581.219/0001-73 | C13: A & V Marques Imóveis Ltda | D13: Simples Nacional | E13: Isenta | F13: São Paulo | G13: 4.285.073-8 | H13: São Paulo | I13: Não se Aplica | J13: Talita | K13: Não se Aplica | L13: Site | M13: 3 | N13: =VLOOKUP(M13,'Controle de Datas'!A:B,2,0) -> 46239 | O13: 46238 | P13: 46238 | Q13: =IF(R13="Não Inicializada",1,IF(R13="Em Andamento",1,IF(R13="Entregue com Atraso",-1,IF(R13="Em Atraso",-1,0)))) -> 0 | R13: =IF(OR(N13="",AND(O13="",P13="")),"Não Inicializada",IF(AND(O13<=N13,P13=""),"Em Andamento",IF(P13>N13,"Entregue com Atraso",IF(O13>N13,"Em Atraso","Entregue")))) -> Entregue | S13: J P Cont
A14: 34 | B14: 22.189.167/0001-85 | C14: A Galeria Artes Presentes Jóias Design Rocym Ltda | D14: Simples Nacional | E14: 128248912111 | F14: São Paulo | G14: 5.212.716-8 | H14: São Paulo | I14: Não se Aplica | J14: Jorge | K14: Não se Aplica | L14: E-mail | M14: 1 | N14: =VLOOKUP(M14,'Controle de Datas'!A:B,2,0) -> 46237 | O14: 46239 | P14: 46239 | Q14: =IF(R14="Não Inicializada",1,IF(R14="Em Andamento",1,IF(R14="Entregue com Atraso",-1,IF(R14="Em Atraso",-1,0)))) -> -1 | R14: =IF(OR(N14="",AND(O14="",P14="")),"Não Inicializada",IF(AND(O14<=N14,P14=""),"Em Andamento",IF(P14>N14,"Entregue com Atraso",IF(O14>N14,"Em Atraso","Entregue")))) -> Entregue com Atraso | S14: Aprobato Neto
A15: 523 | B15: 11.360.241/0001-68 | C15: A. de S. Cafcalas | D15: Simples Nacional | E15: Isenta | F15: São Paulo | G15: 3.994.283-0 | H15: São Paulo | I15: Não se Aplica | J15: Claudia | K15: Não se Aplica | L15: E-mail | M15: 2 | N15: =VLOOKUP(M15,'Controle de Datas'!A:B,2,0) -> 46238 | O15: 46238 | P15: 46238 | Q15: =IF(R15="Não Inicializada",1,IF(R15="Em Andamento",1,IF(R15="Entregue com Atraso",-1,IF(R15="Em Atraso",-1,0)))) -> 0 | R15: =IF(OR(N15="",AND(O15="",P15="")),"Não Inicializada",IF(AND(O15<=N15,P15=""),"Em Andamento",IF(P15>N15,"Entregue com Atraso",IF(O15>N15,"Em Atraso","Entregue")))) -> Entregue | S15: Aprobato Neto
A16: 587 | B16: 61.203.201/0001-80 | C16: A2M Ltda | D16: Lucro Presumido | E16: Isenta | F16: São Paulo | G16: 1.854.114-3 | H16: São Paulo | I16: Não se Aplica | J16: Luana | K16: Não se Aplica | L16: Site | M16: 10 | N16: =VLOOKUP(M16,'Controle de Datas'!A:B,2,0) -> 46248 | O16: 46245 | P16: 46246 | Q16: =IF(R16="Não Inicializada",1,IF(R16="Em Andamento",1,IF(R16="Entregue com Atraso",-1,IF(R16="Em Atraso",-1,0)))) -> 0 | R16: =IF(OR(N16="",AND(O16="",P16="")),"Não Inicializada",IF(AND(O16<=N16,P16=""),"Em Andamento",IF(P16>N16,"Entregue com Atraso",IF(O16>N16,"Em Atraso","Entregue")))) -> Entregue | S16: Aprobato Neto
A17: 225 | B17: 04.438.239/0001-07 | C17: AGM Representações Comerciais Ltda | D17: Lucro Presumido | E17: Isenta | F17: São Paulo | G17: 6942 | H17: Bariri | I17: Não se Aplica | J17: Talita | K17: Não se Aplica | L17: Site | M17: 2 | N17: =VLOOKUP(M17,'Controle de Datas'!A:B,2,0) -> 46238 | O17: 46237 | P17: 46237 | Q17: =IF(R17="Não Inicializada",1,IF(R17="Em Andamento",1,IF(R17="Entregue com Atraso",-1,IF(R17="Em Atraso",-1,0)))) -> 0 | R17: =IF(OR(N17="",AND(O17="",P17="")),"Não Inicializada",IF(AND(O17<=N17,P17=""),"Em Andamento",IF(P17>N17,"Entregue com Atraso",IF(O17>N17,"Em Atraso","Entregue")))) -> Entregue | S17: Aprobato Neto
A18: 572 | B18: 44.114.755/0001-92 | C18: AGR Tubos Conexões e Válvulas Ltda | D18: Simples Nacional | E18: 636583794113 | F18: São Paulo | G18: 141224 | H18: São Caetano do Sul | I18: Grupo Inox Conexões | J18: Michele | K18: Não se Aplica | L18: Site | M18: 3 | N18: =VLOOKUP(M18,'Controle de Datas'!A:B,2,0) -> 46239 | O18: 46237 | P18: 46240 | Q18: =IF(R18="Não Inicializada",1,IF(R18="Em Andamento",1,IF(R18="Entregue com Atraso",-1,IF(R18="Em Atraso",-1,0)))) -> -1 | R18: =IF(OR(N18="",AND(O18="",P18="")),"Não Inicializada",IF(AND(O18<=N18,P18=""),"Em Andamento",IF(P18>N18,"Entregue com Atraso",IF(O18>N18,"Em Atraso","Entregue")))) -> Entregue com Atraso | S18: Aprobato Neto
A19: 597 | B19: 33.023.255/0001-29 | C19: Alan W de O Lima Tecnologia da Informação | D19: Simples Nacional | E19: Isenta | F19: São Paulo | G19: 108240 | H19: São Caetano do Sul | I19: Grupo Fealtec | J19: Kamilly | K19: Não se Aplica | L19: Site | M19: 2 | N19: =VLOOKUP(M19,'Controle de Datas'!A:B,2,0) -> 46238 | O19: 46238 | P19: 46238 | Q19: =IF(R19="Não Inicializada",1,IF(R19="Em Andamento",1,IF(R19="Entregue com Atraso",-1,IF(R19="Em Atraso",-1,0)))) -> 0 | R19: =IF(OR(N19="",AND(O19="",P19="")),"Não Inicializada",IF(AND(O19<=N19,P19=""),"Em Andamento",IF(P19>N19,"Entregue com Atraso",IF(O19>N19,"Em Atraso","Entregue")))) -> Entregue | S19: Aprobato Neto
A20: 617 | B20: 58.717.889/0001-02 | C20: Ale Holding Participações e Negócios Ltda | D20: Lucro Presumido | E20: 152218550110 | F20: São Paulo | G20: 4253100 | H20: São José do Rio Preto | I20: Não se Aplica | J20: Luana | K20: Não se Aplica | L20: Site | M20: 3 | N20: =VLOOKUP(M20,'Controle de Datas'!A:B,2,0) -> 46239 | O20: 46238 | P20: 46238 | Q20: =IF(R20="Não Inicializada",1,IF(R20="Em Andamento",1,IF(R20="Entregue com Atraso",-1,IF(R20="Em Atraso",-1,0)))) -> 0 | R20: =IF(OR(N20="",AND(O20="",P20="")),"Não Inicializada",IF(AND(O20<=N20,P20=""),"Em Andamento",IF(P20>N20,"Entregue com Atraso",IF(O20>N20,"Em Atraso","Entregue")))) -> Entregue | S20: J P Cont
A21: 303 | B21: 02.864.188/0001-41 | C21: Alexandre Sgreccia | D21: Simples Nacional | E21: Isenta | F21: São Paulo | G21: 2.743.353-6 | H21: São Paulo | I21: Não se Aplica | J21: Luana | K21: Não se Aplica | L21: E-mail | M21: 5 | N21: =VLOOKUP(M21,'Controle de Datas'!A:B,2,0) -> 46241 | O21: 46241 | P21: 46241 | Q21: =IF(R21="Não Inicializada",1,IF(R21="Em Andamento",1,IF(R21="Entregue com Atraso",-1,IF(R21="Em Atraso",-1,0)))) -> 0 | R21: =IF(OR(N21="",AND(O21="",P21="")),"Não Inicializada",IF(AND(O21<=N21,P21=""),"Em Andamento",IF(P21>N21,"Entregue com Atraso",IF(O21>N21,"Em Atraso","Entregue")))) -> Entregue | S21: Aprobato Neto
A22: 230 | B22: 04.746.127/0001-05 | C22: Alexandre Silva Voza | D22: Simples Nacional | E22: 149989327117 | F22: São Paulo | G22: 3.070.085-0 | H22: São Paulo | I22: Não se Aplica | J22: Michele | K22: Não se Aplica | L22: Site | M22: 5 | N22: =VLOOKUP(M22,'Controle de Datas'!A:B,2,0) -> 46241 | O22: 46238 | P22: 46238 | Q22: =IF(R22="Não Inicializada",1,IF(R22="Em Andamento",1,IF(R22="Entregue com Atraso",-1,IF(R22="Em Atraso",-1,0)))) -> 0 | R22: =IF(OR(N22="",AND(O22="",P22="")),"Não Inicializada",IF(AND(O22<=N22,P22=""),"Em Andamento",IF(P22>N22,"Entregue com Atraso",IF(O22>N22,"Em Atraso","Entregue")))) -> Entregue | S22: Aprobato Neto
A23: 370 | B23: 37.140.411/0001-92 | C23: Allora Construtora e Incorporadora Ltda | D23: Lucro Presumido | E23: 128936605119 | F23: São Paulo | G23: 6.592.930-6 | H23: São Paulo | I23: Grupo Mobel Engenharia | J23: Kamilly | K23: Não se Aplica | L23: Site | M23: 9 | N23: =VLOOKUP(M23,'Controle de Datas'!A:B,2,0) -> 46247 | O23: 46251 | P23: 46251 | Q23: =IF(R23="Não Inicializada",1,IF(R23="Em Andamento",1,IF(R23="Entregue com Atraso",-1,IF(R23="Em Atraso",-1,0)))) -> -1 | R23: =IF(OR(N23="",AND(O23="",P23="")),"Não Inicializada",IF(AND(O23<=N23,P23=""),"Em Andamento",IF(P23>N23,"Entregue com Atraso",IF(O23>N23,"Em Atraso","Entregue")))) -> Entregue com Atraso | S23: Aprobato Neto
A24: 578 | B24: 13.314.231/0001-11 | C24: Alpha Entretenimento e Lazer Ltda | D24: Simples Nacional | E24: 403008716119 | F24: São Paulo | G24: 1.592.667-2 | H24: São Paulo | I24: Não se Aplica | J24: Talita | K24: Não se Aplica | L24: E-mail | M24: 2 | N24: =VLOOKUP(M24,'Controle de Datas'!A:B,2,0) -> 46238 | O24: 46237 | P24: 46237 | Q24: =IF(R24="Não Inicializada",1,IF(R24="Em Andamento",1,IF(R24="Entregue com Atraso",-1,IF(R24="Em Atraso",-1,0)))) -> 0 | R24: =IF(OR(N24="",AND(O24="",P24="")),"Não Inicializada",IF(AND(O24<=N24,P24=""),"Em Andamento",IF(P24>N24,"Entregue com Atraso",IF(O24>N24,"Em Atraso","Entregue")))) -> Entregue | S24: Aprobato Neto
A25: 302 | B25: 01.665.434/0001-73 | C25: Alphaville Comercial Ltda | D25: Simples Nacional | E25: 114726418111 | F25: São Paulo | G25: 2.558.561-4 | H25: São Paulo | I25: Não se Aplica | J25: Luana | K25: Não se Aplica | L25: Site | M25: 7 | N25: =VLOOKUP(M25,'Controle de Datas'!A:B,2,0) -> 46245 | O25: 46246 | P25: 46248 | Q25: =IF(R25="Não Inicializada",1,IF(R25="Em Andamento",1,IF(R25="Entregue com Atraso",-1,IF(R25="Em Atraso",-1,0)))) -> -1 | R25: =IF(OR(N25="",AND(O25="",P25="")),"Não Inicializada",IF(AND(O25<=N25,P25=""),"Em Andamento",IF(P25>N25,"Entregue com Atraso",IF(O25>N25,"Em Atraso","Entregue")))) -> Entregue com Atraso | S25: Aprobato Neto
A26: 376 | B26: 09.086.104/0001-35 | C26: Américo Suriano e Companhia Ltda | D26: Simples Nacional | E26: 149817697113 | F26: São Paulo | G26: 3.676.979-7 | H26: São Paulo | I26: Não se Aplica | J26: Michele | K26: Não se Aplica | L26: E-mail | M26: 10 | N26: =VLOOKUP(M26,'Controle de Datas'!A:B,2,0) -> 46248 | O26: 46238 | P26: 46246 | Q26: =IF(R26="Não Inicializada",1,IF(R26="Em Andamento",1,IF(R26="Entregue com Atraso",-1,IF(R26="Em Atraso",-1,0)))) -> 0 | R26: =IF(OR(N26="",AND(O26="",P26="")),"Não Inicializada",IF(AND(O26<=N26,P26=""),"Em Andamento",IF(P26>N26,"Entregue com Atraso",IF(O26>N26,"Em Atraso","Entregue")))) -> Entregue | S26: Aprobato Neto
A27: 576 | B27: 49.343.692/0001-60 | C27: Ápice Artes Gráficas Ltda | D27: Lucro Real | E27: 636070583117 | F27: São Paulo | G27: 23830 | H27: São Caetano do Sul | I27: Não se Aplica | J27: Paulo | K27: Não se Aplica | L27: E-mail | M27: 8 | N27: =VLOOKUP(M27,'Controle de Datas'!A:B,2,0) -> 46246 | Q27: =IF(R27="Não Inicializada",1,IF(R27="Em Andamento",1,IF(R27="Entregue com Atraso",-1,IF(R27="Em Atraso",-1,0)))) -> 1 | R27: =IF(OR(N27="",AND(O27="",P27="")),"Não Inicializada",IF(AND(O27<=N27,P27=""),"Em Andamento",IF(P27>N27,"Entregue com Atraso",IF(O27>N27,"Em Atraso","Entregue")))) -> Não Inicializada | S27: J P Cont
A28: 61 | B28: 03.338.180/0001-04 | C28: Aprobato Neto Contabilidade e Apoio Empresarial Ltda | D28: Simples Nacional | E28: Isenta | F28: São Paulo | G28: 2.818.201-4 | H28: São Paulo | I28: Grupo Aprobato Neto | J28: Paulo | K28: Não se Aplica | L28: E-mail | M28: 3 | N28: =VLOOKUP(M28,'Controle de Datas'!A:B,2,0) -> 46239 | Q28: =IF(R28="Não Inicializada",1,IF(R28="Em Andamento",1,IF(R28="Entregue com Atraso",-1,IF(R28="Em Atraso",-1,0)))) -> 1 | R28: =IF(OR(N28="",AND(O28="",P28="")),"Não Inicializada",IF(AND(O28<=N28,P28=""),"Em Andamento",IF(P28>N28,"Entregue com Atraso",IF(O28>N28,"Em Atraso","Entregue")))) -> Não Inicializada | S28: Aprobato Neto
A29: 972 | B29: 00.000.904/0001-17 | C29: Aprobato Neto Perícias Técnicas Ltda | D29: Simples Nacional | E29: Isenta | F29: São Paulo | G29: 2.254.918-8 | H29: São Paulo | I29: Grupo Aprobato Neto | J29: Paulo | K29: Não se Aplica | L29: E-mail | M29: 8 | N29: =VLOOKUP(M29,'Controle de Datas'!A:B,2,0) -> 46246 | Q29: =IF(R29="Não Inicializada",1,IF(R29="Em Andamento",1,IF(R29="Entregue com Atraso",-1,IF(R29="Em Atraso",-1,0)))) -> 1 | R29: =IF(OR(N29="",AND(O29="",P29="")),"Não Inicializada",IF(AND(O29<=N29,P29=""),"Em Andamento",IF(P29>N29,"Entregue com Atraso",IF(O29>N29,"Em Atraso","Entregue")))) -> Não Inicializada | S29: Aprobato Neto
A30: 972 (-2) | B30: 00.000.904/0002-06 | C30: Aprobato Neto Perícias Técnicas Ltda | D30: Simples Nacional | E30: Isenta | F30: São Paulo | H30: São Caetano do Sul | I30: Grupo Aprobato Neto | J30: Paulo | K30: Não se Aplica | L30: E-mail | M30: 8 | N30: =VLOOKUP(M30,'Controle de Datas'!A:B,2,0) -> 46246 | Q30: =IF(R30="Não Inicializada",1,IF(R30="Em Andamento",1,IF(R30="Entregue com Atraso",-1,IF(R30="Em Atraso",-1,0)))) -> 1 | R30: =IF(OR(N30="",AND(O30="",P30="")),"Não Inicializada",IF(AND(O30<=N30,P30=""),"Em Andamento",IF(P30>N30,"Entregue com Atraso",IF(O30>N30,"Em Atraso","Entregue")))) -> Não Inicializada | S30: Aprobato Neto
A31: 440 | B31: 71.912.349/0001-48 | C31: Arakaki Enterprise Ltda | D31: Lucro Presumido | E31: 135658787115 | F31: São Paulo | G31: 2.189.072-2 | H31: São Paulo | I31: Não se Aplica | J31: Talita | K31: Não se Aplica | L31: Site | M31: 10 | N31: =VLOOKUP(M31,'Controle de Datas'!A:B,2,0) -> 46248 | O31: 46247 | P31: 46247 | Q31: =IF(R31="Não Inicializada",1,IF(R31="Em Andamento",1,IF(R31="Entregue com Atraso",-1,IF(R31="Em Atraso",-1,0)))) -> 0 | R31: =IF(OR(N31="",AND(O31="",P31="")),"Não Inicializada",IF(AND(O31<=N31,P31=""),"Em Andamento",IF(P31>N31,"Entregue com Atraso",IF(O31>N31,"Em Atraso","Entregue")))) -> Entregue | S31: J P Cont
A32: 18 | B32: 61.094.660/0001-73 | C32: Aramfactor Utilidades em Arames Ltda | D32: Lucro Presumido | E32: 112425660117 | F32: São Paulo | G32: 9.663.449-9 | H32: São Paulo | I32: Não se Aplica | J32: Talita | K32: Não se Aplica | L32: Site | M32: 6 | N32: =VLOOKUP(M32,'Controle de Datas'!A:B,2,0) -> 46244 | O32: 46254 | P32: 46254 | Q32: =IF(R32="Não Inicializada",1,IF(R32="Em Andamento",1,IF(R32="Entregue com Atraso",-1,IF(R32="Em Atraso",-1,0)))) -> -1 | R32: =IF(OR(N32="",AND(O32="",P32="")),"Não Inicializada",IF(AND(O32<=N32,P32=""),"Em Andamento",IF(P32>N32,"Entregue com Atraso",IF(O32>N32,"Em Atraso","Entregue")))) -> Entregue com Atraso | S32: Aprobato Neto
A33: 127 | B33: 02.400.369/0001-17 | C33: Associação Brasileira de Wakeboard | D33: Lucro Real | E33: Isenta | F33: São Paulo | G33: 2.672.777-3 | H33: São Paulo | I33: Não se Aplica | J33: Jorge | K33: Não se Aplica | L33: Site e WhatsApp | M33: 2 | N33: =VLOOKUP(M33,'Controle de Datas'!A:B,2,0) -> 46238 | O33: 46239 | P33: 46239 | Q33: =IF(R33="Não Inicializada",1,IF(R33="Em Andamento",1,IF(R33="Entregue com Atraso",-1,IF(R33="Em Atraso",-1,0)))) -> -1 | R33: =IF(OR(N33="",AND(O33="",P33="")),"Não Inicializada",IF(AND(O33<=N33,P33=""),"Em Andamento",IF(P33>N33,"Entregue com Atraso",IF(O33>N33,"Em Atraso","Entregue")))) -> Entregue com Atraso | S33: Aprobato Neto
A34: 208 | B34: 07.010.849/0001-95 | C34: Associação dos Serv e Magis Para Manut do Berçário do TRT da 2 Região | D34: Lucro Real | E34: Isenta | F34: São Paulo | G34: 3.390.868-0 | H34: São Paulo | I34: Não se Aplica | J34: Jorge | K34: Não se Aplica | L34: E-mail | M34: 4 | N34: =VLOOKUP(M34,'Controle de Datas'!A:B,2,0) -> 46240 | O34: 46239 | P34: 46239 | Q34: =IF(R34="Não Inicializada",1,IF(R34="Em Andamento",1,IF(R34="Entregue com Atraso",-1,IF(R34="Em Atraso",-1,0)))) -> 0 | R34: =IF(OR(N34="",AND(O34="",P34="")),"Não Inicializada",IF(AND(O34<=N34,P34=""),"Em Andamento",IF(P34>N34,"Entregue com Atraso",IF(O34>N34,"Em Atraso","Entregue")))) -> Entregue | S34: Aprobato Neto
A35: 175 | B35: 39.563.909/0001-93 | C35: Assunção Antunes Corretora de Seguros Ltda | D35: Simples Nacional | E35: Isenta | F35: Minas Gerais | G35: 1.258.826/001-4 | H35: Belo Horizonte | I35: Grupo Indikey Comunicação | J35: Luana | K35: Não se Aplica | L35: Site | M35: 4 | N35: =VLOOKUP(M35,'Controle de Datas'!A:B,2,0) -> 46240 | O35: 46240 | P35: 46240 | Q35: =IF(R35="Não Inicializada",1,IF(R35="Em Andamento",1,IF(R35="Entregue com Atraso",-1,IF(R35="Em Atraso",-1,0)))) -> 0 | R35: =IF(OR(N35="",AND(O35="",P35="")),"Não Inicializada",IF(AND(O35<=N35,P35=""),"Em Andamento",IF(P35>N35,"Entregue com Atraso",IF(O35>N35,"Em Atraso","Entregue")))) -> Entregue | S35: Aprobato Neto
A36: 594 | B36: 61.633.486/0001-90 | C36: Astra Tecnologia Ltda | D36: Simples Nacional | E36: Isenta | F36: São Paulo | G36: 4.BP565-1 | H36: Barueri | I36: Não se Aplica | J36: Claudia | K36: Não se Aplica | L36: Site | M36: 5 | N36: =VLOOKUP(M36,'Controle de Datas'!A:B,2,0) -> 46241 | O36: 46241 | P36: 46241 | Q36: =IF(R36="Não Inicializada",1,IF(R36="Em Andamento",1,IF(R36="Entregue com Atraso",-1,IF(R36="Em Atraso",-1,0)))) -> 0 | R36: =IF(OR(N36="",AND(O36="",P36="")),"Não Inicializada",IF(AND(O36<=N36,P36=""),"Em Andamento",IF(P36>N36,"Entregue com Atraso",IF(O36>N36,"Em Atraso","Entregue")))) -> Entregue | S36: J P Cont
A37: 556 | B37: 37.911.956/0001-55 | C37: Atta Participações Ltda | D37: Lucro Presumido | E37: Isenta | F37: São Paulo | G37: 4996407 | H37: Barueri | I37: Grupo Tixe Participações | J37: Jorge | K37: Não se Aplica | L37: E-mail | M37: 5 | N37: =VLOOKUP(M37,'Controle de Datas'!A:B,2,0) -> 46241 | O37: 46254 | P37: 46254 | Q37: =IF(R37="Não Inicializada",1,IF(R37="Em Andamento",1,IF(R37="Entregue com Atraso",-1,IF(R37="Em Atraso",-1,0)))) -> -1 | R37: =IF(OR(N37="",AND(O37="",P37="")),"Não Inicializada",IF(AND(O37<=N37,P37=""),"Em Andamento",IF(P37>N37,"Entregue com Atraso",IF(O37>N37,"Em Atraso","Entregue")))) -> Entregue com Atraso | S37: Aprobato Neto
A38: 279 | B38: 04.914.402/0001-52 | C38: Augusta e Respeitável Loja Simbólica Paz e Harmonia | D38: Lucro Real | E38: Isenta | F38: São Paulo | G38: 3.106.378-0 | H38: São Paulo | I38: Não se Aplica | J38: Talita | K38: Não se Aplica | L38: Site | M38: 4 | N38: =VLOOKUP(M38,'Controle de Datas'!A:B,2,0) -> 46240 | O38: 46255 | P38: 46255 | Q38: =IF(R38="Não Inicializada",1,IF(R38="Em Andamento",1,IF(R38="Entregue com Atraso",-1,IF(R38="Em Atraso",-1,0)))) -> -1 | R38: =IF(OR(N38="",AND(O38="",P38="")),"Não Inicializada",IF(AND(O38<=N38,P38=""),"Em Andamento",IF(P38>N38,"Entregue com Atraso",IF(O38>N38,"Em Atraso","Entregue")))) -> Entregue com Atraso | S38: Aprobato Neto
A39: 615 | B39: 63.531.342/0001-58 | C39: Augusto Ferrari Gestão Patrimonial Ltda | D39: Lucro Presumido | E39: Isenta | F39: São Paulo | G39: 0.059.091-6 | H39: São Paulo | I39: Não se Aplica | J39: Claudia | K39: Não se Aplica | L39: Site | M39: 5 | N39: =VLOOKUP(M39,'Controle de Datas'!A:B,2,0) -> 46241 | O39: 46246 | P39: 46247 | Q39: =IF(R39="Não Inicializada",1,IF(R39="Em Andamento",1,IF(R39="Entregue com Atraso",-1,IF(R39="Em Atraso",-1,0)))) -> -1 | R39: =IF(OR(N39="",AND(O39="",P39="")),"Não Inicializada",IF(AND(O39<=N39,P39=""),"Em Andamento",IF(P39>N39,"Entregue com Atraso",IF(O39>N39,"Em Atraso","Entregue")))) -> Entregue com Atraso | S39: Aprobato Neto
A40: 586 | B40: 61.108.827/0001-08 | C40: Aviana Ltda | D40: Simples Nacional | E40: Isenta | F40: São Paulo | G40: 1.846.546-3 | H40: São Paulo | I40: Não se Aplica | J40: Bruna | K40: Não se Aplica | L40: Site | M40: 1 | N40: =VLOOKUP(M40,'Controle de Datas'!A:B,2,0) -> 46237 | O40: 46237 | P40: 46238 | Q40: =IF(R40="Não Inicializada",1,IF(R40="Em Andamento",1,IF(R40="Entregue com Atraso",-1,IF(R40="Em Atraso",-1,0)))) -> -1 | R40: =IF(OR(N40="",AND(O40="",P40="")),"Não Inicializada",IF(AND(O40<=N40,P40=""),"Em Andamento",IF(P40>N40,"Entregue com Atraso",IF(O40>N40,"Em Atraso","Entregue")))) -> Entregue com Atraso | S40: J P Cont
A41: 330 | B41: 00.368.304/0001-06 | C41: Avs Vital Comércio de Tecidos e Resíduos Ltda | D41: Simples Nacional | E41: 148043856114 | F41: São Paulo | G41: 2.321.470-8 | H41: São Paulo | I41: Grupo Vital | J41: Claudia | K41: Não se Aplica | L41: Impresso | M41: 1 | N41: =VLOOKUP(M41,'Controle de Datas'!A:B,2,0) -> 46237 | O41: 46237 | P41: 46237 | Q41: =IF(R41="Não Inicializada",1,IF(R41="Em Andamento",1,IF(R41="Entregue com Atraso",-1,IF(R41="Em Atraso",-1,0)))) -> 0 | R41: =IF(OR(N41="",AND(O41="",P41="")),"Não Inicializada",IF(AND(O41<=N41,P41=""),"Em Andamento",IF(P41>N41,"Entregue com Atraso",IF(O41>N41,"Em Atraso","Entregue")))) -> Entregue | S41: Aprobato Neto
A42: 148 | B42: 31.748.724/0001-41 | C42: B.M.M. Apoio Empresarial Ltda | D42: Simples Nacional | E42: Isenta | F42: São Paulo | G42: 6.094.611-3 | H42: São Paulo | I42: Não se Aplica | J42: Jorge | K42: Não se Aplica | L42: Impresso Aprobato | M42: 6 | N42: =VLOOKUP(M42,'Controle de Datas'!A:B,2,0) -> 46244 | O42: 46248 | P42: 46248 | Q42: =IF(R42="Não Inicializada",1,IF(R42="Em Andamento",1,IF(R42="Entregue com Atraso",-1,IF(R42="Em Atraso",-1,0)))) -> -1 | R42: =IF(OR(N42="",AND(O42="",P42="")),"Não Inicializada",IF(AND(O42<=N42,P42=""),"Em Andamento",IF(P42>N42,"Entregue com Atraso",IF(O42>N42,"Em Atraso","Entregue")))) -> Entregue com Atraso | S42: J P Cont
A43: 512 | B43: 65.934.747/0001-62 | C43: Bar e Lanches Volta Cruzeiro Ltda | D43: Lucro Presumido | E43: Isenta | F43: São Paulo | G43: 9.873.890-9 | H43: São Paulo | I43: Não se Aplica | J43: Claudia | K43: Não se Aplica | L43: Site | M43: 2 | N43: =VLOOKUP(M43,'Controle de Datas'!A:B,2,0) -> 46238 | O43: 46238 | P43: 46238 | Q43: =IF(R43="Não Inicializada",1,IF(R43="Em Andamento",1,IF(R43="Entregue com Atraso",-1,IF(R43="Em Atraso",-1,0)))) -> 0 | R43: =IF(OR(N43="",AND(O43="",P43="")),"Não Inicializada",IF(AND(O43<=N43,P43=""),"Em Andamento",IF(P43>N43,"Entregue com Atraso",IF(O43>N43,"Em Atraso","Entregue")))) -> Entregue | S43: Aprobato Neto
A44: 155 | B44: 32.412.497/0001-41 | C44: Benedito José da Silva 08720320868 | D44: MEI | E44: Isenta | F44: São Paulo | G44: 6.160.432-1 | H44: São Paulo | I44: Não se Aplica | J44: Talita | K44: Não se Aplica | L44: E-mail | M44: 1 | N44: =VLOOKUP(M44,'Controle de Datas'!A:B,2,0) -> 46237 | O44: 46237 | P44: 46237 | Q44: =IF(R44="Não Inicializada",1,IF(R44="Em Andamento",1,IF(R44="Entregue com Atraso",-1,IF(R44="Em Atraso",-1,0)))) -> 0 | R44: =IF(OR(N44="",AND(O44="",P44="")),"Não Inicializada",IF(AND(O44<=N44,P44=""),"Em Andamento",IF(P44>N44,"Entregue com Atraso",IF(O44>N44,"Em Atraso","Entregue")))) -> Entregue | S44: J P Cont
A45: 351 | B45: 47.407.177/0001-70 | C45: Bepass S.A. | D45: Lucro Real | E45: 138210963117 | F45: São Paulo | G45: 7.408.877-7 | H45: São Paulo | I45: Não se Aplica | J45: Talita | K45: Não se Aplica | L45: Site e E-mail | M45: 10 | N45: =VLOOKUP(M45,'Controle de Datas'!A:B,2,0) -> 46248 | O45: 46253 | P45: 46253 | Q45: =IF(R45="Não Inicializada",1,IF(R45="Em Andamento",1,IF(R45="Entregue com Atraso",-1,IF(R45="Em Atraso",-1,0)))) -> -1 | R45: =IF(OR(N45="",AND(O45="",P45="")),"Não Inicializada",IF(AND(O45<=N45,P45=""),"Em Andamento",IF(P45>N45,"Entregue com Atraso",IF(O45>N45,"Em Atraso","Entregue")))) -> Entregue com Atraso | S45: Aprobato Neto
A46: 510 | B46: 55.769.305/0001-54 | C46: Bianca Ribeiro Mattos Ltda | D46: Simples Nacional | E46: Isenta | F46: São Paulo | G46: 1.415.650-4 | H46: São Paulo | I46: Não se Aplica | J46: Claudia | K46: Não se Aplica | L46: E-mail | M46: 6 | N46: =VLOOKUP(M46,'Controle de Datas'!A:B,2,0) -> 46244 | O46: 46244 | P46: 46244 | Q46: =IF(R46="Não Inicializada",1,IF(R46="Em Andamento",1,IF(R46="Entregue com Atraso",-1,IF(R46="Em Atraso",-1,0)))) -> 0 | R46: =IF(OR(N46="",AND(O46="",P46="")),"Não Inicializada",IF(AND(O46<=N46,P46=""),"Em Andamento",IF(P46>N46,"Entregue com Atraso",IF(O46>N46,"Em Atraso","Entregue")))) -> Entregue | S46: J P Cont
A47: 646 | B47: 67.041.408/0001-82 | C47: Bitachon Serviços Administrativos Ltda | D47: Simples Nacional | E47: Isenta | F47: São Paulo | G47: 0.343.044-8 | H47: São Paulo | I47: Não se Aplica | J47: Jorge | K47: Não se Aplica | L47: Site | M47: 8 | N47: =VLOOKUP(M47,'Controle de Datas'!A:B,2,0) -> 46246 | O47: 46248 | P47: 46248 | Q47: =IF(R47="Não Inicializada",1,IF(R47="Em Andamento",1,IF(R47="Entregue com Atraso",-1,IF(R47="Em Atraso",-1,0)))) -> -1 | R47: =IF(OR(N47="",AND(O47="",P47="")),"Não Inicializada",IF(AND(O47<=N47,P47=""),"Em Andamento",IF(P47>N47,"Entregue com Atraso",IF(O47>N47,"Em Atraso","Entregue")))) -> Entregue com Atraso | S47: J P Cont
A48: 542 | B48: 12.107.957/0001-10 | C48: BJ2R Serviços Ltda | D48: Simples Nacional | E48: Isenta | F48: São Paulo | G48: 4.089.322-7 | H48: São Paulo | I48: Grupo KV Equipamentos | J48: Kamilly | K48: Não se Aplica | L48: Site | M48: 6 | N48: =VLOOKUP(M48,'Controle de Datas'!A:B,2,0) -> 46244 | O48: 46241 | P48: 46241 | Q48: =IF(R48="Não Inicializada",1,IF(R48="Em Andamento",1,IF(R48="Entregue com Atraso",-1,IF(R48="Em Atraso",-1,0)))) -> 0 | R48: =IF(OR(N48="",AND(O48="",P48="")),"Não Inicializada",IF(AND(O48<=N48,P48=""),"Em Andamento",IF(P48>N48,"Entregue com Atraso",IF(O48>N48,"Em Atraso","Entregue")))) -> Entregue | S48: Aprobato Neto
A49: 240 | B49: 36.557.666/0001-92 | C49: BLGR Serviços Empresariais Ltda | D49: Simples Nacional | E49: Isenta | F49: São Paulo | G49: 6.546.675-6 | H49: São Paulo | I49: Não se Aplica | J49: Bruna | K49: Não se Aplica | L49: Site | M49: 3 | N49: =VLOOKUP(M49,'Controle de Datas'!A:B,2,0) -> 46239 | O49: 46237 | P49: 46239 | Q49: =IF(R49="Não Inicializada",1,IF(R49="Em Andamento",1,IF(R49="Entregue com Atraso",-1,IF(R49="Em Atraso",-1,0)))) -> 0 | R49: =IF(OR(N49="",AND(O49="",P49="")),"Não Inicializada",IF(AND(O49<=N49,P49=""),"Em Andamento",IF(P49>N49,"Entregue com Atraso",IF(O49>N49,"Em Atraso","Entregue")))) -> Entregue | S49: Aprobato Neto
A50: 486 | B50: 35.048.108/0001-39 | C50: BNC Print Comércio e Soluções Técnicas Ltda | D50: Simples Nacional | E50: 636400626118 | F50: São Paulo | G50: 111044 | H50: São Caetano do Sul | I50: Não se Aplica | J50: Talita | K50: Não se Aplica | L50: Site | M50: 2 | N50: =VLOOKUP(M50,'Controle de Datas'!A:B,2,0) -> 46238 | O50: 46237 | P50: 46237 | Q50: =IF(R50="Não Inicializada",1,IF(R50="Em Andamento",1,IF(R50="Entregue com Atraso",-1,IF(R50="Em Atraso",-1,0)))) -> 0 | R50: =IF(OR(N50="",AND(O50="",P50="")),"Não Inicializada",IF(AND(O50<=N50,P50=""),"Em Andamento",IF(P50>N50,"Entregue com Atraso",IF(O50>N50,"Em Atraso","Entregue")))) -> Entregue | S50: J P Cont
A51: 71 | B51: 08.991.576/0001-70 | C51: Botecaria Distribuição e Marketing Ltda | D51: Lucro Presumido | E51: 149765136110 | F51: São Paulo | G51: 3.661.044-5 | H51: São Paulo | I51: Não se Aplica | J51: Bruna | K51: Não se Aplica | L51: Site | M51: 7 | N51: =VLOOKUP(M51,'Controle de Datas'!A:B,2,0) -> 46245 | O51: 46237 | P51: 46244 | Q51: =IF(R51="Não Inicializada",1,IF(R51="Em Andamento",1,IF(R51="Entregue com Atraso",-1,IF(R51="Em Atraso",-1,0)))) -> 0 | R51: =IF(OR(N51="",AND(O51="",P51="")),"Não Inicializada",IF(AND(O51<=N51,P51=""),"Em Andamento",IF(P51>N51,"Entregue com Atraso",IF(O51>N51,"Em Atraso","Entregue")))) -> Entregue | S51: Aprobato Neto
A52: 458 | B52: 26.635.239/0001-21 | C52: Brunna Vomstein Andrade | D52: Simples Nacional | E52: 636568759110 | F52: São Paulo | G52: 136949 | H52: São Caetano do Sul | I52: Não se Aplica | J52: Bruna | K52: Não se Aplica | L52: Site | M52: 1 | N52: =VLOOKUP(M52,'Controle de Datas'!A:B,2,0) -> 46237 | O52: 46237 | P52: 46238 | Q52: =IF(R52="Não Inicializada",1,IF(R52="Em Andamento",1,IF(R52="Entregue com Atraso",-1,IF(R52="Em Atraso",-1,0)))) -> -1 | R52: =IF(OR(N52="",AND(O52="",P52="")),"Não Inicializada",IF(AND(O52<=N52,P52=""),"Em Andamento",IF(P52>N52,"Entregue com Atraso",IF(O52>N52,"Em Atraso","Entregue")))) -> Entregue com Atraso | S52: J P Cont
A53: 122 | B53: 00.833.464/0001-89 | C53: Buffet Israel Ltda | D53: Simples Nacional | E53: 119427678117 | F53: São Paulo | G53: 2.423.915-1 | H53: São Paulo | I53: Não se Aplica | J53: Kamilly | K53: Não se Aplica | L53: Impresso | M53: 8 | N53: =VLOOKUP(M53,'Controle de Datas'!A:B,2,0) -> 46246 | O53: 46245 | P53: 46245 | Q53: =IF(R53="Não Inicializada",1,IF(R53="Em Andamento",1,IF(R53="Entregue com Atraso",-1,IF(R53="Em Atraso",-1,0)))) -> 0 | R53: =IF(OR(N53="",AND(O53="",P53="")),"Não Inicializada",IF(AND(O53<=N53,P53=""),"Em Andamento",IF(P53>N53,"Entregue com Atraso",IF(O53>N53,"Em Atraso","Entregue")))) -> Entregue | S53: Aprobato Neto
A54: 499 | B54: 57.262.385/0001-82 | C54: C.M.S. Holding Participações Ltda | D54: Lucro Presumido | E54: Isenta | F54: São Paulo | G54: 1.500.665-4 | H54: São Paulo | I54: Grupo Croce Simões | J54: Michele | K54: Não se Aplica | L54: E-mail e Site | M54: 3 | N54: =VLOOKUP(M54,'Controle de Datas'!A:B,2,0) -> 46239 | O54: 46237 | P54: 46240 | Q54: =IF(R54="Não Inicializada",1,IF(R54="Em Andamento",1,IF(R54="Entregue com Atraso",-1,IF(R54="Em Atraso",-1,0)))) -> -1 | R54: =IF(OR(N54="",AND(O54="",P54="")),"Não Inicializada",IF(AND(O54<=N54,P54=""),"Em Andamento",IF(P54>N54,"Entregue com Atraso",IF(O54>N54,"Em Atraso","Entregue")))) -> Entregue com Atraso | S54: J P Cont
A55: 435 | B55: 52.796.465/0001-02 | C55: C2C Ltda | D55: Simples Nacional | E55: Isenta | F55: Minas Gerais | G55: 1.514.760/001-2 | H55: Belo Horizonte | I55: Grupo Indikey Comunicação | J55: Luana | K55: Não se Aplica | L55: Site | M55: 1 | N55: =VLOOKUP(M55,'Controle de Datas'!A:B,2,0) -> 46237 | O55: 46237 | P55: 46238 | Q55: =IF(R55="Não Inicializada",1,IF(R55="Em Andamento",1,IF(R55="Entregue com Atraso",-1,IF(R55="Em Atraso",-1,0)))) -> -1 | R55: =IF(OR(N55="",AND(O55="",P55="")),"Não Inicializada",IF(AND(O55<=N55,P55=""),"Em Andamento",IF(P55>N55,"Entregue com Atraso",IF(O55>N55,"Em Atraso","Entregue")))) -> Entregue com Atraso | S55: J P Cont
A56: 591 | B56: 61.256.978/0001-03 | C56: C3C Corretora de Seguros Ltda | D56: Simples Nacional | E56: Isenta | F56: Minas Gerais | G56: 1.670.852/001-0 | H56: Belo Horizonte | I56: Grupo Indikey Comunicação | J56: Luana | K56: Não se Aplica | L56: Site | M56: 1 | N56: =VLOOKUP(M56,'Controle de Datas'!A:B,2,0) -> 46237 | O56: 46237 | P56: 46238 | Q56: =IF(R56="Não Inicializada",1,IF(R56="Em Andamento",1,IF(R56="Entregue com Atraso",-1,IF(R56="Em Atraso",-1,0)))) -> -1 | R56: =IF(OR(N56="",AND(O56="",P56="")),"Não Inicializada",IF(AND(O56<=N56,P56=""),"Em Andamento",IF(P56>N56,"Entregue com Atraso",IF(O56>N56,"Em Atraso","Entregue")))) -> Entregue com Atraso | S56: J P Cont
A57: 419 | B57: 09.666.095/0001-51 | C57: Calcam Comercial de Suprimentos de Informática Ltda | D57: Simples Nacional | E57: 148185395111 | F57: São Paulo | G57: 3.779.834-0 | H57: São Paulo | I57: Grupo SDJ Comercial | J57: Talita | K57: Não se Aplica | L57: Site | M57: 6 | N57: =VLOOKUP(M57,'Controle de Datas'!A:B,2,0) -> 46244 | O57: 46238 | P57: 46238 | Q57: =IF(R57="Não Inicializada",1,IF(R57="Em Andamento",1,IF(R57="Entregue com Atraso",-1,IF(R57="Em Atraso",-1,0)))) -> 0 | R57: =IF(OR(N57="",AND(O57="",P57="")),"Não Inicializada",IF(AND(O57<=N57,P57=""),"Em Andamento",IF(P57>N57,"Entregue com Atraso",IF(O57>N57,"Em Atraso","Entregue")))) -> Entregue | S57: Aprobato Neto
A58: 273 | B58: 41.118.298/0001-16 | C58: Cami Concept Ltda | D58: Simples Nacional | E58: Isenta | F58: São Paulo | G58: 6.874.610-5 | H58: São Paulo | I58: Não se Aplica | J58: Bruna | K58: Não se Aplica | L58: Site | M58: 2 | N58: =VLOOKUP(M58,'Controle de Datas'!A:B,2,0) -> 46238 | O58: 46237 | P58: 46238 | Q58: =IF(R58="Não Inicializada",1,IF(R58="Em Andamento",1,IF(R58="Entregue com Atraso",-1,IF(R58="Em Atraso",-1,0)))) -> 0 | R58: =IF(OR(N58="",AND(O58="",P58="")),"Não Inicializada",IF(AND(O58<=N58,P58=""),"Em Andamento",IF(P58>N58,"Entregue com Atraso",IF(O58>N58,"Em Atraso","Entregue")))) -> Entregue | S58: Aprobato Neto
A59: 262 | B59: 39.960.783/0001-90 | C59: Capella Comércio e Representações de Produtos Químicos Ltda | D59: Lucro Presumido | E59: 130221210116 | F59: São Paulo | G59: 6.775.077-0 | H59: São Paulo | I59: Não se Aplica | J59: Kamilly | K59: Não se Aplica | L59: Site | M59: 10 | N59: =VLOOKUP(M59,'Controle de Datas'!A:B,2,0) -> 46248 | O59: 46252 | P59: 46252 | Q59: =IF(R59="Não Inicializada",1,IF(R59="Em Andamento",1,IF(R59="Entregue com Atraso",-1,IF(R59="Em Atraso",-1,0)))) -> -1 | R59: =IF(OR(N59="",AND(O59="",P59="")),"Não Inicializada",IF(AND(O59<=N59,P59=""),"Em Andamento",IF(P59>N59,"Entregue com Atraso",IF(O59>N59,"Em Atraso","Entregue")))) -> Entregue com Atraso | S59: Aprobato Neto
A60: 411 | B60: 51.764.963/0001-00 | C60: Caresma & Schmidt Office Consultoria Empresarial Ltda | D60: Simples Nacional | E60: Isenta | F60: São Paulo | G60: 7.800.644-9 | H60: São Paulo | I60: Não se Aplica | J60: Bruna | K60: Não se Aplica | L60: Site e WhatsApp | M60: 5 | N60: =VLOOKUP(M60,'Controle de Datas'!A:B,2,0) -> 46241 | O60: 46237 | P60: 46239 | Q60: =IF(R60="Não Inicializada",1,IF(R60="Em Andamento",1,IF(R60="Entregue com Atraso",-1,IF(R60="Em Atraso",-1,0)))) -> 0 | R60: =IF(OR(N60="",AND(O60="",P60="")),"Não Inicializada",IF(AND(O60<=N60,P60=""),"Em Andamento",IF(P60>N60,"Entregue com Atraso",IF(O60>N60,"Em Atraso","Entregue")))) -> Entregue | S60: Aprobato Neto
A61: 505 | B61: 57.642.648/0001-89 | C61: Carrilho Donas Sociedade Individual de Advocacia | D61: Simples Nacional | E61: Isenta | F61: Distrito Federal | G61: 08.336.234/001-60 | H61: Brasília | I61: Não se Aplica | J61: Bruna | K61: Não se Aplica | L61: Site | M61: 2 | N61: =VLOOKUP(M61,'Controle de Datas'!A:B,2,0) -> 46238 | O61: 46237 | P61: 46239 | Q61: =IF(R61="Não Inicializada",1,IF(R61="Em Andamento",1,IF(R61="Entregue com Atraso",-1,IF(R61="Em Atraso",-1,0)))) -> -1 | R61: =IF(OR(N61="",AND(O61="",P61="")),"Não Inicializada",IF(AND(O61<=N61,P61=""),"Em Andamento",IF(P61>N61,"Entregue com Atraso",IF(O61>N61,"Em Atraso","Entregue")))) -> Entregue com Atraso | S61: J P Cont
A62: 495 | B62: 57.121.049/0001-10 | C62: Cass Consultoria Empresarial Ltda | D62: Simples Nacional | E62: Isenta | F62: São Paulo | G62: 1.489.925-6 | H62: São Paulo | I62: Não se Aplica | J62: Claudia | K62: Não se Aplica | L62: Site | M62: 2 | N62: =VLOOKUP(M62,'Controle de Datas'!A:B,2,0) -> 46238 | O62: 46238 | P62: 46238 | Q62: =IF(R62="Não Inicializada",1,IF(R62="Em Andamento",1,IF(R62="Entregue com Atraso",-1,IF(R62="Em Atraso",-1,0)))) -> 0 | R62: =IF(OR(N62="",AND(O62="",P62="")),"Não Inicializada",IF(AND(O62<=N62,P62=""),"Em Andamento",IF(P62>N62,"Entregue com Atraso",IF(O62>N62,"Em Atraso","Entregue")))) -> Entregue | S62: J P Cont
A63: 293 | B63: 42.638.806/0001-50 | C63: Catedral Intermediação de Negócios Ltda | D63: Simples Nacional | E63: Isenta | F63: São Paulo | G63: 6.991.897-0 | H63: São Paulo | I63: Não se Aplica | J63: Claudia | K63: Não se Aplica | L63: Site | M63: 6 | N63: =VLOOKUP(M63,'Controle de Datas'!A:B,2,0) -> 46244 | O63: 46244 | P63: 46247 | Q63: =IF(R63="Não Inicializada",1,IF(R63="Em Andamento",1,IF(R63="Entregue com Atraso",-1,IF(R63="Em Atraso",-1,0)))) -> -1 | R63: =IF(OR(N63="",AND(O63="",P63="")),"Não Inicializada",IF(AND(O63<=N63,P63=""),"Em Andamento",IF(P63>N63,"Entregue com Atraso",IF(O63>N63,"Em Atraso","Entregue")))) -> Entregue com Atraso | S63: Aprobato Neto
A64: 335 | B64: 13.574.084/0001-19 | C64: CCKids Comércio e Confecção de Roupas e Acessórios Ltda | D64: Simples Nacional | E64: 146011920111 | F64: São Paulo | G64: 4.277.156-0 | H64: São Paulo | I64: Não se Aplica | J64: Luana | K64: Não se Aplica | L64: Site | M64: 4 | N64: =VLOOKUP(M64,'Controle de Datas'!A:B,2,0) -> 46240 | O64: 46240 | P64: 46245 | Q64: =IF(R64="Não Inicializada",1,IF(R64="Em Andamento",1,IF(R64="Entregue com Atraso",-1,IF(R64="Em Atraso",-1,0)))) -> -1 | R64: =IF(OR(N64="",AND(O64="",P64="")),"Não Inicializada",IF(AND(O64<=N64,P64=""),"Em Andamento",IF(P64>N64,"Entregue com Atraso",IF(O64>N64,"Em Atraso","Entregue")))) -> Entregue com Atraso | S64: Aprobato Neto
A65: 372 | B65: 50.685.261/0001-60 | C65: CDM Holding Ltda | D65: Lucro Presumido | E65: Isenta | F65: São Paulo | G65: 7.699.823-1 | H65: São Paulo | I65: Grupo Mobel Engenharia | J65: Kamilly | K65: Não se Aplica | L65: E-mail | M65: 5 | N65: =VLOOKUP(M65,'Controle de Datas'!A:B,2,0) -> 46241 | O65: 46239 | P65: 46239 | Q65: =IF(R65="Não Inicializada",1,IF(R65="Em Andamento",1,IF(R65="Entregue com Atraso",-1,IF(R65="Em Atraso",-1,0)))) -> 0 | R65: =IF(OR(N65="",AND(O65="",P65="")),"Não Inicializada",IF(AND(O65<=N65,P65=""),"Em Andamento",IF(P65>N65,"Entregue com Atraso",IF(O65>N65,"Em Atraso","Entregue")))) -> Entregue | S65: Aprobato Neto
A66: 398 | B66: 03.702.166/0001-48 | C66: Cena Cultural Produções Ltda | D66: Lucro Presumido | E66: Isenta | F66: São Paulo | G66: 2.886.451-4 | H66: São Paulo | I66: Não se Aplica | J66: Claudia | K66: Não se Aplica | L66: Site | M66: 2 | N66: =VLOOKUP(M66,'Controle de Datas'!A:B,2,0) -> 46238 | O66: 46238 | P66: 46238 | Q66: =IF(R66="Não Inicializada",1,IF(R66="Em Andamento",1,IF(R66="Entregue com Atraso",-1,IF(R66="Em Atraso",-1,0)))) -> 0 | R66: =IF(OR(N66="",AND(O66="",P66="")),"Não Inicializada",IF(AND(O66<=N66,P66=""),"Em Andamento",IF(P66>N66,"Entregue com Atraso",IF(O66>N66,"Em Atraso","Entregue")))) -> Entregue | S66: Aprobato Neto
A67: 321 | B67: 59.650.721/0001-90 | C67: Central Serviços Médicos Ltda | D67: Lucro Presumido | E67: Isenta | F67: São Paulo | G67: 57123 | H67: Guarulhos | I67: Não se Aplica | J67: Talita | K67: Não se Aplica | L67: Site | M67: 7 | N67: =VLOOKUP(M67,'Controle de Datas'!A:B,2,0) -> 46245 | O67: 46254 | P67: 46254 | Q67: =IF(R67="Não Inicializada",1,IF(R67="Em Andamento",1,IF(R67="Entregue com Atraso",-1,IF(R67="Em Atraso",-1,0)))) -> -1 | R67: =IF(OR(N67="",AND(O67="",P67="")),"Não Inicializada",IF(AND(O67<=N67,P67=""),"Em Andamento",IF(P67>N67,"Entregue com Atraso",IF(O67>N67,"Em Atraso","Entregue")))) -> Entregue com Atraso | S67: Aprobato Neto
A68: 449 | B68: 10.665.359/0001-31 | C68: Centro de Saúde Animal Zoovet Ltda | D68: Lucro Presumido | E68: Isenta | F68: São Paulo | G68: 3.886.732-0 | H68: São Paulo | I68: Grupo Zoovet Veterinário | J68: Talita | K68: Não se Aplica | L68: Site | M68: 4 | N68: =VLOOKUP(M68,'Controle de Datas'!A:B,2,0) -> 46240 | O68: 46254 | P68: 46254 | Q68: =IF(R68="Não Inicializada",1,IF(R68="Em Andamento",1,IF(R68="Entregue com Atraso",-1,IF(R68="Em Atraso",-1,0)))) -> -1 | R68: =IF(OR(N68="",AND(O68="",P68="")),"Não Inicializada",IF(AND(O68<=N68,P68=""),"Em Andamento",IF(P68>N68,"Entregue com Atraso",IF(O68>N68,"Em Atraso","Entregue")))) -> Entregue com Atraso | S68: Aprobato Neto
A69: 730 | B69: 65.887.267/0001-98 | C69: Chipendalle Arte Móveis Ltda | D69: Simples Nacional | E69: Isenta | F69: São Paulo | G69: 9.905.758-1 | H69: São Paulo | I69: Não se Aplica | J69: Jorge | K69: Não se Aplica | L69: Site | M69: 2 | N69: =VLOOKUP(M69,'Controle de Datas'!A:B,2,0) -> 46238 | O69: 46248 | P69: 46248 | Q69: =IF(R69="Não Inicializada",1,IF(R69="Em Andamento",1,IF(R69="Entregue com Atraso",-1,IF(R69="Em Atraso",-1,0)))) -> -1 | R69: =IF(OR(N69="",AND(O69="",P69="")),"Não Inicializada",IF(AND(O69<=N69,P69=""),"Em Andamento",IF(P69>N69,"Entregue com Atraso",IF(O69>N69,"Em Atraso","Entregue")))) -> Entregue com Atraso | S69: Aprobato Neto
A70: 365 | B70: 34.329.315/0001-07 | C70: CJS Comércio Varejista de Tecidos Ltda | D70: Simples Nacional | E70: 558510441112 | F70: São Paulo | G70: 584789 | H70: Praia Grande | I70: Não se Aplica | J70: Bruna | K70: Não se Aplica | L70: E-mail | M70: 7 | N70: =VLOOKUP(M70,'Controle de Datas'!A:B,2,0) -> 46245 | O70: 46237 | P70: 46246 | Q70: =IF(R70="Não Inicializada",1,IF(R70="Em Andamento",1,IF(R70="Entregue com Atraso",-1,IF(R70="Em Atraso",-1,0)))) -> -1 | R70: =IF(OR(N70="",AND(O70="",P70="")),"Não Inicializada",IF(AND(O70<=N70,P70=""),"Em Andamento",IF(P70>N70,"Entregue com Atraso",IF(O70>N70,"Em Atraso","Entregue")))) -> Entregue com Atraso | S70: J P Cont
A71: 365 (-2) | B71: 34.329.315/0002-80 | C71: CJS Comércio Varejista de Tecidos Ltda | D71: Simples Nacional | E71: 127991611111 | F71: São Paulo | G71: 619539 | H71: Guarulhos | I71: Não se Aplica | J71: Bruna | K71: Não se Aplica | L71: E-mail | M71: 7 | N71: =VLOOKUP(M71,'Controle de Datas'!A:B,2,0) -> 46245 | O71: 46237 | P71: 46246 | Q71: =IF(R71="Não Inicializada",1,IF(R71="Em Andamento",1,IF(R71="Entregue com Atraso",-1,IF(R71="Em Atraso",-1,0)))) -> -1 | R71: =IF(OR(N71="",AND(O71="",P71="")),"Não Inicializada",IF(AND(O71<=N71,P71=""),"Em Andamento",IF(P71>N71,"Entregue com Atraso",IF(O71>N71,"Em Atraso","Entregue")))) -> Entregue com Atraso | S71: J P Cont
A72: 365 (-3) | B72: 34.329.315/0003-60 | C72: CJS Comércio Varejista de Tecidos Ltda | D72: Simples Nacional | E72: 558927031110 | F72: São Paulo | G72: Isenta | H72: Praia Grande | I72: Não se Aplica | J72: Bruna | K72: Não se Aplica | L72: E-mail | M72: 7 | N72: =VLOOKUP(M72,'Controle de Datas'!A:B,2,0) -> 46245 | O72: 46237 | P72: 46246 | Q72: =IF(R72="Não Inicializada",1,IF(R72="Em Andamento",1,IF(R72="Entregue com Atraso",-1,IF(R72="Em Atraso",-1,0)))) -> -1 | R72: =IF(OR(N72="",AND(O72="",P72="")),"Não Inicializada",IF(AND(O72<=N72,P72=""),"Em Andamento",IF(P72>N72,"Entregue com Atraso",IF(O72>N72,"Em Atraso","Entregue")))) -> Entregue com Atraso | S72: J P Cont
A73: 408 | B73: 48.292.179/0001-24 | C73: CLE Comunicação Liderança e Educação Ltda | D73: Simples Nacional | E73: Isenta | F73: São Paulo | G73: 7.486.197-2 | H73: São Paulo | I73: Não se Aplica | J73: Luana | K73: Não se Aplica | L73: E-mail | M73: 3 | N73: =VLOOKUP(M73,'Controle de Datas'!A:B,2,0) -> 46239 | O73: 46238 | P73: 46238 | Q73: =IF(R73="Não Inicializada",1,IF(R73="Em Andamento",1,IF(R73="Entregue com Atraso",-1,IF(R73="Em Atraso",-1,0)))) -> 0 | R73: =IF(OR(N73="",AND(O73="",P73="")),"Não Inicializada",IF(AND(O73<=N73,P73=""),"Em Andamento",IF(P73>N73,"Entregue com Atraso",IF(O73>N73,"Em Atraso","Entregue")))) -> Entregue | S73: J P Cont
A74: 402 | B74: 03.754.180/0001-95 | C74: Clínica de Ortopedia Dr. Javier V. S. Vargas Ltda | D74: Lucro Presumido | E74: Isenta | F74: São Paulo | G74: 2.900.531-0 | H74: São Paulo | I74: Não se Aplica | J74: Kamilly | K74: Não se Aplica | L74: Impresso | M74: 5 | N74: =VLOOKUP(M74,'Controle de Datas'!A:B,2,0) -> 46241 | O74: 46239 | P74: 46239 | Q74: =IF(R74="Não Inicializada",1,IF(R74="Em Andamento",1,IF(R74="Entregue com Atraso",-1,IF(R74="Em Atraso",-1,0)))) -> 0 | R74: =IF(OR(N74="",AND(O74="",P74="")),"Não Inicializada",IF(AND(O74<=N74,P74=""),"Em Andamento",IF(P74>N74,"Entregue com Atraso",IF(O74>N74,"Em Atraso","Entregue")))) -> Entregue | S74: Aprobato Neto
A75: 393 | B75: 03.541.023/0001-00 | C75: Clínica Dr. Eduardo de Souza Ltda | D75: Lucro Presumido | E75: Isenta | F75: São Paulo | G75: 2.861.253-1 | H75: São Paulo | I75: Não se Aplica | J75: Luana | K75: Não se Aplica | L75: E-mail | M75: 3 | N75: =VLOOKUP(M75,'Controle de Datas'!A:B,2,0) -> 46239 | O75: 46239 | P75: 46239 | Q75: =IF(R75="Não Inicializada",1,IF(R75="Em Andamento",1,IF(R75="Entregue com Atraso",-1,IF(R75="Em Atraso",-1,0)))) -> 0 | R75: =IF(OR(N75="",AND(O75="",P75="")),"Não Inicializada",IF(AND(O75<=N75,P75=""),"Em Andamento",IF(P75>N75,"Entregue com Atraso",IF(O75>N75,"Em Atraso","Entregue")))) -> Entregue | S75: Aprobato Neto
A76: 420 | B76: 52.145.726/0001-16 | C76: Comércio Estético Maison Hair Ltda | D76: Simples Nacional | E76: Isenta | F76: São Paulo | G76: 7.837.687-4 | H76: São Paulo | I76: Não se Aplica | J76: Jorge | K76: Não se Aplica | L76: E-mail | M76: 1 | N76: =VLOOKUP(M76,'Controle de Datas'!A:B,2,0) -> 46237 | O76: 46248 | P76: 46248 | Q76: =IF(R76="Não Inicializada",1,IF(R76="Em Andamento",1,IF(R76="Entregue com Atraso",-1,IF(R76="Em Atraso",-1,0)))) -> -1 | R76: =IF(OR(N76="",AND(O76="",P76="")),"Não Inicializada",IF(AND(O76<=N76,P76=""),"Em Andamento",IF(P76>N76,"Entregue com Atraso",IF(O76>N76,"Em Atraso","Entregue")))) -> Entregue com Atraso | S76: J P Cont
A77: 187 | B77: 34.504.701/0001-80 | C77: Comuniverse Ltda | D77: Lucro Real | E77: Isenta | F77: São Paulo | G77: 6.360.748-4 | H77: São Paulo | I77: Não se Aplica | J77: Michele | K77: Não se Aplica | L77: Site | M77: 10 | N77: =VLOOKUP(M77,'Controle de Datas'!A:B,2,0) -> 46248 | O77: 46238 | P77: 46238 | Q77: =IF(R77="Não Inicializada",1,IF(R77="Em Andamento",1,IF(R77="Entregue com Atraso",-1,IF(R77="Em Atraso",-1,0)))) -> 0 | R77: =IF(OR(N77="",AND(O77="",P77="")),"Não Inicializada",IF(AND(O77<=N77,P77=""),"Em Andamento",IF(P77>N77,"Entregue com Atraso",IF(O77>N77,"Em Atraso","Entregue")))) -> Entregue | S77: Aprobato Neto
A78: 476 | B78: 03.951.113/0001-60 | C78: Condor Instituto de Psicologia e Pesquisa SS Ltda | D78: Lucro Presumido | E78: Isenta | F78: São Paulo | G78: 2.933.349-0 | H78: São Paulo | I78: Não se Aplica | J78: Talita | K78: Não se Aplica | L78: Site | M78: 4 | N78: =VLOOKUP(M78,'Controle de Datas'!A:B,2,0) -> 46240 | O78: 46254 | P78: 46254 | Q78: =IF(R78="Não Inicializada",1,IF(R78="Em Andamento",1,IF(R78="Entregue com Atraso",-1,IF(R78="Em Atraso",-1,0)))) -> -1 | R78: =IF(OR(N78="",AND(O78="",P78="")),"Não Inicializada",IF(AND(O78<=N78,P78=""),"Em Andamento",IF(P78>N78,"Entregue com Atraso",IF(O78>N78,"Em Atraso","Entregue")))) -> Entregue com Atraso | S78: Aprobato Neto
A79: 128 | B79: 06.347.712/0001-68 | C79: Confederação Brasileira de Empresas Juniores | D79: Lucro Real | E79: Isenta | F79: São Paulo | G79: 5.948.129-3 | H79: São Paulo | I79: Não se Aplica | J79: Kamilly | K79: Não se Aplica | L79: Site e E-mail | M79: 5 | N79: =VLOOKUP(M79,'Controle de Datas'!A:B,2,0) -> 46241 | O79: 46237 | P79: 46239 | Q79: =IF(R79="Não Inicializada",1,IF(R79="Em Andamento",1,IF(R79="Entregue com Atraso",-1,IF(R79="Em Atraso",-1,0)))) -> 0 | R79: =IF(OR(N79="",AND(O79="",P79="")),"Não Inicializada",IF(AND(O79<=N79,P79=""),"Em Andamento",IF(P79>N79,"Entregue com Atraso",IF(O79>N79,"Em Atraso","Entregue")))) -> Entregue | S79: Aprobato Neto
A80: 590 | B80: 61.158.615/0001-35 | C80: Convox Negócios e Serviços Ltda | D80: Simples Nacional | E80: Isenta | F80: São Paulo | G80: 1.856.461-5 | H80: São Paulo | I80: Não se Aplica | J80: Talita | K80: Não se Aplica | L80: Site | M80: 1 | N80: =VLOOKUP(M80,'Controle de Datas'!A:B,2,0) -> 46237 | O80: 46237 | P80: 46237 | Q80: =IF(R80="Não Inicializada",1,IF(R80="Em Andamento",1,IF(R80="Entregue com Atraso",-1,IF(R80="Em Atraso",-1,0)))) -> 0 | R80: =IF(OR(N80="",AND(O80="",P80="")),"Não Inicializada",IF(AND(O80<=N80,P80=""),"Em Andamento",IF(P80>N80,"Entregue com Atraso",IF(O80>N80,"Em Atraso","Entregue")))) -> Entregue | S80: J P Cont
A81: 621 | B81: 42.657.808/0001-96 | C81: Corcovado Investimentos Gestão de Recursos Ltda | D81: Simples Nacional | E81: Isenta | F81: Rio de Janeiro | G81: 13.230.12-9 | H81: Rio de Janeiro | I81: Não se Aplica | J81: Michele | K81: Não se Aplica | L81: Site | M81: 6 | N81: =VLOOKUP(M81,'Controle de Datas'!A:B,2,0) -> 46244 | O81: 46237 | P81: 46246 | Q81: =IF(R81="Não Inicializada",1,IF(R81="Em Andamento",1,IF(R81="Entregue com Atraso",-1,IF(R81="Em Atraso",-1,0)))) -> -1 | R81: =IF(OR(N81="",AND(O81="",P81="")),"Não Inicializada",IF(AND(O81<=N81,P81=""),"Em Andamento",IF(P81>N81,"Entregue com Atraso",IF(O81>N81,"Em Atraso","Entregue")))) -> Entregue com Atraso | S81: J P Cont
A82: 23 | B82: 45.953.312/0001-58 | C82: Cristal Prime Auto Vidros e Acessórios Ltda | D82: Simples Nacional | E82: 143880591118 | F82: São Paulo | G82: 5.077.130-2 | H82: São Paulo | I82: Grupo Hocar Comércio | J82: Kamilly | K82: Não se Aplica | L82: Site | M82: 2 | N82: =VLOOKUP(M82,'Controle de Datas'!A:B,2,0) -> 46238 | O82: 46238 | P82: 46238 | Q82: =IF(R82="Não Inicializada",1,IF(R82="Em Andamento",1,IF(R82="Entregue com Atraso",-1,IF(R82="Em Atraso",-1,0)))) -> 0 | R82: =IF(OR(N82="",AND(O82="",P82="")),"Não Inicializada",IF(AND(O82<=N82,P82=""),"Em Andamento",IF(P82>N82,"Entregue com Atraso",IF(O82>N82,"Em Atraso","Entregue")))) -> Entregue | S82: Aprobato Neto
A83: 137 | B83: 00.569.062/0001-19 | C83: Cristaltech Auto Vidros e Acessorios Ltda | D83: Lucro Presumido | E83: 114389183119 | F83: São Paulo | G83: 2.351.717-4 | H83: São Paulo | I83: Grupo Hocar Comércio | J83: Kamilly | K83: Não se Aplica | L83: Site | M83: 9 | N83: =VLOOKUP(M83,'Controle de Datas'!A:B,2,0) -> 46247 | O83: 46247 | P83: 46247 | Q83: =IF(R83="Não Inicializada",1,IF(R83="Em Andamento",1,IF(R83="Entregue com Atraso",-1,IF(R83="Em Atraso",-1,0)))) -> 0 | R83: =IF(OR(N83="",AND(O83="",P83="")),"Não Inicializada",IF(AND(O83<=N83,P83=""),"Em Andamento",IF(P83>N83,"Entregue com Atraso",IF(O83>N83,"Em Atraso","Entregue")))) -> Entregue | S83: Aprobato Neto
A84: 137 (-2) | B84: 00.569.062/0002-08 | C84: Cristaltech Auto Vidros e Acessorios Ltda | D84: Lucro Presumido | E84: 635779950110 | F84: São Paulo | G84: 231979 | H84: São Bernardo do Campo | I84: Grupo Hocar Comércio | J84: Kamilly | K84: Não se Aplica | L84: Site | M84: 9 | N84: =VLOOKUP(M84,'Controle de Datas'!A:B,2,0) -> 46247 | O84: 46239 | P84: 46239 | Q84: =IF(R84="Não Inicializada",1,IF(R84="Em Andamento",1,IF(R84="Entregue com Atraso",-1,IF(R84="Em Atraso",-1,0)))) -> 0 | R84: =IF(OR(N84="",AND(O84="",P84="")),"Não Inicializada",IF(AND(O84<=N84,P84=""),"Em Andamento",IF(P84>N84,"Entregue com Atraso",IF(O84>N84,"Em Atraso","Entregue")))) -> Entregue | S84: Aprobato Neto
A85: 494 | B85: 56.778.834/0001-87 | C85: Croce Simões Holding Ltda | D85: Lucro Presumido | E85: Isenta | F85: São Paulo | G85: 1.463.586-0 | H85: São Paulo | I85: Grupo Croce Simões | J85: Michele | K85: Não se Aplica | L85: E-mail e Site | M85: 3 | N85: =VLOOKUP(M85,'Controle de Datas'!A:B,2,0) -> 46239 | O85: 46237 | P85: 46240 | Q85: =IF(R85="Não Inicializada",1,IF(R85="Em Andamento",1,IF(R85="Entregue com Atraso",-1,IF(R85="Em Atraso",-1,0)))) -> -1 | R85: =IF(OR(N85="",AND(O85="",P85="")),"Não Inicializada",IF(AND(O85<=N85,P85=""),"Em Andamento",IF(P85>N85,"Entregue com Atraso",IF(O85>N85,"Em Atraso","Entregue")))) -> Entregue com Atraso | S85: J P Cont
A86: 308 | B86: 18.587.752/0001-66 | C86: Crysthiane Henrique de Matos Gonçalves Tripode | D86: MEI | E86: 142641496112 | F86: São Paulo | G86: 4.807.198-6 | H86: São Paulo | I86: Grupo Ibel Maq | J86: Michele | K86: Não se Aplica | L86: Site | M86: 1 | N86: =VLOOKUP(M86,'Controle de Datas'!A:B,2,0) -> 46237 | O86: 46237 | P86: 46237 | Q86: =IF(R86="Não Inicializada",1,IF(R86="Em Andamento",1,IF(R86="Entregue com Atraso",-1,IF(R86="Em Atraso",-1,0)))) -> 0 | R86: =IF(OR(N86="",AND(O86="",P86="")),"Não Inicializada",IF(AND(O86<=N86,P86=""),"Em Andamento",IF(P86>N86,"Entregue com Atraso",IF(O86>N86,"Em Atraso","Entregue")))) -> Entregue | S86: Aprobato Neto
A87: 557 | B87: 39.940.308/0001-52 | C87: Dataind Tecnologia de Informação Ltda | D87: Lucro Real | E87: Isenta | F87: São Paulo | G87: 3370100 | H87: Barueri | I87: Grupo Tixe Participações | J87: Jorge | K87: Não se Aplica | L87: E-mail | M87: 5 | N87: =VLOOKUP(M87,'Controle de Datas'!A:B,2,0) -> 46241 | O87: 46241 | P87: 46241 | Q87: =IF(R87="Não Inicializada",1,IF(R87="Em Andamento",1,IF(R87="Entregue com Atraso",-1,IF(R87="Em Atraso",-1,0)))) -> 0 | R87: =IF(OR(N87="",AND(O87="",P87="")),"Não Inicializada",IF(AND(O87<=N87,P87=""),"Em Andamento",IF(P87>N87,"Entregue com Atraso",IF(O87>N87,"Em Atraso","Entregue")))) -> Entregue | S87: Aprobato Neto
A88: 181 | B88: 00.575.747/0001-78 | C88: Davos Consult Serviços de Apoio Empresarial Ltda | D88: Simples Nacional | E88: 708378532111 | F88: São Paulo | G88: 2.352.524-0 | H88: Valinhos | I88: Não se Aplica | J88: Jorge | K88: Não se Aplica | L88: Site e WhatsApp | M88: 6 | N88: =VLOOKUP(M88,'Controle de Datas'!A:B,2,0) -> 46244 | O88: 46248 | P88: 46248 | Q88: =IF(R88="Não Inicializada",1,IF(R88="Em Andamento",1,IF(R88="Entregue com Atraso",-1,IF(R88="Em Atraso",-1,0)))) -> -1 | R88: =IF(OR(N88="",AND(O88="",P88="")),"Não Inicializada",IF(AND(O88<=N88,P88=""),"Em Andamento",IF(P88>N88,"Entregue com Atraso",IF(O88>N88,"Em Atraso","Entregue")))) -> Entregue com Atraso | S88: Aprobato Neto
A89: 272 | B89: 40.915.081/0001-74 | C89: DBM Consultoria e Participações Ltda | D89: Simples Nacional | E89: Isenta | F89: São Paulo | G89: 6.853.388-8 | H89: São Paulo | I89: Não se Aplica | J89: Claudia | K89: Não se Aplica | L89: Site | M89: 3 | N89: =VLOOKUP(M89,'Controle de Datas'!A:B,2,0) -> 46239 | O89: 46239 | P89: 46239 | Q89: =IF(R89="Não Inicializada",1,IF(R89="Em Andamento",1,IF(R89="Entregue com Atraso",-1,IF(R89="Em Atraso",-1,0)))) -> 0 | R89: =IF(OR(N89="",AND(O89="",P89="")),"Não Inicializada",IF(AND(O89<=N89,P89=""),"Em Andamento",IF(P89>N89,"Entregue com Atraso",IF(O89>N89,"Em Atraso","Entregue")))) -> Entregue | S89: Aprobato Neto
A90: 367 | B90: 50.231.188/0001-57 | C90: Decor Adesivos e Decoração Ltda | D90: Simples Nacional | E90: 138939616118 | F90: São Paulo | G90: 7.660.657-0 | H90: São Paulo | I90: Grupo Decor Adesivos | J90: Talita | K90: Não se Aplica | L90: Site | M90: 5 | N90: =VLOOKUP(M90,'Controle de Datas'!A:B,2,0) -> 46241 | O90: 46253 | P90: 46253 | Q90: =IF(R90="Não Inicializada",1,IF(R90="Em Andamento",1,IF(R90="Entregue com Atraso",-1,IF(R90="Em Atraso",-1,0)))) -> -1 | R90: =IF(OR(N90="",AND(O90="",P90="")),"Não Inicializada",IF(AND(O90<=N90,P90=""),"Em Andamento",IF(P90>N90,"Entregue com Atraso",IF(O90>N90,"Em Atraso","Entregue")))) -> Entregue com Atraso | S90: J P Cont
A91: 254 | B91: 27.532.933/0001-86 | C91: Decor Revestimentos Adesivos Ltda | D91: Simples Nacional | E91: 141959492111 | F91: São Paulo | G91: 5.688.813-9 | H91: São Paulo | I91: Grupo Decor Adesivos | J91: Talita | K91: Não se Aplica | L91: Site | M91: 5 | N91: =VLOOKUP(M91,'Controle de Datas'!A:B,2,0) -> 46241 | O91: 46254 | P91: 46254 | Q91: =IF(R91="Não Inicializada",1,IF(R91="Em Andamento",1,IF(R91="Entregue com Atraso",-1,IF(R91="Em Atraso",-1,0)))) -> -1 | R91: =IF(OR(N91="",AND(O91="",P91="")),"Não Inicializada",IF(AND(O91<=N91,P91=""),"Em Andamento",IF(P91>N91,"Entregue com Atraso",IF(O91>N91,"Em Atraso","Entregue")))) -> Entregue com Atraso | S91: Aprobato Neto
A92: 6 | B92: 16.952.792/0001-34 | C92: Delta Geradores Ltda | D92: Simples Nacional | E92: Isenta | F92: São Paulo | G92: 4.610.430-5 | H92: São Paulo | I92: Não se Aplica | J92: Jorge | K92: Não se Aplica | L92: E-mail | M92: 6 | N92: =VLOOKUP(M92,'Controle de Datas'!A:B,2,0) -> 46244 | O92: 46248 | P92: 46248 | Q92: =IF(R92="Não Inicializada",1,IF(R92="Em Andamento",1,IF(R92="Entregue com Atraso",-1,IF(R92="Em Atraso",-1,0)))) -> -1 | R92: =IF(OR(N92="",AND(O92="",P92="")),"Não Inicializada",IF(AND(O92<=N92,P92=""),"Em Andamento",IF(P92>N92,"Entregue com Atraso",IF(O92>N92,"Em Atraso","Entregue")))) -> Entregue com Atraso | S92: Aprobato Neto
A93: 113 | B93: 27.372.837/0001-18 | C93: Delta Suporte em Vendas Ltda | D93: Simples Nacional | E93: Isenta | F93: São Paulo | G93: 5.681.026-1 | H93: São Paulo | I93: Não se Aplica | J93: Claudia | K93: Não se Aplica | L93: E-mail | M93: 2 | N93: =VLOOKUP(M93,'Controle de Datas'!A:B,2,0) -> 46238 | O93: 46238 | P93: 46238 | Q93: =IF(R93="Não Inicializada",1,IF(R93="Em Andamento",1,IF(R93="Entregue com Atraso",-1,IF(R93="Em Atraso",-1,0)))) -> 0 | R93: =IF(OR(N93="",AND(O93="",P93="")),"Não Inicializada",IF(AND(O93<=N93,P93=""),"Em Andamento",IF(P93>N93,"Entregue com Atraso",IF(O93>N93,"Em Atraso","Entregue")))) -> Entregue | S93: Aprobato Neto
A94: 145 | B94: 31.496.077/0001-28 | C94: Denis Calazans Cordeiro | D94: Simples Nacional | E94: 119966904110 | F94: São Paulo | G94: 6.073.103-6 | H94: São Paulo | I94: Grupo Serralheria Cordeiro | J94: Luana | K94: Não se Aplica | L94: Site | M94: 6 | N94: =VLOOKUP(M94,'Controle de Datas'!A:B,2,0) -> 46244 | O94: 46252 | P94: 46252 | Q94: =IF(R94="Não Inicializada",1,IF(R94="Em Andamento",1,IF(R94="Entregue com Atraso",-1,IF(R94="Em Atraso",-1,0)))) -> -1 | R94: =IF(OR(N94="",AND(O94="",P94="")),"Não Inicializada",IF(AND(O94<=N94,P94=""),"Em Andamento",IF(P94>N94,"Entregue com Atraso",IF(O94>N94,"Em Atraso","Entregue")))) -> Entregue com Atraso | S94: Aprobato Neto
A95: 640 | B95: 33.032.171/0001-51 | C95: DHM Engenharia Ltda | D95: Lucro Presumido | E95: Isenta | F95: Pernambuco | G95: 6378331 | H95: Recife | I95: Não se Aplica | J95: Talita | K95: Não se Aplica | L95: Site | M95: 4 | N95: =VLOOKUP(M95,'Controle de Datas'!A:B,2,0) -> 46240 | O95: 46247 | P95: 46247 | Q95: =IF(R95="Não Inicializada",1,IF(R95="Em Andamento",1,IF(R95="Entregue com Atraso",-1,IF(R95="Em Atraso",-1,0)))) -> -1 | R95: =IF(OR(N95="",AND(O95="",P95="")),"Não Inicializada",IF(AND(O95<=N95,P95=""),"Em Andamento",IF(P95>N95,"Entregue com Atraso",IF(O95>N95,"Em Atraso","Entregue")))) -> Entregue com Atraso | S95: J P Cont
A96: 103 | B96: 26.025.480/0001-39 | C96: Diógenes Prado Batista Sociedade Individual de Advocacia | D96: Simples Nacional | E96: Isenta | F96: São Paulo | G96: 5.548.557-0 | H96: São Paulo | I96: Não se Aplica | J96: Jorge | K96: Não se Aplica | L96: E-mail | M96: 5 | N96: =VLOOKUP(M96,'Controle de Datas'!A:B,2,0) -> 46241 | O96: 46248 | P96: 46248 | Q96: =IF(R96="Não Inicializada",1,IF(R96="Em Andamento",1,IF(R96="Entregue com Atraso",-1,IF(R96="Em Atraso",-1,0)))) -> -1 | R96: =IF(OR(N96="",AND(O96="",P96="")),"Não Inicializada",IF(AND(O96<=N96,P96=""),"Em Andamento",IF(P96>N96,"Entregue com Atraso",IF(O96>N96,"Em Atraso","Entregue")))) -> Entregue com Atraso | S96: Aprobato Neto
A97: 550 | B97: 12.591.454/0001-63 | C97: Direct Advice Serviços Empresariais Ltda | D97: Lucro Presumido | E97: Isenta | F97: São Paulo | G97: 4.146.045-6 | H97: São Paulo | I97: Não se Aplica | J97: Bruna | K97: Não se Aplica | L97: Site | M97: 2 | N97: =VLOOKUP(M97,'Controle de Datas'!A:B,2,0) -> 46238 | O97: 46237 | P97: 46238 | Q97: =IF(R97="Não Inicializada",1,IF(R97="Em Andamento",1,IF(R97="Entregue com Atraso",-1,IF(R97="Em Atraso",-1,0)))) -> 0 | R97: =IF(OR(N97="",AND(O97="",P97="")),"Não Inicializada",IF(AND(O97<=N97,P97=""),"Em Andamento",IF(P97>N97,"Entregue com Atraso",IF(O97>N97,"Em Atraso","Entregue")))) -> Entregue | S97: Aprobato Neto
A98: 169 | B98: 14.627.752/0001-91 | C98: Direction Solução em Serviços Administrativos Ltda | D98: Simples Nacional | E98: Isenta | F98: São Paulo | G98: 4.416.153-0 | H98: São Paulo | I98: Não se Aplica | J98: Bruna | K98: Não se Aplica | L98: Site | M98: 3 | N98: =VLOOKUP(M98,'Controle de Datas'!A:B,2,0) -> 46239 | O98: 46237 | P98: 46239 | Q98: =IF(R98="Não Inicializada",1,IF(R98="Em Andamento",1,IF(R98="Entregue com Atraso",-1,IF(R98="Em Atraso",-1,0)))) -> 0 | R98: =IF(OR(N98="",AND(O98="",P98="")),"Não Inicializada",IF(AND(O98<=N98,P98=""),"Em Andamento",IF(P98>N98,"Entregue com Atraso",IF(O98>N98,"Em Atraso","Entregue")))) -> Entregue | S98: Aprobato Neto
A99: 643 | B99: 66.673.761/0001-12 | C99: DLS Serviços de Tecnologia Ltda | D99: Simples Nacional | E99: 159659366117 | F99: São Paulo | G99: 0.311.426-0 | H99: São Paulo | I99: Não se Aplica | J99: Kamilly | K99: Não se Aplica | L99: Site | M99: 8 | N99: =VLOOKUP(M99,'Controle de Datas'!A:B,2,0) -> 46246 | O99: 46244 | P99: 46244 | Q99: =IF(R99="Não Inicializada",1,IF(R99="Em Andamento",1,IF(R99="Entregue com Atraso",-1,IF(R99="Em Atraso",-1,0)))) -> 0 | R99: =IF(OR(N99="",AND(O99="",P99="")),"Não Inicializada",IF(AND(O99<=N99,P99=""),"Em Andamento",IF(P99>N99,"Entregue com Atraso",IF(O99>N99,"Em Atraso","Entregue")))) -> Entregue | S99: J P Cont
A100: 585 | B100: 61.054.759/0001-41 | C100: Doces da Lu Lu Ltda | D100: Simples Nacional | E100: 154244707118 | F100: São Paulo | G100: 1.838.571-0 | H100: São Paulo | I100: Grupo Lu Lu | J100: Claudia | K100: Não se Aplica | L100: Site | M100: 10 | N100: =VLOOKUP(M100,'Controle de Datas'!A:B,2,0) -> 46248 | O100: 46246 | P100: 46246 | Q100: =IF(R100="Não Inicializada",1,IF(R100="Em Andamento",1,IF(R100="Entregue com Atraso",-1,IF(R100="Em Atraso",-1,0)))) -> 0 | R100: =IF(OR(N100="",AND(O100="",P100="")),"Não Inicializada",IF(AND(O100<=N100,P100=""),"Em Andamento",IF(P100>N100,"Entregue com Atraso",IF(O100>N100,"Em Atraso","Entregue")))) -> Entregue | S100: J P Cont
...

Sheet Planilha1

Sheet Municipais
A1: Código | B1: CNPJ | C1: Razão Social | D1: Tributação | E1: Usuário | F1: Município | G1: Vencimento TFE | H1: Inscrição Municipal | I1: Senha Prefeitura | J1: Vencto. ISS | K1: ISSQN | M1: Escrit. Prefeitura | N1: DSUP | O1: Imunidades SDI | P1: Declaração GBF | Q1: Parc Municipais
A2: 106 | B2: =VLOOKUP(A2,Empresas!A:B,2,0) -> 04.431.460/0001-25 | C2: =VLOOKUP(B2,Empresas!B:C,2,0) -> 04.431.460 Ramiro Duenas Aranzabal | D2: =VLOOKUP(C2,Empresas!C:D,2,0) -> MEI | E2: =VLOOKUP(A2,Empresas!A:J,10,0) -> Jorge | F2: =VLOOKUP(A2,Empresas!A:H,8,0) -> São Paulo | G2: Julho | H2: =VLOOKUP(A2,Empresas!A:G,7,0) -> 3.656.245-9 | I2: ARA217du | J2: 10 | K2: S/M | M2: S/M | N2: N/A | O2: N/A | P2: N/A | Q2: S/M
A3: 119 | B3: 27.541.980/0001-96 | C3: 4.Com Serviços Empresariais Ltda | D3: Simples Nacional | E3: Jorge | F3: São Paulo | G3: Julho | H3: 5.694.018-1 | I3: Cservicos27 | J3: 10 | K3: S/M | M3: OK | N3: N/A | O3: N/A | P3: N/A | Q3: S/M
A4: 415 | B4: 42.360.609/0001-11 | C4: 42.360.609 Dener Mendonça de Souza | D4: MEI | E4: Jorge | F4: Jundiaí | G4: Isento | H4: 1470672 | I4: W8METVGZ | J4: 25 | K4: S/M | M4: S/M | N4: N/A | O4: N/A | P4: N/A | Q4: N/A
A5: 218 | B5: 43.436.474/0001-93 | C5: 43.436.474 Maria Clara Tomé Garcia | D5: MEI | E5: Jorge | F5: São Bernardo do Campo | G5: Isento | H5: 298839 | I5: 298839UQG43441 | J5: 15 | K5: S/M | M5: S/M | N5: N/A | O5: N/A | P5: N/A | Q5: N/A
A6: 628 | B6: 43.959.791/0001-94 | C6: 43.959.791 Ana Isabela Pithan Maraschin | D6: MEI | E6: Jorge | F6: São Paulo | G6: Isento | H6: 7.107.342-6 | J6: 10 | K6: S/M | M6: S/M | N6: N/A | O6: N/A | P6: N/A | Q6: S/M
A7: 227 | B7: 44.645.259/0001-65 | C7: 44.645.259 Rebeca Brito Cardoso | D7: MEI | E7: Jorge | F7: Osasco | G7: Isento | H7: 158982 | I7: 446452Re | J7: 10 | K7: S/M | M7: OK | N7: N/A | O7: N/A | P7: N/A | Q7: N/A
A8: 359 | B8: 04.362.429/0001-80 | C8: 4CS Serviços Ltda | D8: Simples Nacional | E8: Paulo | F8: São Paulo | G8: Julho | H8: 3.005.100-2 | I8: 043624Cs | K8: S/M
A9: 638 | B9: 51.957.545/0001-21 | C9: 51.957.545 Marjorie Abdallah | D9: Simples Nacional | E9: Bruna | F9: São José do Rio Preto | G9: Abril | H9: 4067310 | I9: 51957545Ma! | J9: 17 | K9: N/A | L9: N/A | M9: OK | N9: N/A | O9: N/A | P9: N/A
A10: 437 | B10: 53.494.930/0001-05 | C10: 53.494.930 Gabriela Afonso Prado | D10: MEI | E10: Jorge | F10: Brasília | G10: Isento | H10: 08.271.808/001-19 | I10: Sucesso@22 | J10: 20 | K10: S/M | M10: S/M | N10: N/A | O10: N/A | P10: N/A | Q10: N/A
A11: 461 | B11: 54.535.015/0001-83 | C11: Ada Maria Fraulo Pires | D11: Simples Nacional | E11: Bruna | F11: São Paulo | G11: Julho | H11: 1.302.220-2 | I11: Adamaria1956@ | J11: 10 | K11: S/M | M11: S/M | N11: N/A | O11: N/A | P11: N/A | Q11: N/A
A12: 525 | B12: 58.344.129/0001-05 | C12: 58.344.129 Gilda Maria de Lima Roberto | D12: MEI | E12: Jorge | F12: São Paulo | G12: Isento | H12: 1.609.138-9 | I12: Abapai46# | J12: 10 | K12: S/M | M12: S/M | N12: N/A | O12: N/A | P12: N/A | Q12: N/A
A13: 608 | B13: 13.581.219/0001-73 | C13: A & V Marques Imóveis Ltda | D13: Simples Nacional | E13: Talita | F13: São Paulo | G13: Julho | H13: 4.285.073-8 | J13: 10 | K13: OK | L13: 46244 | M13: OK | N13: N/A | O13: N/A | P13: N/A | Q13: N/A
A14: 34 | B14: 22.189.167/0001-85 | C14: A Galeria Artes Presentes Jóias Design Rocym Ltda | D14: Simples Nacional | E14: Jorge | F14: São Paulo | G14: Julho | H14: 5.212.716-8 | I14: 123456 | J14: 10 | K14: S/M | L14: 46239 | M14: S/M | N14: N/A | O14: N/A | P14: N/A | Q14: N/A
A15: 523 | B15: 11.360.241/0001-68 | C15: A. de S. Cafcalas | D15: Simples Nacional | E15: Claudia | F15: São Paulo | G15: Julho | H15: 3.994.283-0 | I15: 123456 | J15: - | K15: N/A | M15: N/A | N15: N/A | O15: N/A | P15: N/A | Q15: OK | R15: 46247
A16: 587 | B16: 61.203.201/0001-80 | C16: A2M Ltda | D16: Lucro Presumido | E16: Luana | F16: São Paulo | G16: Julho | H16: 1.854.114-3 | I16: A2m61203201 | J16: 10 | K16: S/M | L16: - | M16: S/M | N16: N/A | O16: N/A | P16: N/A | Q16: N/A
A17: 225 | B17: 04.438.239/0001-07 | C17: AGM Representações Comerciais Ltda | D17: Lucro Presumido | E17: Talita | F17: Bariri | G17: Julho | H17: 6942 | I17: agm04438 | J17: 17 | K17: OK | L17: 46238
A18: 572 | B18: 44.114.755/0001-92 | C18: AGR Tubos Conexões e Válvulas Ltda | D18: Simples Nacional | E18: Michele | F18: São Caetano do Sul | G18: Março | H18: 141224 | I18: 1150266 | J18: 15 | K18: S/M | L18: 46239 | M18: OK | N18: N/A | O18: N/A | P18: N/A | Q18: N/A
A19: 597 | B19: 33.023.255/0001-29 | C19: Alan W de O Lima Tecnologia da Informação | D19: Simples Nacional | E19: Kamilly | F19: São Caetano do Sul | G19: Julho | H19: 108240 | I19: 000129 | J19: - | K19: N/A | L19: N/A | M19: N/A | N19: N/A | O19: N/A | P19: N/A | Q19: N/A | R19: N/A
A20: 617 | B20: 58.717.889/0001-02 | C20: Ale Holding Participações e Negócios Ltda | D20: Lucro Presumido | E20: Luana | F20: São José do Rio Preto | G20: Abril | H20: 4253100 | I20: Ale@58717889 | J20: - | K20: N/A | L20: - | M20: S/M | N20: N/A | O20: N/A | P20: N/A | Q20: N/A
A21: 303 | B21: 02.864.188/0001-41 | C21: Alexandre Sgreccia | D21: Simples Nacional | E21: Luana | F21: São Paulo | G21: Julho | H21: 2.743.353-6 | I21: 123456 | J21: - | K21: N/A | L21: - | M21: OK | N21: N/A | O21: N/A | P21: N/A | Q21: N/A
A22: 230 | B22: 04.746.127/0001-05 | C22: Alexandre Silva Voza | D22: Simples Nacional | E22: Michele | F22: São Paulo | G22: Julho | H22: 3.070.085-0 | I22: 123456 | J22: 10 | K22: S/M | L22: 46239 | M22: N/A | N22: N/A | O22: N/A | P22: N/A | Q22: N/A | R22: N/A
A23: 370 | B23: 37.140.411/0001-92 | C23: Allora Construtora e Incorporadora Ltda | D23: Lucro Presumido | E23: Kamilly | F23: São Paulo | G23: Julho | H23: 6.592.930-6 | I23: 371404Al | J23: 10 | K23: N/A | M23: N/A | N23: N/A | O23: N/A | P23: N/A | Q23: N/A | R23: N/A
A24: 578 | B24: 13.314.231/0001-11 | C24: Alpha Entretenimento e Lazer Ltda | D24: Simples Nacional | E24: Talita | F24: São Paulo | G24: Julho | H24: 1.592.667-2 | I24: 634150 | J24: 10 | K24: S/M | M24: S/M | N24: N/A | O24: N/A | P24: N/A | Q24: N/A
A25: 302 | B25: 01.665.434/0001-73 | C25: Alphaville Comercial Ltda | D25: Simples Nacional | E25: Luana | F25: São Paulo | G25: Julho | H25: 2.558.561-4 | I25: 123456 | J25: - | K25: N/A | M25: OK | N25: N/A | O25: N/A | P25: N/A | Q25: N/A
A26: 376 | B26: 09.086.104/0001-35 | C26: Américo Suriano e Companhia Ltda | D26: Simples Nacional | E26: Michele | F26: São Paulo | G26: Julho | H26: 3.676.979-7 | I26: 123456 | J26: 10 | K26: S/M | L26: 46239 | M26: N/A | N26: N/A | O26: N/A | P26: N/A | Q26: N/A
A27: 576 | B27: 49.343.692/0001-60 | C27: Ápice Artes Gráficas Ltda | D27: Lucro Real | E27: Paulo | F27: São Caetano do Sul | G27: Março | H27: 23830 | I27: APICEGRAF | J27: 17 | K27: OK | L27: 46248
A28: 61 | B28: 03.338.180/0001-04 | C28: Aprobato Neto Contabilidade e Apoio Empresarial Ltda | D28: Simples Nacional | E28: Paulo | F28: São Paulo | G28: Julho | H28: 2.818.201-4 | I28: 250679 | K28: S/M
A29: 972 | B29: 00.000.904/0001-17 | C29: Aprobato Neto Perícias Técnicas Ltda | D29: Simples Nacional | E29: Paulo | F29: São Paulo | G29: Julho | H29: 2.254.918-8 | I29: 123456 | J29: 10 | K29: OK | L29: 46241
A30: 972 (-2) | B30: 00.000.904/0002-06 | C30: Aprobato Neto Perícias Técnicas Ltda | D30: Simples Nacional | E30: Paulo | F30: São Caetano do Sul | G30: Julho | H30: 0 | K30: S/M | L30: 46241
A31: 440 | B31: 71.912.349/0001-48 | C31: Arakaki Enterprise Ltda | D31: Lucro Presumido | E31: Talita | F31: São Paulo | G31: Julho | H31: 2.189.072-2 | I31: 71912349Wa | K31: S/M | L31: 46244
A32: 18 | B32: 61.094.660/0001-73 | C32: Aramfactor Utilidades em Arames Ltda | D32: Lucro Presumido | E32: Talita | F32: São Paulo | G32: Julho | H32: 9.663.449-9 | I32: 123456 | J32: 10 | K32: N/A | L32: 46244 | M32: OK | N32: N/A | O32: N/A | P32: N/A
A33: 127 | B33: 02.400.369/0001-17 | C33: Associação Brasileira de Wakeboard | D33: Lucro Real | E33: Jorge | F33: São Paulo | G33: Julho | H33: 2.672.777-3 | I33: Abwakeboard02 | J33: 10 | K33: S/M | L33: - | M33: OK | N33: N/A | O33: N/A | P33: N/A | Q33: N/A
A34: 208 | B34: 07.010.849/0001-95 | C34: Associação dos Serv e Magis Para Manut do Berçário do TRT da 2 Região | D34: Lucro Real | E34: Jorge | F34: São Paulo | G34: Julho | H34: 3.390.868-0 | I34: 123456 | J34: 10 | K34: S/M | L34: 46239 | M34: S/M | N34: N/A | O34: N/A | P34: N/A | Q34: N/A
A35: 175 | B35: 39.563.909/0001-93 | C35: Assunção Antunes Corretora de Seguros Ltda | D35: Simples Nacional | E35: Luana | F35: Belo Horizonte | G35: Maio | H35: 1.258.826/001-4 | I35: 25527176 | J35: - | K35: N/A | L35: - | M35: OK | N35: N/A | O35: N/A | P35: N/A | Q35: N/A
A36: 594 | B36: 61.633.486/0001-90 | C36: Astra Tecnologia Ltda | D36: Simples Nacional | E36: Claudia | F36: Barueri | G36: Março | H36: 4.BP565-1 | I36: !$F4fY$genwUmx | J36: - | K36: N/A | M36: OK | N36: N/A | O36: N/A | P36: N/A | Q36: N/A
A37: 556 | B37: 37.911.956/0001-55 | C37: Atta Participações Ltda | D37: Lucro Presumido | E37: Jorge | F37: Barueri | G37: Março | H37: 4996407 | I37: 1029384756 | J37: - | K37: S/M | L37: 46241 | M37: S/M | N37: N/A | O37: N/A | P37: N/A | Q37: N/A
A38: 279 | B38: 04.914.402/0001-52 | C38: Augusta e Respeitável Loja Simbólica Paz e Harmonia | D38: Lucro Real | E38: Talita | F38: São Paulo | G38: Isento | H38: 3.106.378-0 | I38: ARLSph551 | K38: S/M | N38: N/A | O38: N/A | P38: N/A
A39: 615 | B39: 63.531.342/0001-58 | C39: Augusto Ferrari Gestão Patrimonial Ltda | D39: Lucro Presumido | E39: Claudia | F39: São Paulo | G39: Julho | H39: 0.059.091-6 | I39: Af63531342 | J39: - | K39: S/M | M39: OK | N39: N/A | O39: N/A | P39: N/A | Q39: N/A
A40: 586 | B40: 61.108.827/0001-08 | C40: Aviana Ltda | D40: Simples Nacional | E40: Bruna | F40: São Paulo | G40: Março | H40: 1.846.546-3 | I40: 611088Al | J40: 10 | K40: S/M | M40: S/M | N40: N/A | O40: N/A | P40: N/A | Q40: N/A
A41: 330 | B41: 00.368.304/0001-06 | C41: Avs Vital Comércio de Tecidos e Resíduos Ltda | D41: Simples Nacional | E41: Claudia | F41: São Paulo | G41: Julho | H41: 2.321.470-8 | I41: 00368304Avs | J41: - | K41: S/M | M41: S/M | N41: S/M | O41: S/M | P41: S/M | Q41: N/A
A42: 148 | B42: 31.748.724/0001-41 | C42: B.M.M. Apoio Empresarial Ltda | D42: Simples Nacional | E42: Jorge | F42: São Paulo | G42: Julho | H42: 6.094.611-3 | I42: Bmmorais31 | J42: 10 | K42: S/M
A43: 512 | B43: 65.934.747/0001-62 | C43: Bar e Lanches Volta Cruzeiro Ltda | D43: Lucro Presumido | E43: Claudia | F43: São Paulo | G43: Julho | H43: 9.873.890-9 | I43: 123456 | J43: - | K43: S/M | M43: S/M | N43: S/M | O43: S/M | P43: S/M | Q43: N/A
A44: 155 | B44: 32.412.497/0001-41 | C44: Benedito José da Silva 08720320868 | D44: MEI | E44: Talita | F44: São Paulo | G44: Julho | H44: 6.160.432-1 | I44: Benedito32 | J44: 10 | K44: N/A | L44: 46244 | M44: OK | N44: N/A | O44: N/A | P44: N/A
A45: 351 | B45: 47.407.177/0001-70 | C45: Bepass S.A. | D45: Lucro Real | E45: Talita | F45: São Paulo | G45: Julho | H45: 7.408.877-7 | I45: Bp47407177 | J45: 10 | K45: OK | L45: 46240 | M45: OK | N45: N/A | O45: N/A | P45: N/A
A46: 510 | B46: 55.769.305/0001-54 | C46: Bianca Ribeiro Mattos Ltda | D46: Simples Nacional | E46: Claudia | F46: São Paulo | G46: Julho | H46: 1.415.650-4 | I46: 557693Bi | J46: - | K46: N/A | M46: N/A | N46: N/A | O46: N/A | P46: N/A | Q46: N/A
A47: 646 | B47: 67.041.408/0001-82 | C47: Bitachon Serviços Administrativos Ltda | D47: Simples Nacional | E47: Jorge | F47: São Paulo | G47: Julho | H47: 0.343.044-8 | I47: 670414Je | J47: 10 | K47: S/M
A48: 542 | B48: 12.107.957/0001-10 | C48: BJ2R Serviços Ltda | D48: Simples Nacional | E48: Kamilly | F48: São Paulo | G48: Julho | H48: 4.089.322-7 | I48: 121079 | J48: 10 | K48: N/A | L48: N/A | M48: N/A | N48: N/A | O48: N/A | P48: N/A | Q48: N/A | R48: N/A
A49: 240 | B49: 36.557.666/0001-92 | C49: BLGR Serviços Empresariais Ltda | D49: Simples Nacional | E49: Bruna | F49: São Paulo | G49: Julho | H49: 6.546.675-6 | I49: Blgr3655 | J49: 10 | K49: S/M | M49: OK | N49: N/A | O49: N/A | P49: N/A
A50: 486 | B50: 35.048.108/0001-39 | C50: BNC Print Comércio e Soluções Técnicas Ltda | D50: Simples Nacional | E50: Talita | F50: São Caetano do Sul | G50: Julho | H50: 111044 | I50: 111044EVQ78143 | J50: 10 | K50: S/M | M50: S/M | N50: S/M | O50: S/M | P50: S/M | Q50: S/M
A51: 71 | B51: 08.991.576/0001-70 | C51: Botecaria Distribuição e Marketing Ltda | D51: Lucro Presumido | E51: Bruna | F51: São Paulo | G51: Julho | H51: 3.661.044-5 | I51: 123456 | J51: 10 | K51: S/M | M51: S/M | N51: N/A | O51: N/A | P51: N/A
A52: 458 | B52: 26.635.239/0001-21 | C52: Brunna Vomstein Andrade | D52: Simples Nacional | E52: Bruna | F52: São Caetano do Sul | G52: Março | H52: 136949 | I52: 136949TMP63141 | J52: Cota Única | K52: S/M | M52: S/M | N52: N/A | O52: N/A | P52: N/A | Q52: N/A
A53: 122 | B53: 00.833.464/0001-89 | C53: Buffet Israel Ltda | D53: Simples Nacional | E53: Kamilly | F53: São Paulo | G53: Julho | H53: 2.423.915-1 | I53: 123456 | J53: 10 | K53: N/A | L53: N/A | M53: N/A | N53: N/A | O53: N/A | P53: N/A | Q53: N/A | R53: N/A
A54: 499 | B54: 57.262.385/0001-82 | C54: C.M.S. Holding Participações Ltda | D54: Lucro Presumido | E54: Michele | F54: São Paulo | G54: Julho | H54: 1.500.665-4 | I54: 572623Cm | J54: 10 | K54: S/M | L54: 46239 | M54: N/A | N54: N/A | O54: N/A | P54: N/A | Q54: N/A
A55: 435 | B55: 52.796.465/0001-02 | C55: C2C Ltda | D55: Simples Nacional | E55: Luana | F55: Belo Horizonte | G55: Maio | H55: 1.514.760/001-2 | I55: Indikeyc2c | J55: - | K55: N/A | L55: - | M55: OK | N55: N/A | O55: N/A | P55: N/A | Q55: N/A | R55: N/A
A56: 591 | B56: 61.256.978/0001-03 | C56: C3C Corretora de Seguros Ltda | D56: Simples Nacional | E56: Luana | F56: Belo Horizonte | G56: Maio | H56: 1.670.852/001-0 | J56: - | K56: N/A | L56: - | M56: S/M | N56: N/A | O56: N/A | P56: N/A | Q56: N/A | R56: N/A
A57: 419 | B57: 09.666.095/0001-51 | C57: Calcam Comercial de Suprimentos de Informática Ltda | D57: Simples Nacional | E57: Talita | F57: São Paulo | G57: Julho | H57: 3.779.834-0 | I57: 123456 | J57: 10 | K57: N/A | L57: 46244 | M57: OK | N57: N/A | O57: N/A | P57: N/A | Q57: N/A
A58: 273 | B58: 41.118.298/0001-16 | C58: Cami Concept Ltda | D58: Simples Nacional | E58: Bruna | F58: São Paulo | G58: Julho | H58: 6.874.610-5 | I58: Mamis1408 | J58: 10 | K58: N/A | L58: - | M58: S/M | N58: N/A | O58: N/A | P58: N/A
A59: 262 | B59: 39.960.783/0001-90 | C59: Capella Comércio e Representações de Produtos Químicos Ltda | D59: Lucro Presumido | E59: Kamilly | F59: São Paulo | G59: Julho | H59: 6.775.077-0 | I59: Capellaw39 | J59: 10 | K59: N/A | L59: N/A | M59: N/A | N59: N/A | O59: N/A | P59: N/A | Q59: N/A | R59: N/A
A60: 411 | B60: 51.764.963/0001-00 | C60: Caresma & Schmidt Office Consultoria Empresarial Ltda | D60: Simples Nacional | E60: Bruna | F60: São Paulo | G60: Julho | H60: 7.800.644-9 | I60: 51764963Ca | J60: 10 | K60: N/A | M60: OK | N60: N/A | O60: N/A | P60: N/A
A61: 505 | B61: 57.642.648/0001-89 | C61: Carrilho Donas Sociedade Individual de Advocacia | D61: Simples Nacional | E61: Bruna | F61: Brasília | G61: Julho | H61: 08.336.234/001-60 | J61: 10 | K61: N/A | M61: OK | N61: N/A | O61: N/A | P61: N/A
A62: 495 | B62: 57.121.049/0001-10 | C62: Cass Consultoria Empresarial Ltda | D62: Simples Nacional | E62: Claudia | F62: São Paulo | G62: Julho | H62: 1.489.925-6 | I62: 50121049C@ss | J62: - | K62: N/A | L62: - | M62: N/A | N62: N/A | O62: N/A | P62: N/A | Q62: N/A
A63: 293 | B63: 42.638.806/0001-50 | C63: Catedral Intermediação de Negócios Ltda | D63: Simples Nacional | E63: Claudia | F63: São Paulo | G63: Julho | H63: 6.991.897-0 | I63: Catedral@42638806 | J63: - | K63: N/A | M63: OK | N63: N/A | O63: N/A | P63: N/A | Q63: N/A
A64: 335 | B64: 13.574.084/0001-19 | C64: CCKids Comércio e Confecção de Roupas e Acessórios Ltda | D64: Simples Nacional | E64: Luana | F64: São Paulo | G64: Julho | H64: 4.277.156-0 | I64: 13574084Iz | J64: - | K64: N/A | L64: - | M64: OK | N64: N/A | O64: N/A | P64: N/A | Q64: N/A
A65: 372 | B65: 50.685.261/0001-60 | C65: CDM Holding Ltda | D65: Lucro Presumido | E65: Kamilly | F65: São Paulo | G65: Julho | H65: 7.699.823-1 | I65: 506852Cd | J65: 10 | K65: N/A | L65: N/A | M65: N/A | N65: N/A | O65: N/A | P65: N/A | Q65: N/A | R65: N/A
A66: 398 | B66: 03.702.166/0001-48 | C66: Cena Cultural Produções Ltda | D66: Lucro Presumido | E66: Claudia | F66: São Paulo | G66: Julho | H66: 2.886.451-4 | I66: 123456 | J66: - | K66: S/M | L66: - | M66: S/M | N66: S/M | O66: S/M | P66: S/M | Q66: N/A
A67: 321 | B67: 59.650.721/0001-90 | C67: Central Serviços Médicos Ltda | D67: Lucro Presumido | E67: Talita | F67: Guarulhos | G67: Sem débitos | H67: 57123 | I67: central057123 | J67: 12 | K67: OK | L67: 46246 | M67: OK | N67: N/A | O67: N/A | P67: N/A | Q67: N/A
A68: 449 | B68: 10.665.359/0001-31 | C68: Centro de Saúde Animal Zoovet Ltda | D68: Lucro Presumido | E68: Talita | F68: São Paulo | G68: Julho | H68: 3.886.732-0 | I68: 123456 | J68: 10 | K68: OK | L68: 46244 | M68: OK | N68: N/A | O68: N/A | P68: N/A
A69: 730 | B69: 65.887.267/0001-98 | C69: Chipendalle Arte Móveis Ltda | D69: Simples Nacional | E69: Jorge | F69: São Paulo | G69: Julho | H69: 9.905.758-1 | I69: 123456 | J69: 10 | K69: S/M
A70: 365 | B70: 34.329.315/0001-07 | C70: CJS Comércio Varejista de Tecidos Ltda | D70: Simples Nacional | E70: Bruna | F70: Praia Grande | G70: Sem débitos | H70: 584789 | J70: - | K70: S/M | M70: S/M | N70: N/A | O70: N/A | P70: N/A
A71: 365 (-2) | B71: 34.329.315/0002-80 | C71: CJS Comércio Varejista de Tecidos Ltda | D71: Simples Nacional | E71: Bruna | F71: Guarulhos | G71: Abril | H71: 619539 | I71: 343293Cl | J71: - | K71: S/M
A72: 365 (-3) | B72: 34.329.315/0003-60 | C72: CJS Comércio Varejista de Tecidos Ltda | D72: Simples Nacional | E72: Bruna | F72: Praia Grande | G72: - | H72: Isenta | J72: - | K72: N/A | L72: OK
A73: 408 | B73: 48.292.179/0001-24 | C73: CLE Comunicação Liderança e Educação Ltda | D73: Simples Nacional | E73: Luana | F73: São Paulo | G73: Julho | H73: 7.486.197-2 | I73: 48292179Cle | J73: - | K73: N/A | L73: - | M73: OK | N73: N/A | O73: N/A | P73: N/A | Q73: N/A
A74: 402 | B74: 03.754.180/0001-95 | C74: Clínica de Ortopedia Dr. Javier V. S. Vargas Ltda | D74: Lucro Presumido | E74: Kamilly | F74: São Paulo | G74: Julho | H74: 2.900.531-0 | I74: 123456 | J74: 10 | K74: Ok | M74: OK | N74: N/A | O74: N/A | P74: N/A | Q74: N/A | R74: N/A
A75: 393 | B75: 03.541.023/0001-00 | C75: Clínica Dr. Eduardo de Souza Ltda | D75: Lucro Presumido | E75: Luana | F75: São Paulo | G75: Isento | H75: 2.861.253-1 | I75: 123456 | J75: 10 | K75: Ok | L75: 46239 | M75: OK | N75: N/A | O75: N/A | P75: N/A | Q75: N/A
A76: 420 | B76: 52.145.726/0001-16 | C76: Comércio Estético Maison Hair Ltda | D76: Simples Nacional | E76: Jorge | F76: São Paulo | G76: Julho | H76: 7.837.687-4 | I76: 521457Co | J76: 10 | K76: S/M
A77: 187 | B77: 34.504.701/0001-80 | C77: Comuniverse Ltda | D77: Lucro Real | E77: Michele | F77: São Paulo | G77: Julho | H77: 6.360.748-4 | I77: Comuni34 | J77: 10 | K77: Ok | L77: 46238 | M77: OK | N77: N/A | O77: N/A | P77: N/A | Q77: N/A
A78: 476 | B78: 03.951.113/0001-60 | C78: Condor Instituto de Psicologia e Pesquisa SS Ltda | D78: Lucro Presumido | E78: Talita | F78: São Paulo | G78: Julho | H78: 2.933.349-0 | I78: 123456 | K78: S/M | N78: N/A | O78: N/A | P78: N/A
A79: 128 | B79: 06.347.712/0001-68 | C79: Confederação Brasileira de Empresas Juniores | D79: Lucro Real | E79: Kamilly | F79: São Paulo | G79: Julho | H79: 5.948.129-3 | I79: Bjunior06 | J79: 10 | K79: Ok | M79: N/A | N79: N/A | O79: N/A | P79: N/A | Q79: N/A | R79: N/A
A80: 590 | B80: 61.158.615/0001-35 | C80: Convox Negócios e Serviços Ltda | D80: Simples Nacional | E80: Talita | F80: São Paulo | G80: Julho | H80: 1.856.461-5 | I80: 611586Co | J80: 10 | K80: S/M | L80: 46244 | M80: S/M | N80: N/A | O80: N/A | P80: N/A | Q80: N/A
A81: 621 | B81: 42.657.808/0001-96 | C81: Corcovado Investimentos Gestão de Recursos Ltda | D81: Simples Nacional | E81: Michele | F81: Rio de Janeiro | G81: 0 | H81: 13.230.12-9 | J81: 3 | K81: S/M | L81: 46239 | M81: N/A | N81: N/A | O81: N/A | P81: N/A | Q81: N/A
A82: 23 | B82: 45.953.312/0001-58 | C82: Cristal Prime Auto Vidros e Acessórios Ltda | D82: Simples Nacional | E82: Kamilly | F82: São Paulo | G82: Julho | H82: 5.077.130-2 | I82: 123456 | J82: 10 | K82: N/A | L82: N/A | M82: N/A | N82: N/A | O82: N/A | P82: N/A | Q82: N/A | R82: N/A
A83: 137 | B83: 00.569.062/0001-19 | C83: Cristaltech Auto Vidros e Acessorios Ltda | D83: Lucro Presumido | E83: Kamilly | F83: São Paulo | G83: Isento | H83: 2.351.717-4 | I83: 123456 | J83: 10 | K83: N/A | L83: N/A | M83: N/A | N83: N/A | O83: N/A | P83: N/A | Q83: N/A | R83: N/A
A84: 137 (-2) | B84: 00.569.062/0002-08 | C84: Cristaltech Auto Vidros e Acessorios Ltda | D84: Lucro Presumido | E84: Kamilly | F84: São Bernardo do Campo | G84: Isento | H84: 231979 | I84: 000208 | J84: 15 | K84: N/A | L84: N/A | M84: N/A | N84: N/A | O84: N/A | P84: N/A | Q84: N/A | R84: N/A
A85: 494 | B85: 56.778.834/0001-87 | C85: Croce Simões Holding Ltda | D85: Lucro Presumido | E85: Michele | F85: São Paulo | G85: Julho | H85: 1.463.586-0 | I85: 567788Cr | J85: 10 | K85: S/M | L85: 46239 | M85: N/A | N85: N/A | O85: N/A | P85: N/A | Q85: N/A
A86: 308 | B86: 18.587.752/0001-66 | C86: Crysthiane Henrique de Matos Gonçalves Tripode | D86: MEI | E86: Michele | F86: São Paulo | G86: Isento | H86: 4.807.198-6 | J86: 10 | K86: S/M | L86: 46237 | M86: N/A | N86: N/A | O86: N/A | P86: N/A | Q86: N/A | R86: 46237
A87: 557 | B87: 39.940.308/0001-52 | C87: Dataind Tecnologia de Informação Ltda | D87: Lucro Real | E87: Jorge | F87: Barueri | G87: Março | H87: 3370100 | I87: 1029384756 | J87: 10 | K87: OK | L87: 46241 | M87: OK | N87: N/A | O87: N/A | P87: N/A | Q87: N/A
A88: 181 | B88: 00.575.747/0001-78 | C88: Davos Consult Serviços de Apoio Empresarial Ltda | D88: Simples Nacional | E88: Jorge | F88: Valinhos | G88: Março | H88: 2.352.524-0 | I88: 69956845 | J88: 15 | K88: S/M
A89: 272 | B89: 40.915.081/0001-74 | C89: DBM Consultoria e Participações Ltda | D89: Simples Nacional | E89: Claudia | F89: São Paulo | G89: Julho | H89: 6.853.388-8 | I89: Dbmpart40 | J89: - | K89: N/A | M89: OK | N89: N/A | O89: N/A | P89: N/A | Q89: N/A
A90: 367 | B90: 50.231.188/0001-57 | C90: Decor Adesivos e Decoração Ltda | D90: Simples Nacional | E90: Talita | F90: São Paulo | G90: Julho | H90: 7.660.657-0 | I90: 502311De | J90: 10 | K90: N/A | L90: 46244 | M90: OK | N90: N/A | O90: N/A | P90: N/A
A91: 254 | B91: 27.532.933/0001-86 | C91: Decor Revestimentos Adesivos Ltda | D91: Simples Nacional | E91: Talita | F91: São Paulo | G91: Julho | H91: 5.688.813-9 | I91: Decor172323 | J91: 10 | K91: N/A | L91: 46244 | M91: OK | N91: N/A | O91: N/A | P91: N/A
A92: 6 | B92: 16.952.792/0001-34 | C92: Delta Geradores Ltda | D92: Simples Nacional | E92: Jorge | F92: São Paulo | G92: Julho | H92: 4.610.430-5 | I92: 123456 | J92: 10 | K92: S/M
A93: 113 | B93: 27.372.837/0001-18 | C93: Delta Suporte em Vendas Ltda | D93: Simples Nacional | E93: Claudia | F93: São Paulo | G93: Julho | H93: 5.681.026-1 | I93: Dsuporte27 | J93: - | K93: N/A | M93: N/A | N93: N/A | O93: N/A | P93: N/A | Q93: N/A
A94: 145 | B94: 31.496.077/0001-28 | C94: Denis Calazans Cordeiro | D94: Simples Nacional | E94: Luana | F94: São Paulo | G94: Julho | H94: 6.073.103-6 | I94: Denis123 | J94: - | K94: N/A | L94: - | M94: OK | N94: N/A | O94: N/A | P94: N/A | Q94: N/A
A95: 649 | B95: 31.721.911/0001-31 | C95: Dentalfinance Odontologia e Gestão Financeira Ltda. | D95: Simples Nacional | E95: Bruna | F95: Cotia | G95: 0 | H95: 6062646 | J95: - | K95: N/A | M95: OK | N95: N/A | O95: N/A | P95: N/A | Q95: N/A
A96: 640 | B96: 33.032.171/0001-51 | C96: DHM Engenharia Ltda | D96: Lucro Presumido | E96: Talita | F96: Recife | G96: Julho | H96: 6378331 | J96: 10 | K96: OK | L96: 46244 | M96: OK | N96: N/A | O96: N/A | P96: N/A
A97: 103 | B97: 26.025.480/0001-39 | C97: Diógenes Prado Batista Sociedade Individual de Advocacia | D97: Simples Nacional | E97: Jorge | F97: São Paulo | G97: Julho | H97: 5.548.557-0 | I97: Dpbatista26 | J97: 10 | K97: S/M
A98: 550 | B98: 12.591.454/0001-63 | C98: Direct Advice Serviços Empresariais Ltda | D98: Lucro Presumido | E98: Bruna | F98: São Paulo | G98: Julho | H98: 4.146.045-6 | I98: 123456 | J98: 10 | K98: S/M | M98: OK | N98: N/A | O98: N/A | P98: N/A
A99: 169 | B99: 14.627.752/0001-91 | C99: Direction Solução em Serviços Administrativos Ltda | D99: Simples Nacional | E99: Bruna | F99: São Paulo | G99: Julho | H99: 4.416.153-0 | I99: 123456 | J99: 10 | K99: S/M | M99: OK | N99: N/A | O99: N/A | P99: N/A
A100: 643 | B100: 66.673.761/0001-12 | C100: DLS Serviços de Tecnologia Ltda | D100: Simples Nacional | E100: Kamilly | F100: São Paulo | G100: Setembro | H100: 0.311.426-0 | I100: 666737Dl | J100: 10 | K100: N/A | L100: N/A | M100: N/A | N100: N/A | O100: N/A | P100: N/A | Q100: N/A | R100: N/A
...

Sheet Estaduais
A1: Código | B1: CNPJ | C1: Razão Social | D1: Tributação | E1: Usuário | F1: Estado | G1: Inscrição Estadual | H1: GUIA ICMS | J1: DIFAL | L1: GUIA IPI | N1: Bloco K | O1: SPED Fiscal | Q1: DeSTDA | R1: Parc Estaduais
A2: 106 | B2: =VLOOKUP(A2,Empresas!A:B,2,0) -> 04.431.460/0001-25 | C2: =VLOOKUP(B2,Empresas!B:C,2,0) -> 04.431.460 Ramiro Duenas Aranzabal | D2: =VLOOKUP(C2,Empresas!C:D,2,0) -> MEI | E2: =VLOOKUP(A2,Empresas!A:J,10,0) -> Jorge | F2: =VLOOKUP(A2,Empresas!A:F,6,0) -> São Paulo | G2: =VLOOKUP(A2,Empresas!A:E,5,0) -> 116270616110 | H2: N/A | I2: N/A | L2: N/A | M2: N/A | N2: N/A | O2: N/A | P2: N/A
A3: 119 | B3: 27.541.980/0001-96 | C3: 4.Com Serviços Empresariais Ltda | D3: Simples Nacional | E3: Jorge | F3: São Paulo | G3: Isenta | H3: N/A | I3: N/A | L3: N/A | M3: N/A | N3: N/A | O3: N/A | P3: N/A
A4: 415 | B4: 42.360.609/0001-11 | C4: 42.360.609 Dener Mendonça de Souza | D4: MEI | E4: Jorge | F4: São Paulo | G4: Isenta | H4: N/A | I4: N/A | L4: N/A | M4: N/A | N4: N/A | O4: N/A | P4: N/A
A5: 218 | B5: 43.436.474/0001-93 | C5: 43.436.474 Maria Clara Tomé Garcia | D5: MEI | E5: Jorge | F5: São Paulo | G5: 799468637111 | H5: N/A | I5: N/A | L5: N/A | M5: N/A | N5: N/A | O5: N/A | P5: N/A
A6: 628 | B6: 43.959.791/0001-94 | C6: 43.959.791 Ana Isabela Pithan Maraschin | D6: MEI | E6: Jorge | F6: São Paulo | G6: 133256510113 | H6: N/A | I6: N/A | L6: N/A | M6: N/A | N6: N/A | O6: N/A | P6: N/A
A7: 227 | B7: 44.645.259/0001-65 | C7: 44.645.259 Rebeca Brito Cardoso | D7: MEI | E7: Jorge | F7: São Paulo | G7: Isenta | H7: N/A | I7: N/A | L7: N/A | M7: N/A | N7: N/A | O7: N/A | P7: N/A
A8: 359 | B8: 04.362.429/0001-80 | C8: 4CS Serviços Ltda | D8: Simples Nacional | E8: Paulo | F8: São Paulo | G8: Isenta | H8: N/A | I8: N/A | J8: S/M | L8: N/A | M8: N/A | N8: N/A | O8: N/A | P8: N/A
A9: 638 | B9: 51.957.545/0001-21 | C9: 51.957.545 Marjorie Abdallah | D9: Simples Nacional | E9: Bruna | F9: São Paulo | G9: Isenta | H9: N/A | I9: N/A | J9: S/M | L9: N/A | M9: N/A | N9: N/A | O9: N/A | P9: N/A | Q9: S/M
A10: 437 | B10: 53.494.930/0001-05 | C10: 53.494.930 Gabriela Afonso Prado | D10: MEI | E10: Jorge | F10: Distrito Federal | G10: Isenta | H10: N/A | I10: N/A | L10: N/A | M10: N/A | N10: N/A | O10: N/A | P10: N/A
A11: 461 | B11: 54.535.015/0001-83 | C11: Ada Maria Fraulo Pires | D11: Simples Nacional | E11: Bruna | F11: São Paulo | G11: 135862064112 | H11: N/A | I11: N/A | J11: S/M | L11: N/A | M11: N/A | N11: N/A | O11: N/A | P11: N/A | Q11: S/M | R11: S/M
A12: 525 | B12: 58.344.129/0001-05 | C12: 58.344.129 Gilda Maria de Lima Roberto | D12: MEI | E12: Jorge | F12: São Paulo | G12: 151811726114 | H12: N/A | I12: N/A | L12: N/A | M12: N/A | N12: N/A | O12: N/A | P12: N/A
A13: 608 | B13: 13.581.219/0001-73 | C13: A & V Marques Imóveis Ltda | D13: Simples Nacional | E13: Talita | F13: São Paulo | G13: Isenta | H13: N/A | I13: N/A | L13: N/A | M13: N/A | N13: N/A | O13: N/A | P13: N/A
A14: 34 | B14: 22.189.167/0001-85 | C14: A Galeria Artes Presentes Jóias Design Rocym Ltda | D14: Simples Nacional | E14: Jorge | F14: São Paulo | G14: 128248912111 | H14: N/A | I14: N/A | J14: S/M | K14: 46239 | L14: N/A | M14: N/A | N14: N/A | O14: N/A | P14: N/A | Q14: S/M | R14: S/M | S14: 46238
A15: 523 | B15: 11.360.241/0001-68 | C15: A. de S. Cafcalas | D15: Simples Nacional | E15: Claudia | F15: São Paulo | G15: Isenta | H15: N/A | I15: N/A | J15: S/M | L15: N/A | M15: N/A | N15: N/A | O15: N/A | P15: N/A | Q15: S/M | R15: S/M
A16: 587 | B16: 61.203.201/0001-80 | C16: A2M Ltda | D16: Lucro Presumido | E16: Luana | F16: São Paulo | G16: Isenta | H16: N/A | I16: N/A | J16: S/M | K16: 46245 | L16: N/A | M16: N/A | N16: N/A | O16: N/A | P16: N/A | Q16: N/A | R16: N/A | S16: N/A
A17: 225 | B17: 04.438.239/0001-07 | C17: AGM Representações Comerciais Ltda | D17: Lucro Presumido | E17: Talita | F17: São Paulo | G17: Isenta | H17: N/A | I17: N/A | J17: S/M | K17: 46245 | L17: N/A | M17: N/A | N17: N/A | O17: S/M | P17: 46246 | Q17: N/A | R17: N/A | S17: N/A
A18: 572 | B18: 44.114.755/0001-92 | C18: AGR Tubos Conexões e Válvulas Ltda | D18: Simples Nacional | E18: Michele | F18: São Paulo | G18: 636583794113 | H18: N/A | I18: N/A | L18: N/A | M18: N/A | N18: N/A | O18: N/A | P18: N/A
A19: 597 | B19: 33.023.255/0001-29 | C19: Alan W de O Lima Tecnologia da Informação | D19: Simples Nacional | E19: Kamilly | F19: São Paulo | G19: Isenta | H19: N/A | I19: N/A | J19: S/M | L19: N/A | M19: N/A | N19: N/A | O19: N/A | P19: N/A | Q19: S/M | R19: S/M
A20: 617 | B20: 58.717.889/0001-02 | C20: Ale Holding Participações e Negócios Ltda | D20: Lucro Presumido | E20: Luana | F20: São Paulo | G20: 152218550110 | H20: N/A | J20: S/M | K20: 46238 | L20: N/A | M20: 46238 | N20: S/M | O20: OK | P20: 46238 | Q20: N/A | R20: S/M | S20: 46238
A21: 303 | B21: 02.864.188/0001-41 | C21: Alexandre Sgreccia | D21: Simples Nacional | E21: Luana | F21: São Paulo | G21: Isenta | H21: N/A | I21: N/A | J21: S/M | K21: 46241 | L21: N/A | M21: N/A | N21: N/A | O21: N/A | P21: N/A | Q21: S/M | R21: N/A | S21: N/A
A22: 230 | B22: 04.746.127/0001-05 | C22: Alexandre Silva Voza | D22: Simples Nacional | E22: Michele | F22: São Paulo | G22: 149989327117 | H22: N/A | I22: N/A | J22: S/M | K22: 46238 | L22: N/A | M22: N/A | N22: N/A | O22: N/A | P22: N/A | Q22: S/M | R22: S/M | S22: 46238
A23: 370 | B23: 37.140.411/0001-92 | C23: Allora Construtora e Incorporadora Ltda | D23: Lucro Presumido | E23: Kamilly | F23: São Paulo | G23: 128936605119 | H23: N/A | I23: N/A | J23: N/A | K23: N/A | L23: N/A | M23: N/A | N23: N/A | O23: Ok | Q23: N/A | R23: N/A | S23: N/A
A24: 578 | B24: 13.314.231/0001-11 | C24: Alpha Entretenimento e Lazer Ltda | D24: Simples Nacional | E24: Talita | F24: São Paulo | G24: 403008716119 | H24: N/A | I24: N/A | J24: S/M | L24: N/A | M24: N/A | N24: N/A | O24: N/A | P24: N/A | Q24: S/M | R24: S/M
A25: 302 | B25: 01.665.434/0001-73 | C25: Alphaville Comercial Ltda | D25: Simples Nacional | E25: Luana | F25: São Paulo | G25: 114726418111 | H25: N/A | I25: N/A | J25: S/M | K25: 46248 | L25: N/A | M25: N/A | N25: N/A | O25: N/A | P25: N/A | Q25: S/M | R25: N/A | S25: N/A
A26: 376 | B26: 09.086.104/0001-35 | C26: Américo Suriano e Companhia Ltda | D26: Simples Nacional | E26: Michele | F26: São Paulo | G26: 149817697113 | H26: N/A | I26: N/A | L26: N/A | M26: N/A | N26: N/A | O26: N/A | P26: N/A
A27: 576 | B27: 49.343.692/0001-60 | C27: Ápice Artes Gráficas Ltda | D27: Lucro Real | E27: Paulo | F27: São Paulo | G27: 636070583117 | H27: OK | I27: 46248 | J27: S/M | L27: OK | M27: 46248 | O27: OK | P27: 46254 | Q27: N/A
A28: 61 | B28: 03.338.180/0001-04 | C28: Aprobato Neto Contabilidade e Apoio Empresarial Ltda | D28: Simples Nacional | E28: Paulo | F28: São Paulo | G28: Isenta | H28: N/A | I28: N/A | J28: S/M | L28: N/A | M28: N/A | N28: N/A | O28: N/A | P28: N/A
A29: 972 | B29: 00.000.904/0001-17 | C29: Aprobato Neto Perícias Técnicas Ltda | D29: Simples Nacional | E29: Paulo | F29: São Paulo | G29: Isenta | H29: N/A | I29: N/A | J29: S/M | L29: N/A | M29: N/A | N29: N/A | O29: N/A | P29: N/A
A30: 972 (-2) | B30: 00.000.904/0002-06 | C30: Aprobato Neto Perícias Técnicas Ltda | D30: Simples Nacional | E30: Paulo | F30: São Paulo | G30: Isenta | H30: N/A | I30: N/A | J30: S/M | L30: N/A | M30: N/A | N30: N/A | O30: N/A | P30: N/A
A31: 440 | B31: 71.912.349/0001-48 | C31: Arakaki Enterprise Ltda | D31: Lucro Presumido | E31: Talita | F31: São Paulo | G31: 135658787115 | H31: N/A | I31: N/A | J31: S/M | K31: 46245 | L31: N/A | M31: N/A | N31: N/A | O31: S/M | P31: 46254 | Q31: N/A | R31: N/A | S31: N/A
A32: 18 | B32: 61.094.660/0001-73 | C32: Aramfactor Utilidades em Arames Ltda | D32: Lucro Presumido | E32: Talita | F32: São Paulo | G32: 112425660117 | H32: OK | I32: 46252 | J32: S/M | K32: 46245 | L32: OK | M32: 46254 | N32: OK | O32: OK | P32: 46252 | Q32: N/A | R32: N/A | S32: N/A
A33: 127 | B33: 02.400.369/0001-17 | C33: Associação Brasileira de Wakeboard | D33: Lucro Real | E33: Jorge | F33: São Paulo | G33: Isenta | H33: N/A | I33: N/A | J33: S/M | K33: 46239 | L33: N/A | M33: N/A | N33: N/A | O33: N/A | P33: N/A | Q33: N/A | R33: N/A | S33: N/A
A34: 208 | B34: 07.010.849/0001-95 | C34: Associação dos Serv e Magis Para Manut do Berçário do TRT da 2 Região | D34: Lucro Real | E34: Jorge | F34: São Paulo | G34: Isenta | H34: N/A | I34: N/A | J34: S/M | K34: 46239 | L34: N/A | M34: N/A | N34: N/A | O34: N/A | P34: N/A | Q34: N/A | R34: N/A | S34: N/A
A35: 175 | B35: 39.563.909/0001-93 | C35: Assunção Antunes Corretora de Seguros Ltda | D35: Simples Nacional | E35: Luana | F35: Minas Gerais | G35: Isenta | H35: N/A | I35: N/A | J35: S/M | K35: 46240 | L35: N/A | M35: N/A | N35: N/A | O35: N/A | P35: N/A | Q35: S/M | R35: N/A | S35: N/A
A36: 594 | B36: 61.633.486/0001-90 | C36: Astra Tecnologia Ltda | D36: Simples Nacional | E36: Claudia | F36: São Paulo | G36: Isenta | H36: N/A | I36: N/A | J36: S/M | L36: N/A | M36: N/A | N36: N/A | O36: N/A | P36: N/A | Q36: S/M | R36: S/M
A37: 556 | B37: 37.911.956/0001-55 | C37: Atta Participações Ltda | D37: Lucro Presumido | E37: Jorge | F37: São Paulo | G37: Isenta | H37: N/A | I37: N/A | J37: S/M | L37: N/A | M37: N/A | N37: N/A | O37: S/M | Q37: N/A | R37: S/M
A38: 279 | B38: 04.914.402/0001-52 | C38: Augusta e Respeitável Loja Simbólica Paz e Harmonia | D38: Lucro Real | E38: Talita | F38: São Paulo | G38: Isenta | H38: N/A | I38: N/A | J38: S/M | K38: 46245 | L38: N/A | M38: N/A | N38: N/A | O38: N/A | P38: 46255 | Q38: N/A | R38: N/A | S38: N/A
A39: 615 | B39: 63.531.342/0001-58 | C39: Augusto Ferrari Gestão Patrimonial Ltda | D39: Lucro Presumido | E39: Claudia | F39: São Paulo | G39: Isenta | H39: N/A | I39: N/A | J39: S/M | L39: N/A | M39: N/A | N39: N/A | O39: S/M | Q39: N/A | R39: S/M
A40: 586 | B40: 61.108.827/0001-08 | C40: Aviana Ltda | D40: Simples Nacional | E40: Bruna | F40: São Paulo | G40: Isenta | H40: N/A | I40: N/A | J40: S/M | L40: N/A | M40: N/A | N40: N/A | O40: N/A | P40: N/A | Q40: S/M | R40: S/M
A41: 330 | B41: 00.368.304/0001-06 | C41: Avs Vital Comércio de Tecidos e Resíduos Ltda | D41: Simples Nacional | E41: Claudia | F41: São Paulo | G41: 148043856114 | H41: N/A | I41: N/A | J41: S/M | L41: N/A | M41: N/A | N41: N/A | O41: N/A | P41: N/A | Q41: S/M | R41: S/M
A42: 148 | B42: 31.748.724/0001-41 | C42: B.M.M. Apoio Empresarial Ltda | D42: Simples Nacional | E42: Jorge | F42: São Paulo | G42: Isenta | H42: N/A | I42: N/A | L42: N/A | M42: N/A | N42: N/A | O42: N/A | P42: N/A
A43: 512 | B43: 65.934.747/0001-62 | C43: Bar e Lanches Volta Cruzeiro Ltda | D43: Lucro Presumido | E43: Claudia | F43: São Paulo | G43: Isenta | H43: N/A | I43: N/A | J43: S/M | L43: N/A | M43: N/A | N43: N/A | O43: S/M | Q43: N/A | R43: S/M
A44: 155 | B44: 32.412.497/0001-41 | C44: Benedito José da Silva 08720320868 | D44: MEI | E44: Talita | F44: São Paulo | G44: Isenta | H44: N/A | I44: N/A | L44: N/A | M44: N/A | N44: N/A | O44: N/A | P44: N/A
A45: 351 | B45: 47.407.177/0001-70 | C45: Bepass S.A. | D45: Lucro Real | E45: Talita | F45: São Paulo | G45: 138210963117 | H45: OK | I45: 46253 | J45: OK | K45: 46245 | L45: N/A | M45: N/A | N45: S/M | O45: OK | P45: 46254 | Q45: N/A | R45: N/A | S45: N/A
A46: 510 | B46: 55.769.305/0001-54 | C46: Bianca Ribeiro Mattos Ltda | D46: Simples Nacional | E46: Claudia | F46: São Paulo | G46: Isenta | H46: N/A | I46: N/A | J46: S/M | L46: N/A | M46: N/A | N46: N/A | O46: N/A | P46: N/A | Q46: S/M | R46: S/M
A47: 646 | B47: 67.041.408/0001-82 | C47: Bitachon Serviços Administrativos Ltda | D47: Simples Nacional | E47: Jorge | F47: São Paulo | G47: Isenta | H47: N/A | I47: N/A | L47: N/A | M47: N/A | N47: N/A | O47: N/A | P47: N/A
A48: 542 | B48: 12.107.957/0001-10 | C48: BJ2R Serviços Ltda | D48: Simples Nacional | E48: Kamilly | F48: São Paulo | G48: Isenta | H48: N/A | I48: N/A | J48: S/M | K48: S/M | L48: N/A | M48: N/A | N48: N/A | O48: N/A | P48: N/A | Q48: S/M | R48: S/M | S48: S/M
A49: 240 | B49: 36.557.666/0001-92 | C49: BLGR Serviços Empresariais Ltda | D49: Simples Nacional | E49: Bruna | F49: São Paulo | G49: Isenta | H49: N/A | I49: N/A | J49: S/M | L49: N/A | M49: N/A | N49: N/A | O49: N/A | P49: N/A | Q49: S/M
A50: 486 | B50: 35.048.108/0001-39 | C50: BNC Print Comércio e Soluções Técnicas Ltda | D50: Simples Nacional | E50: Talita | F50: São Paulo | G50: 636400626118 | H50: N/A | I50: N/A | L50: N/A | M50: N/A | N50: N/A | O50: N/A | P50: N/A
A51: 71 | B51: 08.991.576/0001-70 | C51: Botecaria Distribuição e Marketing Ltda | D51: Lucro Presumido | E51: Bruna | F51: São Paulo | G51: 149765136110 | H51: S/M | J51: S/M | L51: S/M | N51: S/M | O51: OK | P51: 46254 | Q51: N/A
A52: 458 | B52: 26.635.239/0001-21 | C52: Brunna Vomstein Andrade | D52: Simples Nacional | E52: Bruna | F52: São Paulo | G52: 636568759110 | H52: N/A | I52: N/A | J52: S/M | L52: N/A | M52: N/A | N52: N/A | O52: N/A | P52: N/A | Q52: S/M | R52: S/M
A53: 122 | B53: 00.833.464/0001-89 | C53: Buffet Israel Ltda | D53: Simples Nacional | E53: Kamilly | F53: São Paulo | G53: 119427678117 | H53: N/A | I53: N/A | J53: S/M | K53: S/M | L53: N/A | M53: N/A | N53: N/A | O53: N/A | P53: N/A | Q53: S/M | R53: S/M | S53: S/M
A54: 499 | B54: 57.262.385/0001-82 | C54: C.M.S. Holding Participações Ltda | D54: Lucro Presumido | E54: Michele | F54: São Paulo | G54: Isenta | H54: N/A | I54: N/A | L54: N/A | M54: N/A | N54: N/A | O54: N/A | Q54: N/A
A55: 435 | B55: 52.796.465/0001-02 | C55: C2C Ltda | D55: Simples Nacional | E55: Luana | F55: Minas Gerais | G55: Isenta | H55: N/A | I55: N/A | J55: S/M | K55: S/M | L55: N/A | M55: N/A | N55: N/A | O55: N/A | P55: N/A | Q55: S/M | R55: S/M | S55: S/M
A56: 591 | B56: 61.256.978/0001-03 | C56: C3C Corretora de Seguros Ltda | D56: Simples Nacional | E56: Luana | F56: Minas Gerais | G56: Isenta | H56: N/A | I56: N/A | J56: S/M | K56: S/M | L56: N/A | M56: N/A | N56: N/A | O56: N/A | P56: N/A | Q56: S/M | R56: S/M | S56: S/M
A57: 419 | B57: 09.666.095/0001-51 | C57: Calcam Comercial de Suprimentos de Informática Ltda | D57: Simples Nacional | E57: Talita | F57: São Paulo | G57: 148185395111 | H57: N/A | I57: N/A | J57: S/M | L57: N/A | M57: N/A | N57: N/A | O57: N/A | P57: N/A | Q57: S/M | R57: S/M
A58: 273 | B58: 41.118.298/0001-16 | C58: Cami Concept Ltda | D58: Simples Nacional | E58: Bruna | F58: São Paulo | G58: Isenta | H58: N/A | I58: N/A | J58: S/M | L58: N/A | M58: N/A | N58: N/A | O58: N/A | P58: N/A | Q58: S/M
A59: 262 | B59: 39.960.783/0001-90 | C59: Capella Comércio e Representações de Produtos Químicos Ltda | D59: Lucro Presumido | E59: Kamilly | F59: São Paulo | G59: 130221210116 | H59: Ok | J59: N/A | L59: N/A | N59: S/M | O59: Ok | Q59: N/A | R59: S/M | S59: S/M
A60: 411 | B60: 51.764.963/0001-00 | C60: Caresma & Schmidt Office Consultoria Empresarial Ltda | D60: Simples Nacional | E60: Bruna | F60: São Paulo | G60: Isenta | H60: N/A | I60: N/A | J60: S/M | L60: N/A | M60: N/A | N60: N/A | O60: N/A | P60: N/A | Q60: S/M
A61: 505 | B61: 57.642.648/0001-89 | C61: Carrilho Donas Sociedade Individual de Advocacia | D61: Simples Nacional | E61: Bruna | F61: Distrito Federal | G61: Isenta | H61: N/A | I61: N/A | J61: S/M | L61: N/A | M61: N/A | N61: N/A | O61: N/A | P61: N/A | Q61: S/M
A62: 495 | B62: 57.121.049/0001-10 | C62: Cass Consultoria Empresarial Ltda | D62: Simples Nacional | E62: Claudia | F62: São Paulo | G62: Isenta | H62: N/A | I62: N/A | J62: S/M | L62: N/A | M62: N/A | N62: N/A | O62: N/A | P62: N/A | Q62: S/M | R62: S/M
A63: 293 | B63: 42.638.806/0001-50 | C63: Catedral Intermediação de Negócios Ltda | D63: Simples Nacional | E63: Claudia | F63: São Paulo | G63: Isenta | H63: N/A | I63: N/A | J63: S/M | L63: N/A | M63: N/A | N63: N/A | O63: N/A | P63: N/A | Q63: S/M | R63: S/M
A64: 335 | B64: 13.574.084/0001-19 | C64: CCKids Comércio e Confecção de Roupas e Acessórios Ltda | D64: Simples Nacional | E64: Luana | F64: São Paulo | G64: 146011920111 | H64: N/A | I64: N/A | J64: S/M | K64: 46245 | L64: N/A | M64: N/A | N64: N/A | O64: N/A | P64: N/A | Q64: S/M | R64: N/A | S64: N/A
A65: 372 | B65: 50.685.261/0001-60 | C65: CDM Holding Ltda | D65: Lucro Presumido | E65: Kamilly | F65: São Paulo | G65: Isenta | H65: N/A | I65: N/A | J65: S/M | K65: S/M | L65: N/A | M65: N/A | N65: N/A | O65: S/M | P65: S/M | Q65: N/A | R65: S/M | S65: S/M
A66: 398 | B66: 03.702.166/0001-48 | C66: Cena Cultural Produções Ltda | D66: Lucro Presumido | E66: Claudia | F66: São Paulo | G66: Isenta | H66: N/A | I66: N/A | J66: S/M | L66: N/A | M66: N/A | N66: N/A | O66: S/M | Q66: N/A | R66: S/M
A67: 321 | B67: 59.650.721/0001-90 | C67: Central Serviços Médicos Ltda | D67: Lucro Presumido | E67: Talita | F67: São Paulo | G67: Isenta | H67: N/A | I67: N/A | J67: S/M | K67: 46245 | L67: N/A | M67: N/A | N67: N/A | O67: S/M | P67: 46246 | Q67: N/A | R67: N/A | S67: N/A
A68: 449 | B68: 10.665.359/0001-31 | C68: Centro de Saúde Animal Zoovet Ltda | D68: Lucro Presumido | E68: Talita | F68: São Paulo | G68: Isenta | H68: N/A | I68: N/A | J68: S/M | K68: 46245 | L68: N/A | M68: N/A | N68: N/A | O68: S/M | P68: 46246 | Q68: N/A | R68: N/A | S68: N/A
A69: 730 | B69: 65.887.267/0001-98 | C69: Chipendalle Arte Móveis Ltda | D69: Simples Nacional | E69: Jorge | F69: São Paulo | G69: Isenta | H69: N/A | I69: N/A | L69: N/A | M69: N/A | N69: N/A | O69: N/A | P69: N/A
A70: 365 | B70: 34.329.315/0001-07 | C70: CJS Comércio Varejista de Tecidos Ltda | D70: Simples Nacional | E70: Bruna | F70: São Paulo | G70: 558510441112 | H70: N/A | I70: N/A | L70: N/A | M70: N/A | N70: N/A | O70: N/A | P70: N/A | Q70: S/M | R70: S/M
A71: 365 (-2) | B71: 34.329.315/0002-80 | C71: CJS Comércio Varejista de Tecidos Ltda | D71: Simples Nacional | E71: Bruna | F71: São Paulo | G71: 127991611111 | H71: N/A | I71: N/A | L71: N/A | M71: N/A | N71: N/A | O71: N/A | P71: N/A
A72: 365 (-3) | B72: 34.329.315/0003-60 | C72: CJS Comércio Varejista de Tecidos Ltda | D72: Simples Nacional | E72: Bruna | F72: São Paulo | G72: 558927031110 | H72: N/A | I72: N/A | L72: N/A | M72: N/A | N72: N/A | O72: N/A | P72: N/A
A73: 408 | B73: 48.292.179/0001-24 | C73: CLE Comunicação Liderança e Educação Ltda | D73: Simples Nacional | E73: Luana | F73: São Paulo | G73: Isenta | H73: N/A | I73: N/A | J73: S/M | K73: 46238 | L73: N/A | M73: N/A | N73: N/A | O73: N/A | P73: N/A | Q73: S/M | R73: S/M | S73: 46238
A74: 402 | B74: 03.754.180/0001-95 | C74: Clínica de Ortopedia Dr. Javier V. S. Vargas Ltda | D74: Lucro Presumido | E74: Kamilly | F74: São Paulo | G74: Isenta | H74: N/A | I74: N/A | J74: S/M | K74: S/M | L74: N/A | M74: N/A | N74: N/A | O74: S/M | P74: S/M | Q74: N/A | R74: S/M | S74: S/M
A75: 393 | B75: 03.541.023/0001-00 | C75: Clínica Dr. Eduardo de Souza Ltda | D75: Lucro Presumido | E75: Luana | F75: São Paulo | G75: Isenta | H75: N/A | I75: N/A | J75: S/M | K75: 46239 | L75: N/A | M75: N/A | N75: N/A | O75: N/A | P75: N/A | Q75: N/A | R75: N/A | S75: N/A
A76: 420 | B76: 52.145.726/0001-16 | C76: Comércio Estético Maison Hair Ltda | D76: Simples Nacional | E76: Jorge | F76: São Paulo | G76: Isenta | H76: N/A | I76: N/A | L76: N/A | M76: N/A | N76: N/A | O76: N/A | P76: N/A
A77: 187 | B77: 34.504.701/0001-80 | C77: Comuniverse Ltda | D77: Lucro Real | E77: Michele | F77: São Paulo | G77: Isenta | H77: N/A | I77: N/A | L77: N/A | M77: N/A | N77: N/A | O77: N/A | Q77: N/A
A78: 476 | B78: 03.951.113/0001-60 | C78: Condor Instituto de Psicologia e Pesquisa SS Ltda | D78: Lucro Presumido | E78: Talita | F78: São Paulo | G78: Isenta | H78: N/A | I78: N/A | J78: S/M | K78: 46245 | L78: N/A | M78: N/A | N78: N/A | O78: S/M | P78: 46246 | Q78: N/A | R78: N/A | S78: N/A
A79: 128 | B79: 06.347.712/0001-68 | C79: Confederação Brasileira de Empresas Juniores | D79: Lucro Real | E79: Kamilly | F79: São Paulo | G79: Isenta | H79: N/A | I79: N/A | J79: S/M | K79: S/M | L79: N/A | M79: N/A | N79: N/A | O79: S/M | P79: S/M | Q79: N/A | R79: S/M | S79: S/M
A80: 590 | B80: 61.158.615/0001-35 | C80: Convox Negócios e Serviços Ltda | D80: Simples Nacional | E80: Talita | F80: São Paulo | G80: Isenta | H80: N/A | I80: N/A | J80: S/M | L80: N/A | M80: N/A | N80: N/A | O80: N/A | P80: N/A | Q80: S/M | R80: S/M
A81: 621 | B81: 42.657.808/0001-96 | C81: Corcovado Investimentos Gestão de Recursos Ltda | D81: Simples Nacional | E81: Michele | F81: Rio de Janeiro | G81: Isenta | H81: N/A | I81: N/A | L81: N/A | M81: N/A | N81: N/A | O81: N/A | P81: N/A
A82: 23 | B82: 45.953.312/0001-58 | C82: Cristal Prime Auto Vidros e Acessórios Ltda | D82: Simples Nacional | E82: Kamilly | F82: São Paulo | G82: 143880591118 | H82: N/A | I82: N/A | J82: S/M | L82: N/A | M82: N/A | N82: N/A | O82: N/A | P82: N/A | Q82: S/M | R82: S/M
A83: 137 | B83: 00.569.062/0001-19 | C83: Cristaltech Auto Vidros e Acessorios Ltda | D83: Lucro Presumido | E83: Kamilly | F83: São Paulo | G83: 114389183119 | H83: N/A | I83: N/A | J83: N/A | K83: N/A | L83: N/A | M83: N/A | N83: N/A | O83: Ok | Q83: N/A | R83: N/A | S83: N/A
A84: 137 (-2) | B84: 00.569.062/0002-08 | C84: Cristaltech Auto Vidros e Acessorios Ltda | D84: Lucro Presumido | E84: Kamilly | F84: São Paulo | G84: 635779950110 | H84: N/A | I84: N/A | J84: N/A | K84: N/A | L84: N/A | M84: N/A | N84: N/A | O84: Ok | Q84: N/A | R84: N/A | S84: N/A
A85: 494 | B85: 56.778.834/0001-87 | C85: Croce Simões Holding Ltda | D85: Lucro Presumido | E85: Michele | F85: São Paulo | G85: Isenta | H85: N/A | I85: N/A | L85: N/A | M85: N/A | N85: N/A | O85: N/A | Q85: N/A
A86: 308 | B86: 18.587.752/0001-66 | C86: Crysthiane Henrique de Matos Gonçalves Tripode | D86: MEI | E86: Michele | F86: São Paulo | G86: 142641496112 | H86: N/A | I86: N/A | J86: S/M | K86: 46237 | L86: N/A | M86: N/A | N86: N/A | O86: N/A | P86: N/A | Q86: S/M | R86: S/M | S86: 46237
A87: 557 | B87: 39.940.308/0001-52 | C87: Dataind Tecnologia de Informação Ltda | D87: Lucro Real | E87: Jorge | F87: São Paulo | G87: Isenta | H87: N/A | I87: N/A | J87: S/M | L87: N/A | M87: N/A | N87: N/A | O87: N/A | P87: N/A | Q87: N/A | R87: N/A | S87: N/A
A88: 181 | B88: 00.575.747/0001-78 | C88: Davos Consult Serviços de Apoio Empresarial Ltda | D88: Simples Nacional | E88: Jorge | F88: São Paulo | G88: 708378532111 | H88: N/A | I88: N/A | L88: N/A | M88: N/A | N88: N/A | O88: N/A | P88: N/A
A89: 272 | B89: 40.915.081/0001-74 | C89: DBM Consultoria e Participações Ltda | D89: Simples Nacional | E89: Claudia | F89: São Paulo | G89: Isenta | H89: N/A | I89: N/A | J89: S/M | L89: N/A | M89: N/A | N89: N/A | O89: N/A | P89: N/A | Q89: S/M | R89: S/M
A90: 367 | B90: 50.231.188/0001-57 | C90: Decor Adesivos e Decoração Ltda | D90: Simples Nacional | E90: Talita | F90: São Paulo | G90: 138939616118 | H90: N/A | I90: N/A | L90: N/A | M90: N/A | N90: N/A | O90: N/A | P90: N/A
A91: 254 | B91: 27.532.933/0001-86 | C91: Decor Revestimentos Adesivos Ltda | D91: Simples Nacional | E91: Talita | F91: São Paulo | G91: 141959492111 | H91: N/A | I91: N/A | L91: N/A | M91: N/A | N91: N/A | O91: N/A | P91: N/A
A92: 6 | B92: 16.952.792/0001-34 | C92: Delta Geradores Ltda | D92: Simples Nacional | E92: Jorge | F92: São Paulo | G92: Isenta | H92: N/A | I92: N/A | L92: N/A | M92: N/A | N92: N/A | O92: N/A | P92: N/A
A93: 113 | B93: 27.372.837/0001-18 | C93: Delta Suporte em Vendas Ltda | D93: Simples Nacional | E93: Claudia | F93: São Paulo | G93: Isenta | H93: N/A | I93: N/A | J93: S/M | L93: N/A | M93: N/A | N93: N/A | O93: N/A | P93: N/A | Q93: S/M | R93: S/M
A94: 145 | B94: 31.496.077/0001-28 | C94: Denis Calazans Cordeiro | D94: Simples Nacional | E94: Luana | F94: São Paulo | G94: 119966904110 | H94: N/A | I94: N/A | J94: S/M | K94: 46252 | L94: N/A | M94: N/A | N94: N/A | O94: N/A | P94: N/A | Q94: S/M | R94: N/A | S94: N/A
A95: 640 | B95: 33.032.171/0001-51 | C95: DHM Engenharia Ltda | D95: Lucro Presumido | E95: Talita | F95: Pernambuco | G95: Isenta | H95: N/A | I95: N/A | J95: S/M | K95: 46245 | L95: N/A | M95: N/A | N95: N/A | O95: S/M | P95: 46246 | Q95: N/A | R95: N/A | S95: N/A
A96: 103 | B96: 26.025.480/0001-39 | C96: Diógenes Prado Batista Sociedade Individual de Advocacia | D96: Simples Nacional | E96: Jorge | F96: São Paulo | G96: Isenta | H96: N/A | I96: N/A | L96: N/A | M96: N/A | N96: N/A | O96: N/A | P96: N/A
A97: 550 | B97: 12.591.454/0001-63 | C97: Direct Advice Serviços Empresariais Ltda | D97: Lucro Presumido | E97: Bruna | F97: São Paulo | G97: Isenta | H97: N/A | I97: N/A | L97: N/A | M97: N/A | N97: N/A | O97: S/M | Q97: N/A
A98: 169 | B98: 14.627.752/0001-91 | C98: Direction Solução em Serviços Administrativos Ltda | D98: Simples Nacional | E98: Bruna | F98: São Paulo | G98: Isenta | H98: N/A | I98: N/A | J98: S/M | L98: N/A | M98: N/A | N98: N/A | O98: N/A | P98: N/A | Q98: S/M
A99: 643 | B99: 66.673.761/0001-12 | C99: DLS Serviços de Tecnologia Ltda | D99: Simples Nacional | E99: Kamilly | F99: São Paulo | G99: 159659366117 | H99: N/A | I99: N/A | J99: S/M | K99: S/M | L99: N/A | M99: N/A | N99: N/A | O99: N/A | P99: N/A | Q99: S/M | R99: S/M | S99: S/M
A100: 585 | B100: 61.054.759/0001-41 | C100: Doces da Lu Lu Ltda | D100: Simples Nacional | E100: Claudia | F100: São Paulo | G100: 154244707118 | H100: N/A | I100: N/A | J100: S/M | L100: N/A | M100: N/A | N100: N/A | O100: N/A | P100: N/A | Q100: S/M | R100: S/M
...

Sheet Federais
A1: Código | B1: CNPJ | C1: Razão Social | D1: Inscrição Estadual | E1: Tributação | F1: Usuário | G1: Darfs Retidos | I1: Darfs CPRB | K1: EFD-Reinf 2000 | L1: EFD-Reinf 4000 | M1: Aluguel | N1: Convênio Médico | O1: DIRBI | P1: DAS | R1: Darfs PisCofins | T1: Darfs IrpjCsll | V1: EFD Contribuições | X1: MIT | Y1: DCTFWeb | AA1: Parc Federais | AC1: Conferência
A2: 106 | B2: =VLOOKUP(A2,Empresas!A:B,2,0) -> 04.431.460/0001-25 | C2: =VLOOKUP(B2,Empresas!B:C,2,0) -> 04.431.460 Ramiro Duenas Aranzabal | D2: =VLOOKUP(A2,Empresas!A:E,5,0) -> 116270616110 | E2: =VLOOKUP(A2,Empresas!A:D,4,0) -> MEI | F2: =VLOOKUP(A2,Empresas!A:J,10,0) -> Jorge | G2: N/A | H2: N/A | I2: N/A | J2: N/A | K2: OK | L2: S/M | M2: S/M | N2: S/M | O2: N/A | P2: OK | Q2: 46239 | R2: N/A | S2: N/A | T2: N/A | U2: N/A | V2: N/A | W2: N/A | X2: N/A | Y2: OK | Z2: 46238 | AA2: OK | AB2: 46255
A3: 119 | B3: 27.541.980/0001-96 | C3: 4.Com Serviços Empresariais Ltda | D3: Isenta | E3: Simples Nacional | F3: Jorge | G3: N/A | H3: N/A | I3: N/A | J3: N/A | K3: S/M | L3: S/M | M3: S/M | N3: S/M | O3: N/A | P3: OK | Q3: 46248 | R3: N/A | S3: N/A | T3: N/A | U3: N/A | V3: N/A | W3: N/A | X3: N/A
A4: 415 | B4: 42.360.609/0001-11 | C4: 42.360.609 Dener Mendonça de Souza | D4: Isenta | E4: MEI | F4: Jorge | G4: N/A | H4: N/A | I4: N/A | J4: N/A | K4: OK | L4: S/M | M4: S/M | N4: S/M | O4: N/A | P4: OK | Q4: 46239 | R4: N/A | S4: N/A | T4: N/A | U4: N/A | V4: N/A | W4: N/A | X4: N/A
A5: 218 | B5: 43.436.474/0001-93 | C5: 43.436.474 Maria Clara Tomé Garcia | D5: 799468637111 | E5: MEI | F5: Jorge | G5: N/A | H5: N/A | I5: N/A | J5: N/A | K5: S/M | L5: S/M | M5: S/M | N5: S/M | O5: N/A | P5: N/A | Q5: 46239 | R5: N/A | S5: N/A | T5: N/A | U5: N/A | V5: N/A | W5: N/A | X5: N/A
A6: 628 | B6: 43.959.791/0001-94 | C6: 43.959.791 Ana Isabela Pithan Maraschin | D6: 133256510113 | E6: MEI | F6: Jorge | G6: N/A | H6: N/A | I6: N/A | J6: N/A | K6: OK | L6: S/M | M6: S/M | N6: S/M | O6: N/A | P6: OK | Q6: 46239 | R6: N/A | S6: N/A | T6: N/A | U6: N/A | V6: N/A | W6: N/A | X6: N/A
A7: 227 | B7: 44.645.259/0001-65 | C7: 44.645.259 Rebeca Brito Cardoso | D7: Isenta | E7: MEI | F7: Jorge | G7: N/A | H7: N/A | I7: N/A | J7: N/A | K7: OK | L7: S/M | M7: S/M | N7: S/M | O7: N/A | P7: OK | Q7: 46239 | R7: N/A | S7: N/A | T7: N/A | U7: N/A | V7: N/A | W7: N/A | X7: N/A
A8: 359 | B8: 04.362.429/0001-80 | C8: 4CS Serviços Ltda | D8: Isenta | E8: Simples Nacional | F8: Paulo | G8: N/A | H8: N/A | J8: N/A | K8: S/M | L8: S/M | P8: OK | Q8: 46244 | R8: N/A | S8: N/A | T8: N/A | U8: N/A | V8: N/A | W8: N/A
A9: 638 | B9: 51.957.545/0001-21 | C9: 51.957.545 Marjorie Abdallah | D9: Isenta | E9: Simples Nacional | F9: Bruna | G9: N/A | H9: N/A | I9: N/A | J9: N/A | K9: S/M | L9: OK | M9: N/A | N9: N/A | O9: N/A | P9: OK | Q9: 46238 | R9: N/A | S9: N/A | T9: N/A | U9: N/A | V9: N/A | W9: N/A | X9: N/A | Y9: OK | Z9: 46238 | AA9: OK | AB9: 46244
A10: 437 | B10: 53.494.930/0001-05 | C10: 53.494.930 Gabriela Afonso Prado | D10: Isenta | E10: MEI | F10: Jorge | G10: N/A | H10: N/A | I10: N/A | J10: N/A | K10: OK | L10: S/M | M10: S/M | N10: S/M | O10: N/A | P10: OK | Q10: 46239 | R10: N/A | S10: N/A | T10: N/A | U10: N/A | V10: N/A | W10: N/A | X10: N/A
A11: 461 | B11: 54.535.015/0001-83 | C11: Ada Maria Fraulo Pires | D11: 135862064112 | E11: Simples Nacional | F11: Bruna | G11: N/A | H11: N/A | I11: S/M | K11: S/M | L11: OK | M11: N/A | N11: N/A | O11: N/A | P11: OK | Q11: 46244 | R11: N/A | S11: N/A | T11: N/A | U11: N/A | V11: N/A | W11: N/A | X11: N/A | Y11: OK | Z11: 46244 | AA11: OK | AB11: 46244
A12: 525 | B12: 58.344.129/0001-05 | C12: 58.344.129 Gilda Maria de Lima Roberto | D12: 151811726114 | E12: MEI | F12: Jorge | G12: N/A | H12: N/A | I12: N/A | J12: N/A | K12: OK | L12: S/M | M12: S/M | N12: S/M | O12: N/A | P12: OK | Q12: 46239 | R12: N/A | S12: N/A | T12: N/A | U12: N/A | V12: N/A | W12: N/A | X12: N/A
A13: 608 | B13: 13.581.219/0001-73 | C13: A & V Marques Imóveis Ltda | D13: Isenta | E13: Simples Nacional | F13: Talita | G13: N/A | I13: N/A | K13: S/M | L13: OK | M13: N/A | N13: N/A | O13: N/A | P13: OK | Q13: 46238 | R13: N/A | S13: N/A | T13: N/A | U13: N/A | V13: N/A | W13: N/A | X13: N/A
A14: 34 | B14: 22.189.167/0001-85 | C14: A Galeria Artes Presentes Jóias Design Rocym Ltda | D14: 128248912111 | E14: Simples Nacional | F14: Jorge | G14: N/A | H14: N/A | I14: N/A | J14: N/A | K14: OK | L14: S/M | M14: S/M | N14: S/M | O14: N/A | P14: S/M | Q14: 46239 | R14: N/A | S14: N/A | T14: N/A | U14: N/A | V14: N/A | W14: N/A | X14: N/A
A15: 523 | B15: 11.360.241/0001-68 | C15: A. de S. Cafcalas | D15: Isenta | E15: Simples Nacional | F15: Claudia | G15: N/A | H15: N/A | I15: S/M | J15: N/A | K15: OK | L15: S/M | M15: N/A | N15: N/A | O15: N/A | P15: OK | Q15: 46238 | R15: N/A | S15: N/A | T15: N/A | U15: N/A | V15: N/A | W15: N/A | X15: N/A | Y15: OK | Z15: 46247 | AA15: Ok | AB15: 46247
A16: 587 | B16: 61.203.201/0001-80 | C16: A2M Ltda | D16: Isenta | E16: Lucro Presumido | F16: Luana | I16: N/A | J16: N/A | K16: OK | L16: OK | M16: N/A | N16: N/A | O16: N/A | P16: N/A | Q16: N/A | R16: S/M | S16: 46245 | T16: S/M | U16: 46245 | V16: OK | W16: 46245 | X16: OK | AA16: N/A | AB16: N/A
A17: 225 | B17: 04.438.239/0001-07 | C17: AGM Representações Comerciais Ltda | D17: Isenta | E17: Lucro Presumido | F17: Talita | G17: N/A | H17: 46247 | I17: N/A | K17: S/M | L17: N/A | M17: N/A | N17: N/A | O17: N/A | P17: N/A | Q17: N/A | R17: OK | S17: 46255 | T17: N/A | U17: 46244 | V17: OK | W17: 46255 | X17: OK | Y17: OK | Z17: 46255 | AA17: N/A
A18: 572 | B18: 44.114.755/0001-92 | C18: AGR Tubos Conexões e Válvulas Ltda | D18: 636583794113 | E18: Simples Nacional | F18: Michele | G18: OK | H18: OK | I18: N/A | J18: N/A | K18: S/M | L18: OK | M18: N/A | N18: N/A | O18: N/A | P18: S/M | Q18: 46240 | R18: N/A | S18: N/A | T18: N/A | U18: N/A | V18: N/A | W18: N/A | X18: N/A | Y18: OK | Z18: 46240
A19: 597 | B19: 33.023.255/0001-29 | C19: Alan W de O Lima Tecnologia da Informação | D19: Isenta | E19: Simples Nacional | F19: Kamilly | G19: N/A | H19: N/A | I19: N/A | J19: N/A | K19: Ok | L19: Ok | M19: N/A | N19: OK | O19: N/A | P19: Ok | R19: N/A | S19: N/A | T19: N/A | U19: N/A | V19: N/A | W19: N/A
A20: 617 | B20: 58.717.889/0001-02 | C20: Ale Holding Participações e Negócios Ltda | D20: 152218550110 | E20: Lucro Presumido | F20: Luana | G20: N/A | I20: N/A | J20: N/A | K20: OK | L20: S/M | M20: N/A | N20: N/A | O20: N/A | P20: N/A | Q20: N/A | R20: S/M | T20: S/M | V20: OK | W20: 46238 | X20: OK | Y20: OK | Z20: 46238 | AA20: - | AB20: -
A21: 303 | B21: 02.864.188/0001-41 | C21: Alexandre Sgreccia | D21: Isenta | E21: Simples Nacional | F21: Luana | G21: N/A | H21: N/A | I21: N/A | J21: N/A | K21: OK | L21: OK | M21: N/A | N21: N/A | O21: N/A | P21: OK | Q21: 46241 | R21: N/A | S21: N/A | T21: N/A | U21: N/A | V21: N/A | W21: N/A | X21: N/A | Y21: OK | Z21: 46241 | AA21: OK | AB21: 46255
A22: 230 | B22: 04.746.127/0001-05 | C22: Alexandre Silva Voza | D22: 149989327117 | E22: Simples Nacional | F22: Michele | G22: N/A | H22: N/A | I22: N/A | K22: S/M | L22: OK | M22: N/A | N22: N/A | O22: N/A | P22: Ok | Q22: 46238 | R22: N/A | S22: N/A | T22: N/A | U22: N/A | V22: N/A | W22: N/A | X22: N/A | Y22: OK | Z22: 46241
A23: 370 | B23: 37.140.411/0001-92 | C23: Allora Construtora e Incorporadora Ltda | D23: 128936605119 | E23: Lucro Presumido | F23: Kamilly | G23: Ok | I23: N/A | J23: N/A | K23: Ok | L23: Ok | M23: Ok | N23: N/A | O23: N/A | P23: N/A | Q23: N/A | R23: Ok | T23: N/A | U23: N/A | X23: Ok | AA23: N/A | AB23: N/A
A24: 578 | B24: 13.314.231/0001-11 | C24: Alpha Entretenimento e Lazer Ltda | D24: 403008716119 | E24: Simples Nacional | F24: Talita | G24: N/A | H24: N/A | I24: N/A | K24: S/M | L24: S/M | M24: N/A | N24: N/A | O24: N/A | P24: S/M | R24: N/A | S24: N/A | T24: N/A | U24: N/A | V24: N/A | W24: N/A | X24: N/A | AA24: N/A
A25: 302 | B25: 01.665.434/0001-73 | C25: Alphaville Comercial Ltda | D25: 114726418111 | E25: Simples Nacional | F25: Luana | G25: N/A | H25: OK | I25: N/A | J25: N/A | K25: OK | L25: OK | M25: N/A | N25: N/A | O25: N/A | P25: OK | Q25: 46248 | R25: N/A | S25: N/A | T25: N/A | U25: N/A | V25: N/A | W25: N/A | X25: N/A | Y25: OK | Z25: 46248 | AA25: N/A | AB25: N/A
A26: 376 | B26: 09.086.104/0001-35 | C26: Américo Suriano e Companhia Ltda | D26: 149817697113 | E26: Simples Nacional | F26: Michele | G26: N/A | H26: N/A | I26: N/A | K26: S/M | L26: OK | M26: N/A | N26: N/A | O26: N/A | P26: OK | Q26: 46246 | R26: N/A | S26: N/A | T26: N/A | U26: N/A | V26: N/A | W26: N/A | X26: N/A | Y26: OK | Z26: 46246
A27: 576 | B27: 49.343.692/0001-60 | C27: Ápice Artes Gráficas Ltda | D27: 636070583117 | E27: Lucro Real | F27: Paulo | G27: OK | H27: 46247 | I27: OK | J27: 46247 | K27: OK | L27: OK | P27: N/A | Q27: N/A | R27: OK | S27: 46248
A28: 61 | B28: 03.338.180/0001-04 | C28: Aprobato Neto Contabilidade e Apoio Empresarial Ltda | D28: Isenta | E28: Simples Nacional | F28: Paulo | G28: OK | H28: OK | I28: OK | K28: S/M | L28: S/M | P28: OK | Q28: 46246 | R28: N/A | S28: N/A | T28: N/A | U28: N/A | V28: N/A | W28: N/A
A29: 972 | B29: 00.000.904/0001-17 | C29: Aprobato Neto Perícias Técnicas Ltda | D29: Isenta | E29: Simples Nacional | F29: Paulo | G29: N/A | H29: N/A | K29: S/M | L29: S/M | P29: OK | Q29: 46246 | R29: N/A | S29: N/A | T29: N/A | U29: N/A | V29: N/A | W29: N/A
A30: 972 (-2) | B30: 00.000.904/0002-06 | C30: Aprobato Neto Perícias Técnicas Ltda | D30: Isenta | E30: Simples Nacional | F30: Paulo | G30: N/A | H30: N/A | K30: S/M | L30: S/M | P30: S/M | R30: N/A | S30: N/A | T30: N/A | U30: N/A | V30: N/A | W30: N/A
A31: 440 | B31: 71.912.349/0001-48 | C31: Arakaki Enterprise Ltda | D31: 135658787115 | E31: Lucro Presumido | F31: Talita | G31: S/M | H31: 46247 | I31: N/A | K31: OK | L31: OK | M31: OK | N31: OK | O31: OK | P31: N/A | Q31: N/A | R31: OK | S31: 46247 | T31: S/M | U31: 46246 | V31: OK | W31: 46255 | X31: OK | Y31: OK | Z31: 46255 | AA31: N/A
A32: 18 | B32: 61.094.660/0001-73 | C32: Aramfactor Utilidades em Arames Ltda | D32: 112425660117 | E32: Lucro Presumido | F32: Talita | G32: S/M | H32: 46240 | I32: N/A | K32: S/M | L32: OK | M32: N/A | N32: N/A | O32: N/A | P32: N/A | Q32: N/A | R32: OK | S32: 46254 | T32: S/M | U32: 46246 | V32: OK | W32: 46255 | X32: OK | Y32: OK | Z32: 46255 | AA32: N/A
A33: 127 | B33: 02.400.369/0001-17 | C33: Associação Brasileira de Wakeboard | D33: Isenta | E33: Lucro Real | F33: Jorge | G33: N/A | H33: N/A | I33: N/A | J33: N/A | K33: OK | L33: S/M | M33: N/A | N33: N/A | O33: N/A | P33: N/A | Q33: N/A | R33: S/M | S33: S/M | T33: S/M | U33: S/M | V33: OK | W33: 46239 | X33: OK | Y33: OK | Z33: 46239 | AA33: N/A | AB33: N/A
A34: 208 | B34: 07.010.849/0001-95 | C34: Associação dos Serv e Magis Para Manut do Berçário do TRT da 2 Região | D34: Isenta | E34: Lucro Real | F34: Jorge | G34: N/A | H34: N/A | I34: N/A | J34: N/A | K34: OK | L34: S/M | M34: N/A | N34: N/A | O34: N/A | P34: N/A | Q34: N/A | R34: S/M | S34: S/M | T34: S/M | U34: S/M | V34: OK | W34: 46239 | X34: OK | Y34: OK | Z34: 46239 | AA34: N/A | AB34: N/A
A35: 175 | B35: 39.563.909/0001-93 | C35: Assunção Antunes Corretora de Seguros Ltda | D35: Isenta | E35: Simples Nacional | F35: Luana | G35: N/A | H35: N/A | I35: N/A | J35: N/A | K35: OK | L35: OK | M35: N/A | N35: N/A | O35: N/A | P35: OK | Q35: 46240 | R35: N/A | S35: N/A | T35: N/A | U35: N/A | V35: N/A | W35: N/A | X35: N/A | Y35: OK | Z35: 46240 | AA35: N/A | AB35: N/A
A36: 594 | B36: 61.633.486/0001-90 | C36: Astra Tecnologia Ltda | D36: Isenta | E36: Simples Nacional | F36: Claudia | G36: OK | I36: N/A | J36: N/A | K36: OK | L36: OK | M36: N/A | N36: N/A | O36: N/A | P36: OK | Q36: 46241 | R36: N/A | S36: N/A | T36: N/A | U36: N/A | V36: N/A | W36: N/A | X36: N/A | AA36: N/A
